Workbook
Name Departments: "GE,IT,ENG,BM,HRM,THM,AS"
Name SHS1FIELD: '[1]3.3 - SHS Term 1 '!$E$4:$E$255
Name SHS1FIELD: '[2]3.3 - SHS Term 1 '!$E$4:$E$255
Name SHS1FIELD: '3.3 - SHS Term 1 '!$E$3:$E$254
Name SHS1LOAD: '[1]3.3 - SHS Term 1 '!$I$4:$I$255
Name SHS1LOAD: '[2]3.3 - SHS Term 1 '!$I$4:$I$255
Name SHS1LOAD: '3.3 - SHS Term 1 '!$I$3:$I$254
Name SHS2FIELD: '[1]3.4 - SHS Term 2'!$E$4:$E$255
Name SHS2FIELD: '[2]3.4 - SHS Term 2'!$E$4:$E$255
Name SHS2FIELD: '3.4 - SHS Term 2'!$E$3:$E$254
Name SHS2LOAD: '[3]3.4 - SHS Term 2'!$I$4:$I$255
Name SHS2LOAD: '[1]3.4 - SHS Term 2'!$I$4:$I$255
Name SHS2LOAD: '[1]3.4 - SHS Term 2'!$I$4:$I$255
Name SHS2LOAD: '[2]3.4 - SHS Term 2'!$I$4:$I$255
Name SHS2LOAD: '3.4 - SHS Term 2'!$I$3:$I$254
Name TER1FIELD: '[1]3.1 - Tertiary - Term 1'!$E$4:$E$653
Name TER1FIELD: '[2]3.1 - Tertiary - Term 1'!$E$4:$E$653
Name TER1FIELD: '3.1 - Tertiary - Term 1'!$E$3:$E$659
Name TER1LOAD: '[1]3.1 - Tertiary - Term 1'!$J$4:$J$653
Name TER1LOAD: '[2]3.1 - Tertiary - Term 1'!$J$4:$J$653
Name TER1LOAD: '3.1 - Tertiary - Term 1'!$J$3:$J$659
Name TER2FIELD: '[1]3.2 - Tertiary - Term 2'!$E$4:$E$571
Name TER2FIELD: '[1]3.2 - Tertiary - Term 2'!$E$4:$E$571
Name TER2FIELD: '[2]3.2 - Tertiary - Term 2'!$E$4:$E$571
Name TER2FIELD: '3.2 - Tertiary - Term 2'!$E$3:$E$588
Name TER2LOAD: '[3]3.2 - Tertiary - Term 2'!$J$4:$J$571
Name TER2LOAD: '[1]3.2 - Tertiary - Term 2'!$J$4:$J$571
Name TER2LOAD: '[1]3.2 - Tertiary - Term 2'!$J$4:$J$571
Name TER2LOAD: '[2]3.2 - Tertiary - Term 2'!$J$4:$J$571
Name TER2LOAD: '3.2 - Tertiary - Term 2'!$J$3:$J$588
Name ThuRooms: [1]THURSDAY!$C$4:$BK$31
Name Thursday: [1]THURSDAY!$C$3:$BK$3
Name TIME: '[3]<Day 1>'!$A$4:$A$31
Name TIME: [1]MONDAY!$A$4:$A$31
Name TIME: [1]MONDAY!$A$4:$A$31
Name TIME: FRIDAY!$A$4:$A$31
Name TIME: [2]MONDAY!$A$4:$A$31
Name TIME: SATURDAY!$A$4:$A$31
Name TIME: THURSDAY!$A$4:$A$31
Name TIME: TUESDAY!$A$4:$A$31
Name TIME: WEDNESDAY!$A$4:$A$31
Name TIME: MONDAY!$A$4:$A$31
Name TueRooms: [1]TUESDAY!$C$4:$BK$31
Name Tuesday: [1]TUESDAY!$C$3:$BK$3
Name Wednesday: [1]WEDNESDAY!$C$3:$BK$3
Name WedRooms: [1]WEDNESDAY!$C$4:$BK$31

Sheet 1 - Top Sheet
B6: STI | D6: Novaliches | F6: <-- indicate Campus
B7: School Year | D7: 2024-2025 | F7: <-- indicate School Year
B8: Term | D8: 1 | F8: <-- indicate Term
B10: Section Count Projection | H10: Projected Faculty Count: Tertiary | N10: Projected Faculty Count: High School | T10: Room Projections
D12: Class Density | E12: Projected NS/OS | F12: Section Count | K12: Full-time FM | L12: Excess Units | Q12: Full-time FM | R12: Excess Units | T12: Lecture Rooms
B13: Highschool | D13: ='2 - Section Count Projection'!D5 -> 40 | E13: ='2 - Section Count Projection'!F71 -> 0 | F13: ='2 - Section Count Projection'!G71 -> 0 | H13: Information & Communication Tech. | K13: ='Faculty Count Projection'!E14+'Faculty Count Projection'!E16+'Faculty Count Projection'!E20 -> 16 | L13: ='Faculty Count Projection'!F14+'Faculty Count Projection'!F16+'Faculty Count Projection'!F20 -> 18.5 | N13: Business and Management | Q13: ='Faculty Count Projection'!K9 -> 1 | R13: ='Faculty Count Projection'!L9 -> 12
B14: 4-Year Degree | D14: ='2 - Section Count Projection'!L5 -> 40 | E14: ='2 - Section Count Projection'!N162 -> 0 | F14: ='2 - Section Count Projection'!O162 -> 0 | H14: Business and Management | K14: ='Faculty Count Projection'!E9+'Faculty Count Projection'!E11+'Faculty Count Projection'!E21 -> 1 | L14: ='Faculty Count Projection'!F9+'Faculty Count Projection'!F11+'Faculty Count Projection'!F21 -> 4.5 | N14: Electrical/Electronics | Q14: ='Faculty Count Projection'!K10 -> 0 | R14: ='Faculty Count Projection'!L10 -> 0 | T14: Available Lecture Sessions | V14: ='Room Utilization Efficiency'!$I$51 -> 2808
B15: 2-Year Degree | D15: ='2 - Section Count Projection'!D75 -> 0 | E15: ='2 - Section Count Projection'!F107 -> 0 | F15: ='2 - Section Count Projection'!G107 -> 0 | H15: Tourism & Hospitality Management | K15: ='Faculty Count Projection'!E19+'Faculty Count Projection'!E29 -> 4 | L15: ='Faculty Count Projection'!F19+'Faculty Count Projection'!F29 -> 18 | N15: English | Q15: ='Faculty Count Projection'!K11 -> 6 | R15: ='Faculty Count Projection'!L11 -> 6 | T15: Projected Lecture Sessions | V15: ='Room Utilization Efficiency'!$I$52 -> 973
F16: =SUM(F13:F15) -> 0 | H16: General Education | K16: ='Faculty Count Projection'!E10+'Faculty Count Projection'!E12+'Faculty Count Projection'!E15+'Faculty Count Projection'!E17+'Faculty Count Projection'!E18+'Faculty Count Projection'!E22+'Faculty Count Projection'!E25+'Faculty Count Projection'!E26+'Faculty Count Projection'!E27+'Faculty Count Projection'!E28 -> 14 | L16: ='Faculty Count Projection'!F10+'Faculty Count Projection'!F12+'Faculty Count Projection'!F15+'Faculty Count Projection'!F17+'Faculty Count Projection'!F18+'Faculty Count Projection'!F22+'Faculty Count Projection'!F25+'Faculty Count Projection'!F26+'Faculty Count Projection'!F27+'Faculty Count Projection'!F28 -> 53 | N16: Filipino | Q16: ='Faculty Count Projection'!K12 -> 3 | R16: ='Faculty Count Projection'!L12 -> 21
H17: Arts & Sciences | K17: ='Faculty Count Projection'!E23 -> 6 | L17: ='Faculty Count Projection'!F23 -> 9.5 | N17: Hospitality/Culinary Mgt | Q17: ='Faculty Count Projection'!K13 -> 0 | R17: ='Faculty Count Projection'!L13 -> 24 | T17: Computer Laboratory
K18: =SUM(K13:K17) -> 41 | L18: =SUM(L13:L17) -> 103.5 | N18: Information Technology | Q18: ='Faculty Count Projection'!K14 -> 1 | R18: ='Faculty Count Projection'!L14 -> 9
I19: *For a more detailed breakdown refer to the faculty count projection sheet | N19: Mathematics | Q19: ='Faculty Count Projection'!K15 -> 3 | R19: ='Faculty Count Projection'!L15 -> 12 | T19: Available Lab Sessions | V19: ='5 - Computer Lab'!$L$4 -> 120
N20: Physical Education | Q20: ='Faculty Count Projection'!K16 -> 4 | R20: ='Faculty Count Projection'!L16 -> 21 | T20: Projected Lab Sessions | V20: ='5 - Computer Lab'!$L$6 -> 205
N21: Sciences | Q21: ='Faculty Count Projection'!K17 -> 4 | R21: ='Faculty Count Projection'!L17 -> 6
N22: Social and Behavioral Sciences | Q22: ='Faculty Count Projection'!K18 -> 7 | R22: ='Faculty Count Projection'!L18 -> 18 | T22: Culinary Laboratory
N23: Tourism Management | Q23: ='Faculty Count Projection'!K19 -> 0 | R23: ='Faculty Count Projection'!L19 -> 24
Q24: =SUM(Q13:Q23) -> 29 | R24: =SUM(R13:R23) -> 153 | T24: Available Lab Sessions | V24: ='6 - Culinary Lab '!$L$4 -> 0
T25: Projected Lab Sessions | V25: ='6 - Culinary Lab '!$L$6 -> 0
T27: Room Utilization
T29: Lecture Rooms | V29: ='Room Utilization Efficiency'!$I$50 -> 1
T30: Laboratories | V30: ='Room Utilization Efficiency'!$R$19 -> 1

Sheet 2 - Section Count Projection
B1: =_xlfn.CONCAT("STI College ",'1 - Top Sheet'!D6:E6) -> STI College Novaliches
B2: Section Count Projection
B3: =_xlfn.CONCAT("School Year ",'1 - Top Sheet'!D7:E7," Term ", '1 - Top Sheet'!D8:E8) -> School Year 2024-2025 Term 1
B4: High School Programs | J4: 4-Year Degree Programs
C5: Class Density | D5: 40 | K5: Class Density | L5: 40
B7: Instruction: Fill-out only the GREEN cells
E8: =B3 -> School Year 2024-2025 Term 1 | M8: =B3 -> School Year 2024-2025 Term 1
B9: Track / Strand | C9: Year Level Term | D9: Current OGS | E9: Year Level Term | F9: Projected NS /OS | G9: Section Count | H9: Remarks | J9: Program | K9: Year Level Term | L9: Current OS | M9: Year Level Term | N9: Projected NS / OS | O9: Section Count | P9: Remarks
B11: Junior High School | C11: 7 | G11: =IF($D$5=0,0,IF(AND(F11>0,F11-$D$5<6),ROUNDUP((F11-5)/$D$5,0),ROUNDUP(F11/$D$5,0))) -> 0 | H11: =IF(AND(F11<$D$5,F11>0),"can be merged","") | J11: BS in Information Techology (BSIT) | K11: 1-1 | M11: 1-1 | O11: =IF($L$5=0,0,IF(AND(N11>0,N11-$L$5<6),ROUNDUP((N11-5)/$L$5,0),ROUNDUP(N11/$L$5,0))) -> 0 | P11: =IF(AND(N11<$L$5,N11>0),"can be merged","")
B12: Retention Rate: | C12: 8 | E12: 8 | F12: =ROUNDUP((F11*$B$13)*$B$15,0) -> 0 | G12: =IF($D$5=0,0,IF(AND(F12>0,F12-$D$5<6),ROUNDUP((F12-5)/$D$5,0),ROUNDUP(F12/$D$5,0))) -> 0 | H12: =IF(AND(F12<$D$5,F12>0),"can be merged","") | K12: 1-2 | M12: 1-2 | N12: =IF(L11<>"",ROUNDUP((L11*$J$15)*$J$17,0),0) -> 0 | O12: =IF($L$5=0,0,IF(AND(N12>0,N12-$L$5<6),ROUNDUP((N12-5)/$L$5,0),ROUNDUP(N12/$L$5,0))) -> 0 | P12: =IF(AND(N12<$L$5,N12>0),"can be merged","")
C13: 9 | E13: 9 | F13: =ROUNDUP((D12*$B$13)*$B$15,0) -> 0 | G13: =IF($D$5=0,0,IF(AND(F13>0,F13-$D$5<6),ROUNDUP((F13-5)/$D$5,0),ROUNDUP(F13/$D$5,0))) -> 0 | H13: =IF(AND(F13<$D$5,F13>0),"can be merged","") | K13: 2-1 | M13: 2-1 | N13: =IF(L12<>"",ROUNDUP((L12*$J$15)*$J$17,0),0) -> 0 | O13: =IF($L$5=0,0,IF(AND(N13>0,N13-$L$5<6),ROUNDUP((N13-5)/$L$5,0),ROUNDUP(N13/$L$5,0))) -> 0 | P13: =IF(AND(N13<$L$5,N13>0),"can be merged","")
B14: Migration Rate: | C14: 10 | E14: 10 | F14: =ROUNDUP((D13*$B$13)*$B$15,0) -> 0 | G14: =IF($D$5=0,0,IF(AND(F14>0,F14-$D$5<6),ROUNDUP((F14-5)/$D$5,0),ROUNDUP(F14/$D$5,0))) -> 0 | H14: =IF(AND(F14<$D$5,F14>0),"can be merged","") | J14: Retention Rate: | K14: 2-2 | M14: 2-2 | N14: =IF(L13<>"",ROUNDUP((L13*$J$15)*$J$17,0),0) -> 0 | O14: =IF($L$5=0,0,IF(AND(N14>0,N14-$L$5<6),ROUNDUP((N14-5)/$L$5,0),ROUNDUP(N14/$L$5,0))) -> 0 | P14: =IF(AND(N14<$L$5,N14>0),"can be merged","")
C15: Total | F15: =SUM(F11:F14) -> 0 | G15: =SUM(G11:G14) -> 0 | J15: 0.95 | K15: 3-1 | M15: 3-1 | N15: =IF(L14<>"",ROUNDUP((L14*$J$15)*$J$17,0),0) -> 0 | O15: =IF($L$5=0,0,IF(AND(N15>0,N15-$L$5<6),ROUNDUP((N15-5)/$L$5,0),ROUNDUP(N15/$L$5,0))) -> 0 | P15: =IF(AND(N15<$L$5,N15>0),"can be merged","")
B16: STEM | C16: 11-1 | E16: 11-1 | G16: =IF($D$5=0,0,IF(AND(F16>0,F16-$D$5<6),ROUNDUP((F16-5)/$D$5,0),ROUNDUP(F16/$D$5,0))) -> 0 | H16: =IF(AND(F16<$D$5,F16>0),"can be merged","") | J16: Migration Rate: | K16: 3-2 | M16: 3-2 | N16: =IF(L15<>"",ROUNDUP((L15*$J$15)*$J$17,0),0) -> 0 | O16: =IF($L$5=0,0,IF(AND(N16>0,N16-$L$5<6),ROUNDUP((N16-5)/$L$5,0),ROUNDUP(N16/$L$5,0))) -> 0 | P16: =IF(AND(N16<$L$5,N16>0),"can be merged","")
B17: Retention Rate: | C17: 11-2 | E17: 11-2 | F17: =ROUNDUP((D16*$B$18)*$B$20,0) -> 0 | G17: =IF($D$5=0,0,IF(AND(F17>0,F17-$D$5<6),ROUNDUP((F17-5)/$D$5,0),ROUNDUP(F17/$D$5,0))) -> 0 | H17: =IF(AND(F17<$D$5,F17>0),"can be merged","") | J17: 0.95 | K17: 4-1 | M17: 4-1 | N17: =IF(L16<>"",ROUNDUP((L16*$J$15)*$J$17,0),0) -> 0 | O17: =IF($L$5=0,0,IF(AND(N17>0,N17-$L$5<6),ROUNDUP((N17-5)/$L$5,0),ROUNDUP(N17/$L$5,0))) -> 0 | P17: =IF(AND(N17<$L$5,N17>0),"can be merged","")
C18: 12-1 | E18: 12-1 | F18: =ROUNDUP((D17*$B$18)*$B$20,0) -> 0 | G18: =IF($D$5=0,0,IF(AND(F18>0,F18-$D$5<6),ROUNDUP((F18-5)/$D$5,0),ROUNDUP(F18/$D$5,0))) -> 0 | H18: =IF(AND(F18<$D$5,F18>0),"can be merged","") | K18: 4-2 | M18: 4-2 | N18: =IF(L17<>"",ROUNDUP((L17*$J$15)*$J$17,0),0) -> 0 | O18: =IF($L$5=0,0,IF(AND(N18>0,N18-$L$5<6),ROUNDUP((N18-5)/$L$5,0),ROUNDUP(N18/$L$5,0))) -> 0 | P18: =IF(AND(N18<$L$5,N18>0),"can be merged","")
B19: Migration Rate: | C19: 12-2 | E19: 12-2 | F19: =ROUNDUP((D18*$B$18)*$B$20,0) -> 0 | G19: =IF($D$5=0,0,IF(AND(F19>0,F19-$D$5<6),ROUNDUP((F19-5)/$D$5,0),ROUNDUP(F19/$D$5,0))) -> 0 | H19: =IF(AND(F19<$D$5,F19>0),"can be merged","") | K19: Total | N19: =SUM(N11:N18) -> 0 | O19: =SUM(O11:O18) -> 0
C20: Total | F20: =SUM(F16:F19) -> 0 | G20: =SUM(G16:G19) -> 0 | J20: BS in Computer Science (BSCS) | K20: 1-1 | M20: 1-1 | O20: =IF($L$5=0,0,IF(AND(N20>0,N20-$L$5<6),ROUNDUP((N20-5)/$L$5,0),ROUNDUP(N20/$L$5,0))) -> 0 | P20: =IF(AND(N20<$L$5,N20>0),"can be merged","")
B21: ABM | C21: 11-1 | E21: 11-1 | G21: =IF($D$5=0,0,IF(AND(F21>0,F21-$D$5<6),ROUNDUP((F21-5)/$D$5,0),ROUNDUP(F21/$D$5,0))) -> 0 | H21: =IF(AND(F21<$D$5,F21>0),"can be merged","") | K21: 1-2 | M21: 1-2 | N21: =ROUNDUP((L20*$J$24)*$J$26,0) -> 0 | O21: =IF($L$5=0,0,IF(AND(N21>0,N21-$L$5<6),ROUNDUP((N21-5)/$L$5,0),ROUNDUP(N21/$L$5,0))) -> 0 | P21: =IF(AND(N21<$L$5,N21>0),"can be merged","")
B22: Retention Rate: | C22: 11-2 | E22: 11-2 | F22: =ROUNDUP((D21*$B$23)*$B$25,0) -> 0 | G22: =IF($D$5=0,0,IF(AND(F22>0,F22-$D$5<6),ROUNDUP((F22-5)/$D$5,0),ROUNDUP(F22/$D$5,0))) -> 0 | H22: =IF(AND(F22<$D$5,F22>0),"can be merged","") | K22: 2-1 | M22: 2-1 | N22: =ROUNDUP((L21*$J$24)*$J$26,0) -> 0 | O22: =IF($L$5=0,0,IF(AND(N22>0,N22-$L$5<6),ROUNDUP((N22-5)/$L$5,0),ROUNDUP(N22/$L$5,0))) -> 0 | P22: =IF(AND(N22<$L$5,N22>0),"can be merged","")
C23: 12-1 | E23: 12-1 | F23: =ROUNDUP((D22*$B$23)*$B$25,0) -> 0 | G23: =IF($D$5=0,0,IF(AND(F23>0,F23-$D$5<6),ROUNDUP((F23-5)/$D$5,0),ROUNDUP(F23/$D$5,0))) -> 0 | H23: =IF(AND(F23<$D$5,F23>0),"can be merged","") | J23: Retention Rate: | K23: 2-2 | M23: 2-2 | N23: =ROUNDUP((L22*$J$24)*$J$26,0) -> 0 | O23: =IF($L$5=0,0,IF(AND(N23>0,N23-$L$5<6),ROUNDUP((N23-5)/$L$5,0),ROUNDUP(N23/$L$5,0))) -> 0 | P23: =IF(AND(N23<$L$5,N23>0),"can be merged","")
B24: Migration Rate: | C24: 12-2 | E24: 12-2 | F24: =ROUNDUP((D23*$B$23)*$B$25,0) -> 0 | G24: =IF($D$5=0,0,IF(AND(F24>0,F24-$D$5<6),ROUNDUP((F24-5)/$D$5,0),ROUNDUP(F24/$D$5,0))) -> 0 | H24: =IF(AND(F24<$D$5,F24>0),"can be merged","") | K24: 3-1 | M24: 3-1 | N24: =ROUNDUP((L23*$J$24)*$J$26,0) -> 0 | O24: =IF($L$5=0,0,IF(AND(N24>0,N24-$L$5<6),ROUNDUP((N24-5)/$L$5,0),ROUNDUP(N24/$L$5,0))) -> 0 | P24: =IF(AND(N24<$L$5,N24>0),"can be merged","")
C25: Total | F25: =SUM(F21:F24) -> 0 | G25: =SUM(G21:G24) -> 0 | J25: Migration Rate: | K25: 3-2 | M25: 3-2 | N25: =ROUNDUP((L24*$J$24)*$J$26,0) -> 0 | O25: =IF($L$5=0,0,IF(AND(N25>0,N25-$L$5<6),ROUNDUP((N25-5)/$L$5,0),ROUNDUP(N25/$L$5,0))) -> 0 | P25: =IF(AND(N25<$L$5,N25>0),"can be merged","")
B26: General Academic (GA) | C26: 11-1 | E26: 11-1 | G26: =IF($D$5=0,0,IF(AND(F26>0,F26-$D$5<6),ROUNDUP((F26-5)/$D$5,0),ROUNDUP(F26/$D$5,0))) -> 0 | H26: =IF(AND(F26<$D$5,F26>0),"can be merged","") | K26: 4-1 | M26: 4-1 | N26: =ROUNDUP((L25*$J$24)*$J$26,0) -> 0 | O26: =IF($L$5=0,0,IF(AND(N26>0,N26-$L$5<6),ROUNDUP((N26-5)/$L$5,0),ROUNDUP(N26/$L$5,0))) -> 0 | P26: =IF(AND(N26<$L$5,N26>0),"can be merged","")
B27: Retention Rate: | C27: 11-2 | E27: 11-2 | F27: =ROUNDUP((D26*$B$28)*$B$30,0) -> 0 | G27: =IF($D$5=0,0,IF(AND(F27>0,F27-$D$5<6),ROUNDUP((F27-5)/$D$5,0),ROUNDUP(F27/$D$5,0))) -> 0 | H27: =IF(AND(F27<$D$5,F27>0),"can be merged","") | K27: 4-2 | M27: 4-2 | N27: =ROUNDUP((L26*$J$24)*$J$26,0) -> 0 | O27: =IF($L$5=0,0,IF(AND(N27>0,N27-$L$5<6),ROUNDUP((N27-5)/$L$5,0),ROUNDUP(N27/$L$5,0))) -> 0 | P27: =IF(AND(N27<$L$5,N27>0),"can be merged","")
C28: 12-1 | E28: 12-1 | F28: =ROUNDUP((D27*$B$28)*$B$30,0) -> 0 | G28: =IF($D$5=0,0,IF(AND(F28>0,F28-$D$5<6),ROUNDUP((F28-5)/$D$5,0),ROUNDUP(F28/$D$5,0))) -> 0 | H28: =IF(AND(F28<$D$5,F28>0),"can be merged","") | K28: Total | N28: =SUM(N20:N27) -> 0 | O28: =SUM(O20:O27) -> 0
B29: Migration Rate: | C29: 12-2 | E29: 12-2 | F29: =ROUNDUP((D28*$B$28)*$B$30,0) -> 0 | G29: =IF($D$5=0,0,IF(AND(F29>0,F29-$D$5<6),ROUNDUP((F29-5)/$D$5,0),ROUNDUP(F29/$D$5,0))) -> 0 | H29: =IF(AND(F29<$D$5,F29>0),"can be merged","") | J29: BS in Information System (BSIS) | K29: 1-1 | M29: 1-1 | O29: =IF($L$5=0,0,IF(AND(N29>0,N29-$L$5<6),ROUNDUP((N29-5)/$L$5,0),ROUNDUP(N29/$L$5,0))) -> 0 | P29: =IF(AND(N29<$L$5,N29>0),"can be merged","")
C30: Total | F30: =SUM(F26:F29) -> 0 | G30: =SUM(G26:G29) -> 0 | K30: 1-2 | M30: 1-2 | N30: =ROUNDUP((L29*$J$33)*$J$35,0) -> 0 | O30: =IF($L$5=0,0,IF(AND(N30>0,N30-$L$5<6),ROUNDUP((N30-5)/$L$5,0),ROUNDUP(N30/$L$5,0))) -> 0 | P30: =IF(AND(N30<$L$5,N30>0),"can be merged","")
B31: HUMSS | C31: 11-1 | E31: 11-1 | G31: =IF($D$5=0,0,IF(AND(F31>0,F31-$D$5<6),ROUNDUP((F31-5)/$D$5,0),ROUNDUP(F31/$D$5,0))) -> 0 | H31: =IF(AND(F31<$D$5,F31>0),"can be merged","") | K31: 2-1 | M31: 2-1 | N31: =ROUNDUP((L30*$J$33)*$J$35,0) -> 0 | O31: =IF($L$5=0,0,IF(AND(N31>0,N31-$L$5<6),ROUNDUP((N31-5)/$L$5,0),ROUNDUP(N31/$L$5,0))) -> 0 | P31: =IF(AND(N31<$L$5,N31>0),"can be merged","")
B32: Retention Rate: | C32: 11-2 | E32: 11-2 | F32: =ROUNDUP((D31*$B$33)*$B$35,0) -> 0 | G32: =IF($D$5=0,0,IF(AND(F32>0,F32-$D$5<6),ROUNDUP((F32-5)/$D$5,0),ROUNDUP(F32/$D$5,0))) -> 0 | H32: =IF(AND(F32<$D$5,F32>0),"can be merged","") | J32: Retention Rate: | K32: 2-2 | M32: 2-2 | N32: =ROUNDUP((L31*$J$33)*$J$35,0) -> 0 | O32: =IF($L$5=0,0,IF(AND(N32>0,N32-$L$5<6),ROUNDUP((N32-5)/$L$5,0),ROUNDUP(N32/$L$5,0))) -> 0 | P32: =IF(AND(N32<$L$5,N32>0),"can be merged","")
C33: 12-1 | E33: 12-1 | F33: =ROUNDUP((D32*$B$33)*$B$35,0) -> 0 | G33: =IF($D$5=0,0,IF(AND(F33>0,F33-$D$5<6),ROUNDUP((F33-5)/$D$5,0),ROUNDUP(F33/$D$5,0))) -> 0 | H33: =IF(AND(F33<$D$5,F33>0),"can be merged","") | K33: 3-1 | M33: 3-1 | N33: =ROUNDUP((L32*$J$33)*$J$35,0) -> 0 | O33: =IF($L$5=0,0,IF(AND(N33>0,N33-$L$5<6),ROUNDUP((N33-5)/$L$5,0),ROUNDUP(N33/$L$5,0))) -> 0 | P33: =IF(AND(N33<$L$5,N33>0),"can be merged","")
B34: Migration Rate: | C34: 12-2 | E34: 12-2 | F34: =ROUNDUP((D33*$B$33)*$B$35,0) -> 0 | G34: =IF($D$5=0,0,IF(AND(F34>0,F34-$D$5<6),ROUNDUP((F34-5)/$D$5,0),ROUNDUP(F34/$D$5,0))) -> 0 | H34: =IF(AND(F34<$D$5,F34>0),"can be merged","") | J34: Migration Rate: | K34: 3-2 | M34: 3-2 | N34: =ROUNDUP((L33*$J$33)*$J$35,0) -> 0 | O34: =IF($L$5=0,0,IF(AND(N34>0,N34-$L$5<6),ROUNDUP((N34-5)/$L$5,0),ROUNDUP(N34/$L$5,0))) -> 0 | P34: =IF(AND(N34<$L$5,N34>0),"can be merged","")
C35: Total | F35: =SUM(F31:F34) -> 0 | G35: =SUM(G31:G34) -> 0 | K35: 4-1 | M35: 4-1 | N35: =ROUNDUP((L34*$J$33)*$J$35,0) -> 0 | O35: =IF($L$5=0,0,IF(AND(N35>0,N35-$L$5<6),ROUNDUP((N35-5)/$L$5,0),ROUNDUP(N35/$L$5,0))) -> 0 | P35: =IF(AND(N35<$L$5,N35>0),"can be merged","")
B36: IT-MAWD | C36: 11-1 | E36: 11-1 | G36: =IF($D$5=0,0,IF(AND(F36>0,F36-$D$5<6),ROUNDUP((F36-5)/$D$5,0),ROUNDUP(F36/$D$5,0))) -> 0 | H36: =IF(AND(F36<$D$5,F36>0),"can be merged","") | K36: 4-2 | M36: 4-2 | N36: =ROUNDUP((L35*$J$33)*$J$35,0) -> 0 | O36: =IF($L$5=0,0,IF(AND(N36>0,N36-$L$5<6),ROUNDUP((N36-5)/$L$5,0),ROUNDUP(N36/$L$5,0))) -> 0 | P36: =IF(AND(N36<$L$5,N36>0),"can be merged","")
B37: Retention Rate: | C37: 11-2 | E37: 11-2 | F37: =ROUNDUP((D36*$B$38)*$B$40,0) -> 0 | G37: =IF($D$5=0,0,IF(AND(F37>0,F37-$D$5<6),ROUNDUP((F37-5)/$D$5,0),ROUNDUP(F37/$D$5,0))) -> 0 | H37: =IF(AND(F37<$D$5,F37>0),"can be merged","") | K37: Total | N37: =SUM(N29:N36) -> 0 | O37: =SUM(O29:O36) -> 0
C38: 12-1 | E38: 12-1 | F38: =ROUNDUP((D37*$B$38)*$B$40,0) -> 0 | G38: =IF($D$5=0,0,IF(AND(F38>0,F38-$D$5<6),ROUNDUP((F38-5)/$D$5,0),ROUNDUP(F38/$D$5,0))) -> 0 | H38: =IF(AND(F38<$D$5,F38>0),"can be merged","") | J38: BS in Computer Engineering (BSCPE) | K38: 1-1 | M38: 1-1 | O38: =IF($L$5=0,0,IF(AND(N38>0,N38-$L$5<6),ROUNDUP((N38-5)/$L$5,0),ROUNDUP(N38/$L$5,0))) -> 0 | P38: =IF(AND(N38<$L$5,N38>0),"can be merged","")
B39: Migration Rate: | C39: 12-2 | E39: 12-2 | F39: =ROUNDUP((D38*$B$38)*$B$40,0) -> 0 | G39: =IF($D$5=0,0,IF(AND(F39>0,F39-$D$5<6),ROUNDUP((F39-5)/$D$5,0),ROUNDUP(F39/$D$5,0))) -> 0 | H39: =IF(AND(F39<$D$5,F39>0),"can be merged","") | K39: 1-2 | M39: 1-2 | N39: =ROUNDUP((L38*$J$42)*$J$44,0) -> 0 | O39: =IF($L$5=0,0,IF(AND(N39>0,N39-$L$5<6),ROUNDUP((N39-5)/$L$5,0),ROUNDUP(N39/$L$5,0))) -> 0 | P39: =IF(AND(N39<$L$5,N39>0),"can be merged","")
C40: Total | F40: =SUM(F36:F39) -> 0 | G40: =SUM(G36:G39) -> 0 | K40: 2-1 | M40: 2-1 | N40: =ROUNDUP((L39*$J$42)*$J$44,0) -> 0 | O40: =IF($L$5=0,0,IF(AND(N40>0,N40-$L$5<6),ROUNDUP((N40-5)/$L$5,0),ROUNDUP(N40/$L$5,0))) -> 0 | P40: =IF(AND(N40<$L$5,N40>0),"can be merged","")
B41: IT-DA | C41: 11-1 | E41: 11-1 | G41: =IF($D$5=0,0,IF(AND(F41>0,F41-$D$5<6),ROUNDUP((F41-5)/$D$5,0),ROUNDUP(F41/$D$5,0))) -> 0 | H41: =IF(AND(F41<$D$5,F41>0),"can be merged","") | J41: Retention Rate: | K41: 2-2 | M41: 2-2 | N41: =ROUNDUP((L40*$J$42)*$J$44,0) -> 0 | O41: =IF($L$5=0,0,IF(AND(N41>0,N41-$L$5<6),ROUNDUP((N41-5)/$L$5,0),ROUNDUP(N41/$L$5,0))) -> 0 | P41: =IF(AND(N41<$L$5,N41>0),"can be merged","")
B42: Retention Rate: | C42: 11-2 | E42: 11-2 | F42: =ROUNDUP((D41*$B$43)*$B$45,0) -> 0 | G42: =IF($D$5=0,0,IF(AND(F42>0,F42-$D$5<6),ROUNDUP((F42-5)/$D$5,0),ROUNDUP(F42/$D$5,0))) -> 0 | H42: =IF(AND(F42<$D$5,F42>0),"can be merged","") | K42: 3-1 | M42: 3-1 | N42: =ROUNDUP((L41*$J$42)*$J$44,0) -> 0 | O42: =IF($L$5=0,0,IF(AND(N42>0,N42-$L$5<6),ROUNDUP((N42-5)/$L$5,0),ROUNDUP(N42/$L$5,0))) -> 0 | P42: =IF(AND(N42<$L$5,N42>0),"can be merged","")
C43: 12-1 | E43: 12-1 | F43: =ROUNDUP((D42*$B$43)*$B$45,0) -> 0 | G43: =IF($D$5=0,0,IF(AND(F43>0,F43-$D$5<6),ROUNDUP((F43-5)/$D$5,0),ROUNDUP(F43/$D$5,0))) -> 0 | H43: =IF(AND(F43<$D$5,F43>0),"can be merged","") | J43: Migration Rate: | K43: 3-2 | M43: 3-2 | N43: =ROUNDUP((L42*$J$42)*$J$44,0) -> 0 | O43: =IF($L$5=0,0,IF(AND(N43>0,N43-$L$5<6),ROUNDUP((N43-5)/$L$5,0),ROUNDUP(N43/$L$5,0))) -> 0 | P43: =IF(AND(N43<$L$5,N43>0),"can be merged","")
B44: Migration Rate: | C44: 12-2 | E44: 12-2 | F44: =ROUNDUP((D43*$B$43)*$B$45,0) -> 0 | G44: =IF($D$5=0,0,IF(AND(F44>0,F44-$D$5<6),ROUNDUP((F44-5)/$D$5,0),ROUNDUP(F44/$D$5,0))) -> 0 | H44: =IF(AND(F44<$D$5,F44>0),"can be merged","") | K44: 4-1 | M44: 4-1 | N44: =ROUNDUP((L43*$J$42)*$J$44,0) -> 0 | O44: =IF($L$5=0,0,IF(AND(N44>0,N44-$L$5<6),ROUNDUP((N44-5)/$L$5,0),ROUNDUP(N44/$L$5,0))) -> 0 | P44: =IF(AND(N44<$L$5,N44>0),"can be merged","")
C45: Total | F45: =SUM(F41:F44) -> 0 | G45: =SUM(G41:G44) -> 0 | K45: 4-2 | M45: 4-2 | N45: =ROUNDUP((L44*$J$42)*$J$44,0) -> 0 | O45: =IF($L$5=0,0,IF(AND(N45>0,N45-$L$5<6),ROUNDUP((N45-5)/$L$5,0),ROUNDUP(N45/$L$5,0))) -> 0 | P45: =IF(AND(N45<$L$5,N45>0),"can be merged","")
B46: IT -CCTECH | C46: 11-1 | E46: 11-1 | G46: =IF($D$5=0,0,IF(AND(F46>0,F46-$D$5<6),ROUNDUP((F46-5)/$D$5,0),ROUNDUP(F46/$D$5,0))) -> 0 | H46: =IF(AND(F46<$D$5,F46>0),"can be merged","") | K46: Total | N46: =SUM(N38:N45) -> 0 | O46: =SUM(O38:O45) -> 0
B47: Retention Rate: | C47: 11-2 | E47: 11-2 | F47: =ROUNDUP((D46*$B$48)*$B$50,0) -> 0 | G47: =IF($D$5=0,0,IF(AND(F47>0,F47-$D$5<6),ROUNDUP((F47-5)/$D$5,0),ROUNDUP(F47/$D$5,0))) -> 0 | H47: =IF(AND(F47<$D$5,F47>0),"can be merged","") | J47: BS in Hospitality Management (BSHM) | K47: 1-1 | M47: 1-1 | O47: =IF($L$5=0,0,IF(AND(N47>0,N47-$L$5<6),ROUNDUP((N47-5)/$L$5,0),ROUNDUP(N47/$L$5,0))) -> 0 | P47: =IF(AND(N47<$L$5,N47>0),"can be merged","")
C48: 12-1 | E48: 12-1 | F48: =ROUNDUP((D47*$B$48)*$B$50,0) -> 0 | G48: =IF($D$5=0,0,IF(AND(F48>0,F48-$D$5<6),ROUNDUP((F48-5)/$D$5,0),ROUNDUP(F48/$D$5,0))) -> 0 | H48: =IF(AND(F48<$D$5,F48>0),"can be merged","") | K48: 1-2 | M48: 1-2 | N48: =ROUNDUP((L47*$J$51)*$J$53,0) -> 0 | O48: =IF($L$5=0,0,IF(AND(N48>0,N48-$L$5<6),ROUNDUP((N48-5)/$L$5,0),ROUNDUP(N48/$L$5,0))) -> 0 | P48: =IF(AND(N48<$L$5,N48>0),"can be merged","")
B49: Migration Rate: | C49: 12-2 | E49: 12-2 | F49: =ROUNDUP((D48*$B$48)*$B$50,0) -> 0 | G49: =IF($D$5=0,0,IF(AND(F49>0,F49-$D$5<6),ROUNDUP((F49-5)/$D$5,0),ROUNDUP(F49/$D$5,0))) -> 0 | H49: =IF(AND(F49<$D$5,F49>0),"can be merged","") | K49: 2-1 | M49: 2-1 | N49: =ROUNDUP((L48*$J$51)*$J$53,0) -> 0 | O49: =IF($L$5=0,0,IF(AND(N49>0,N49-$L$5<6),ROUNDUP((N49-5)/$L$5,0),ROUNDUP(N49/$L$5,0))) -> 0 | P49: =IF(AND(N49<$L$5,N49>0),"can be merged","")
C50: Total | F50: =SUM(F46:F49) -> 0 | G50: =SUM(G46:G49) -> 0 | J50: Retention Rate: | K50: 2-2 | M50: 2-2 | N50: =ROUNDUP((L49*$J$51)*$J$53,0) -> 0 | O50: =IF($L$5=0,0,IF(AND(N50>0,N50-$L$5<6),ROUNDUP((N50-5)/$L$5,0),ROUNDUP(N50/$L$5,0))) -> 0 | P50: =IF(AND(N50<$L$5,N50>0),"can be merged","")
B51: HE - CA | C51: 11-1 | E51: 11-1 | G51: =IF($D$5=0,0,IF(AND(F51>0,F51-$D$5<6),ROUNDUP((F51-5)/$D$5,0),ROUNDUP(F51/$D$5,0))) -> 0 | H51: =IF(AND(F51<$D$5,F51>0),"can be merged","") | K51: 3-1 | M51: 3-1 | N51: =ROUNDUP((L50*$J$51)*$J$53,0) -> 0 | O51: =IF($L$5=0,0,IF(AND(N51>0,N51-$L$5<6),ROUNDUP((N51-5)/$L$5,0),ROUNDUP(N51/$L$5,0))) -> 0 | P51: =IF(AND(N51<$L$5,N51>0),"can be merged","")
B52: Retention Rate: | C52: 11-2 | E52: 11-2 | F52: =ROUNDUP((D51*$B$53)*$B$55,0) -> 0 | G52: =IF($D$5=0,0,IF(AND(F52>0,F52-$D$5<6),ROUNDUP((F52-5)/$D$5,0),ROUNDUP(F52/$D$5,0))) -> 0 | H52: =IF(AND(F52<$D$5,F52>0),"can be merged","") | J52: Migration Rate: | K52: 3-2 | M52: 3-2 | N52: =ROUNDUP((L51*$J$51)*$J$53,0) -> 0 | O52: =IF($L$5=0,0,IF(AND(N52>0,N52-$L$5<6),ROUNDUP((N52-5)/$L$5,0),ROUNDUP(N52/$L$5,0))) -> 0 | P52: =IF(AND(N52<$L$5,N52>0),"can be merged","")
C53: 12-1 | E53: 12-1 | F53: =ROUNDUP((D52*$B$53)*$B$55,0) -> 0 | G53: =IF($D$5=0,0,IF(AND(F53>0,F53-$D$5<6),ROUNDUP((F53-5)/$D$5,0),ROUNDUP(F53/$D$5,0))) -> 0 | H53: =IF(AND(F53<$D$5,F53>0),"can be merged","") | K53: 4-1 | M53: 4-1 | N53: =ROUNDUP((L52*$J$51)*$J$53,0) -> 0 | O53: =IF($L$5=0,0,IF(AND(N53>0,N53-$L$5<6),ROUNDUP((N53-5)/$L$5,0),ROUNDUP(N53/$L$5,0))) -> 0 | P53: =IF(AND(N53<$L$5,N53>0),"can be merged","")
B54: Migration Rate: | C54: 12-2 | E54: 12-2 | F54: =ROUNDUP((D53*$B$53)*$B$55,0) -> 0 | G54: =IF($D$5=0,0,IF(AND(F54>0,F54-$D$5<6),ROUNDUP((F54-5)/$D$5,0),ROUNDUP(F54/$D$5,0))) -> 0 | H54: =IF(AND(F54<$D$5,F54>0),"can be merged","") | K54: 4-2 | M54: 4-2 | N54: =ROUNDUP((L53*$J$51)*$J$53,0) -> 0 | O54: =IF($L$5=0,0,IF(AND(N54>0,N54-$L$5<6),ROUNDUP((N54-5)/$L$5,0),ROUNDUP(N54/$L$5,0))) -> 0 | P54: =IF(AND(N54<$L$5,N54>0),"can be merged","")
C55: Total | F55: =SUM(F51:F54) -> 0 | G55: =SUM(G51:G54) -> 0 | K55: Total | N55: =SUM(N47:N54) -> 0 | O55: =SUM(O47:O54) -> 0
B56: HE - RCO | C56: 11-1 | E56: 11-1 | G56: =IF($D$5=0,0,IF(AND(F56>0,F56-$D$5<6),ROUNDUP((F56-5)/$D$5,0),ROUNDUP(F56/$D$5,0))) -> 0 | H56: =IF(AND(F56<$D$5,F56>0),"can be merged","") | J56: BS in Culinary Management (BSCM) | K56: 1-1 | M56: 1-1 | O56: =IF($L$5=0,0,IF(AND(N56>0,N56-$L$5<6),ROUNDUP((N56-5)/$L$5,0),ROUNDUP(N56/$L$5,0))) -> 0 | P56: =IF(AND(N56<$L$5,N56>0),"can be merged","")
B57: Retention Rate: | C57: 11-2 | E57: 11-2 | F57: =ROUNDUP((D56*$B$58)*$B$60,0) -> 0 | G57: =IF($D$5=0,0,IF(AND(F57>0,F57-$D$5<6),ROUNDUP((F57-5)/$D$5,0),ROUNDUP(F57/$D$5,0))) -> 0 | H57: =IF(AND(F57<$D$5,F57>0),"can be merged","") | K57: 1-2 | M57: 1-2 | N57: =ROUNDUP((L56*$J$60)*$J$62,0) -> 0 | O57: =IF($L$5=0,0,IF(AND(N57>0,N57-$L$5<6),ROUNDUP((N57-5)/$L$5,0),ROUNDUP(N57/$L$5,0))) -> 0 | P57: =IF(AND(N57<$L$5,N57>0),"can be merged","")
C58: 12-1 | E58: 12-1 | F58: =ROUNDUP((D57*$B$58)*$B$60,0) -> 0 | G58: =IF($D$5=0,0,IF(AND(F58>0,F58-$D$5<6),ROUNDUP((F58-5)/$D$5,0),ROUNDUP(F58/$D$5,0))) -> 0 | H58: =IF(AND(F58<$D$5,F58>0),"can be merged","") | K58: 2-1 | M58: 2-1 | N58: =ROUNDUP((L57*$J$60)*$J$62,0) -> 0 | O58: =IF($L$5=0,0,IF(AND(N58>0,N58-$L$5<6),ROUNDUP((N58-5)/$L$5,0),ROUNDUP(N58/$L$5,0))) -> 0 | P58: =IF(AND(N58<$L$5,N58>0),"can be merged","")
B59: Migration Rate: | C59: 12-2 | E59: 12-2 | F59: =ROUNDUP((D58*$B$58)*$B$60,0) -> 0 | G59: =IF($D$5=0,0,IF(AND(F59>0,F59-$D$5<6),ROUNDUP((F59-5)/$D$5,0),ROUNDUP(F59/$D$5,0))) -> 0 | H59: =IF(AND(F59<$D$5,F59>0),"can be merged","") | J59: Retention Rate: | K59: 2-2 | M59: 2-2 | N59: =ROUNDUP((L58*$J$60)*$J$62,0) -> 0 | O59: =IF($L$5=0,0,IF(AND(N59>0,N59-$L$5<6),ROUNDUP((N59-5)/$L$5,0),ROUNDUP(N59/$L$5,0))) -> 0 | P59: =IF(AND(N59<$L$5,N59>0),"can be merged","")
C60: Total | F60: =SUM(F56:F59) -> 0 | G60: =SUM(G56:G59) -> 0 | K60: 3-1 | M60: 3-1 | N60: =ROUNDUP((L59*$J$60)*$J$62,0) -> 0 | O60: =IF($L$5=0,0,IF(AND(N60>0,N60-$L$5<6),ROUNDUP((N60-5)/$L$5,0),ROUNDUP(N60/$L$5,0))) -> 0 | P60: =IF(AND(N60<$L$5,N60>0),"can be merged","")
B61: HE - TO | C61: 11-1 | E61: 11-1 | G61: =IF($D$5=0,0,IF(AND(F61>0,F61-$D$5<6),ROUNDUP((F61-5)/$D$5,0),ROUNDUP(F61/$D$5,0))) -> 0 | H61: =IF(AND(F61<$D$5,F61>0),"can be merged","") | J61: Migration Rate: | K61: 3-2 | M61: 3-2 | N61: =ROUNDUP((L60*$J$60)*$J$62,0) -> 0 | O61: =IF($L$5=0,0,IF(AND(N61>0,N61-$L$5<6),ROUNDUP((N61-5)/$L$5,0),ROUNDUP(N61/$L$5,0))) -> 0 | P61: =IF(AND(N61<$L$5,N61>0),"can be merged","")
B62: Retention Rate: | C62: 11-2 | E62: 11-2 | F62: =ROUNDUP((D61*$B$63)*$B$65,0) -> 0 | G62: =IF($D$5=0,0,IF(AND(F62>0,F62-$D$5<6),ROUNDUP((F62-5)/$D$5,0),ROUNDUP(F62/$D$5,0))) -> 0 | H62: =IF(AND(F62<$D$5,F62>0),"can be merged","") | K62: 4-1 | M62: 4-1 | N62: =ROUNDUP((L61*$J$60)*$J$62,0) -> 0 | O62: =IF($L$5=0,0,IF(AND(N62>0,N62-$L$5<6),ROUNDUP((N62-5)/$L$5,0),ROUNDUP(N62/$L$5,0))) -> 0 | P62: =IF(AND(N62<$L$5,N62>0),"can be merged","")
C63: 12-1 | E63: 12-1 | F63: =ROUNDUP((D62*$B$63)*$B$65,0) -> 0 | G63: =IF($D$5=0,0,IF(AND(F63>0,F63-$D$5<6),ROUNDUP((F63-5)/$D$5,0),ROUNDUP(F63/$D$5,0))) -> 0 | H63: =IF(AND(F63<$D$5,F63>0),"can be merged","") | K63: 4-2 | M63: 4-2 | N63: =ROUNDUP((L62*$J$60)*$J$62,0) -> 0 | O63: =IF($L$5=0,0,IF(AND(N63>0,N63-$L$5<6),ROUNDUP((N63-5)/$L$5,0),ROUNDUP(N63/$L$5,0))) -> 0 | P63: =IF(AND(N63<$L$5,N63>0),"can be merged","")
B64: Migration Rate: | C64: 12-2 | E64: 12-2 | F64: =ROUNDUP((D63*$B$63)*$B$65,0) -> 0 | G64: =IF($D$5=0,0,IF(AND(F64>0,F64-$D$5<6),ROUNDUP((F64-5)/$D$5,0),ROUNDUP(F64/$D$5,0))) -> 0 | H64: =IF(AND(F64<$D$5,F64>0),"can be merged","") | K64: Total | N64: =SUM(N56:N63) -> 0 | O64: =SUM(O56:O63) -> 0
C65: Total | F65: =SUM(F61:F64) -> 0 | G65: =SUM(G61:G64) -> 0 | J65: BS in Tourism Management (BSTM) | K65: 1-1 | M65: 1-1 | O65: =IF($L$5=0,0,IF(AND(N65>0,N65-$L$5<6),ROUNDUP((N65-5)/$L$5,0),ROUNDUP(N65/$L$5,0))) -> 0 | P65: =IF(AND(N65<$L$5,N65>0),"can be merged","")
B66: IA - CE | C66: 11-1 | E66: 11-1 | G66: =IF($D$5=0,0,IF(AND(F66>0,F66-$D$5<6),ROUNDUP((F66-5)/$D$5,0),ROUNDUP(F66/$D$5,0))) -> 0 | H66: =IF(AND(F66<$D$5,F66>0),"can be merged","") | K66: 1-2 | M66: 1-2 | N66: =ROUNDUP((L65*$J$69)*$J$71,0) -> 0 | O66: =IF($L$5=0,0,IF(AND(N66>0,N66-$L$5<6),ROUNDUP((N66-5)/$L$5,0),ROUNDUP(N66/$L$5,0))) -> 0 | P66: =IF(AND(N66<$L$5,N66>0),"can be merged","")
B67: Retention Rate: | C67: 11-2 | E67: 11-2 | F67: =ROUNDUP((D66*$B$68)*$B$70,0) -> 0 | G67: =IF($D$5=0,0,IF(AND(F67>0,F67-$D$5<6),ROUNDUP((F67-5)/$D$5,0),ROUNDUP(F67/$D$5,0))) -> 0 | H67: =IF(AND(F67<$D$5,F67>0),"can be merged","") | K67: 2-1 | M67: 2-1 | N67: =ROUNDUP((L66*$J$69)*$J$71,0) -> 0 | O67: =IF($L$5=0,0,IF(AND(N67>0,N67-$L$5<6),ROUNDUP((N67-5)/$L$5,0),ROUNDUP(N67/$L$5,0))) -> 0 | P67: =IF(AND(N67<$L$5,N67>0),"can be merged","")
B68: 0.95 | C68: 12-1 | E68: 12-1 | F68: =ROUNDUP((D67*$B$68)*$B$70,0) -> 0 | G68: =IF($D$5=0,0,IF(AND(F68>0,F68-$D$5<6),ROUNDUP((F68-5)/$D$5,0),ROUNDUP(F68/$D$5,0))) -> 0 | H68: =IF(AND(F68<$D$5,F68>0),"can be merged","") | J68: Retention Rate: | K68: 2-2 | M68: 2-2 | N68: =ROUNDUP((L67*$J$69)*$J$71,0) -> 0 | O68: =IF($L$5=0,0,IF(AND(N68>0,N68-$L$5<6),ROUNDUP((N68-5)/$L$5,0),ROUNDUP(N68/$L$5,0))) -> 0 | P68: =IF(AND(N68<$L$5,N68>0),"can be merged","")
B69: Migration Rate: | C69: 12-2 | E69: 12-2 | F69: =ROUNDUP((D68*$B$68)*$B$70,0) -> 0 | G69: =IF($D$5=0,0,IF(AND(F69>0,F69-$D$5<6),ROUNDUP((F69-5)/$D$5,0),ROUNDUP(F69/$D$5,0))) -> 0 | H69: =IF(AND(F69<$D$5,F69>0),"can be merged","") | K69: 3-1 | M69: 3-1 | N69: =ROUNDUP((L68*$J$69)*$J$71,0) -> 0 | O69: =IF($L$5=0,0,IF(AND(N69>0,N69-$L$5<6),ROUNDUP((N69-5)/$L$5,0),ROUNDUP(N69/$L$5,0))) -> 0 | P69: =IF(AND(N69<$L$5,N69>0),"can be merged","")
B70: 0.95 | C70: Total | F70: =SUM(F66:F69) -> 0 | G70: =SUM(G66:G69) -> 0 | J70: Migration Rate: | K70: 3-2 | M70: 3-2 | N70: =ROUNDUP((L69*$J$69)*$J$71,0) -> 0 | O70: =IF($L$5=0,0,IF(AND(N70>0,N70-$L$5<6),ROUNDUP((N70-5)/$L$5,0),ROUNDUP(N70/$L$5,0))) -> 0 | P70: =IF(AND(N70<$L$5,N70>0),"can be merged","")
F71: =F15+F20+F25+F30+F35+F40+F45+F50+F55+F60+F65+F70 -> 0 | G71: =G15+G20+G25+G30+G35+G40+G45+G50+G55+G60+G65+G70 -> 0 | K71: 4-1 | M71: 4-1 | N71: =ROUNDUP((L70*$J$69)*$J$71,0) -> 0 | O71: =IF($L$5=0,0,IF(AND(N71>0,N71-$L$5<6),ROUNDUP((N71-5)/$L$5,0),ROUNDUP(N71/$L$5,0))) -> 0 | P71: =IF(AND(N71<$L$5,N71>0),"can be merged","")
K72: 4-2 | M72: 4-2 | N72: =ROUNDUP((L71*$J$69)*$J$71,0) -> 0 | O72: =IF($L$5=0,0,IF(AND(N72>0,N72-$L$5<6),ROUNDUP((N72-5)/$L$5,0),ROUNDUP(N72/$L$5,0))) -> 0 | P72: =IF(AND(N72<$L$5,N72>0),"can be merged","")
K73: Total | N73: =SUM(N65:N72) -> 0 | O73: =SUM(O65:O72) -> 0
B74: 2-Year Degree Programs | J74: BS in Business Administration (BSBA) | K74: 1-1 | M74: 1-1 | O74: =IF($L$5=0,0,IF(AND(N74>0,N74-$L$5<6),ROUNDUP((N74-5)/$L$5,0),ROUNDUP(N74/$L$5,0))) -> 0 | P74: =IF(AND(N74<$L$5,N74>0),"can be merged","")
C75: Class Density | K75: 1-2 | M75: 1-2 | N75: =ROUNDUP((L74*$J$78)*$J$80,0) -> 0 | O75: =IF($L$5=0,0,IF(AND(N75>0,N75-$L$5<6),ROUNDUP((N75-5)/$L$5,0),ROUNDUP(N75/$L$5,0))) -> 0 | P75: =IF(AND(N75<$L$5,N75>0),"can be merged","")
K76: 2-1 | M76: 2-1 | N76: =ROUNDUP((L75*$J$78)*$J$80,0) -> 0 | O76: =IF($L$5=0,0,IF(AND(N76>0,N76-$L$5<6),ROUNDUP((N76-5)/$L$5,0),ROUNDUP(N76/$L$5,0))) -> 0 | P76: =IF(AND(N76<$L$5,N76>0),"can be merged","")
J77: Retention Rate: | K77: 2-2 | M77: 2-2 | N77: =ROUNDUP((L76*$J$78)*$J$80,0) -> 0 | O77: =IF($L$5=0,0,IF(AND(N77>0,N77-$L$5<6),ROUNDUP((N77-5)/$L$5,0),ROUNDUP(N77/$L$5,0))) -> 0 | P77: =IF(AND(N77<$L$5,N77>0),"can be merged","")
J78: 0.95 | K78: 3-1 | M78: 3-1 | N78: =ROUNDUP((L77*$J$78)*$J$80,0) -> 0 | O78: =IF($L$5=0,0,IF(AND(N78>0,N78-$L$5<6),ROUNDUP((N78-5)/$L$5,0),ROUNDUP(N78/$L$5,0))) -> 0 | P78: =IF(AND(N78<$L$5,N78>0),"can be merged","")
E79: ="SY "&#REF! & " Term " &#REF! -> #REF! | J79: Migration Rate: | K79: 3-2 | M79: 3-2 | N79: =ROUNDUP((L78*$J$78)*$J$80,0) -> 0 | O79: =IF($L$5=0,0,IF(AND(N79>0,N79-$L$5<6),ROUNDUP((N79-5)/$L$5,0),ROUNDUP(N79/$L$5,0))) -> 0 | P79: =IF(AND(N79<$L$5,N79>0),"can be merged","")
B80: Program | C80: Year Level Term | D80: Current OGS | E80: Year Level Term | F80: Projected NS / OS | G80: Section Count | H80: Remarks | J80: 0.95 | K80: 4-1 | M80: 4-1 | N80: =ROUNDUP((L79*$J$78)*$J$80,0) -> 0 | O80: =IF($L$5=0,0,IF(AND(N80>0,N80-$L$5<6),ROUNDUP((N80-5)/$L$5,0),ROUNDUP(N80/$L$5,0))) -> 0 | P80: =IF(AND(N80<$L$5,N80>0),"can be merged","")
K81: 4-2 | M81: 4-2 | N81: =ROUNDUP((L80*$J$78)*$J$80,0) -> 0 | O81: =IF($L$5=0,0,IF(AND(N81>0,N81-$L$5<6),ROUNDUP((N81-5)/$L$5,0),ROUNDUP(N81/$L$5,0))) -> 0 | P81: =IF(AND(N81<$L$5,N81>0),"can be merged","")
B82: Hosp. and Res. Services (HRS) | C82: 1-1 | E82: 1-1 | G82: =IF($D$75=0,0,IF(AND(F82>0,F82-$D$75<6),ROUNDUP((F82-5)/$D$75,0),ROUNDUP(F82/$D$75,0))) -> 0 | H82: =IF(AND(F82<$D$75,F82>0),"can be merged","") | K82: Total | N82: =SUM(N74:N81) -> 0 | O82: =SUM(O74:O81) -> 0
B83: Retention Rate: | C83: 1-2 | E83: 1-2 | F83: =ROUNDUP((D82*$B$84)*$B$86,0) -> 0 | G83: =IF($D$75=0,0,IF(AND(F83>0,F83-$D$75<6),ROUNDUP((F83-5)/$D$75,0),ROUNDUP(F83/$D$75,0))) -> 0 | H83: =IF(AND(F83<$D$75,F83>0),"can be merged","") | J83: BS in Accounting Information System (BSAIS) | K83: 1-1 | M83: 1-1 | O83: =IF($L$5=0,0,IF(AND(N83>0,N83-$L$5<6),ROUNDUP((N83-5)/$L$5,0),ROUNDUP(N83/$L$5,0))) -> 0 | P83: =IF(AND(N83<$L$5,N83>0),"can be merged","")
C84: 2-1 | E84: 2-1 | F84: =ROUNDUP((D83*$B$84)*$B$86,0) -> 0 | G84: =IF($D$75=0,0,IF(AND(F84>0,F84-$D$75<6),ROUNDUP((F84-5)/$D$75,0),ROUNDUP(F84/$D$75,0))) -> 0 | H84: =IF(AND(F84<$D$75,F84>0),"can be merged","") | K84: 1-2 | M84: 1-2 | N84: =ROUNDUP((L83*$J$87)*$J$89,0) -> 0 | O84: =IF($L$5=0,0,IF(AND(N84>0,N84-$L$5<6),ROUNDUP((N84-5)/$L$5,0),ROUNDUP(N84/$L$5,0))) -> 0 | P84: =IF(AND(N84<$L$5,N84>0),"can be merged","")
B85: Migration Rate: | C85: 2-2 | E85: 2-2 | F85: =ROUNDUP((D84*$B$84)*$B$86,0) -> 0 | G85: =IF($D$75=0,0,IF(AND(F85>0,F85-$D$75<6),ROUNDUP((F85-5)/$D$75,0),ROUNDUP(F85/$D$75,0))) -> 0 | H85: =IF(AND(F85<$D$75,F85>0),"can be merged","") | K85: 2-1 | M85: 2-1 | N85: =ROUNDUP((L84*$J$87)*$J$89,0) -> 0 | O85: =IF($L$5=0,0,IF(AND(N85>0,N85-$L$5<6),ROUNDUP((N85-5)/$L$5,0),ROUNDUP(N85/$L$5,0))) -> 0 | P85: =IF(AND(N85<$L$5,N85>0),"can be merged","")
C86: Total | F86: =SUM(F75:F85) -> 0 | G86: =SUM(G82:G85) -> 0 | J86: Retention Rate: | K86: 2-2 | M86: 2-2 | N86: =ROUNDUP((L85*$J$87)*$J$89,0) -> 0 | O86: =IF($L$5=0,0,IF(AND(N86>0,N86-$L$5<6),ROUNDUP((N86-5)/$L$5,0),ROUNDUP(N86/$L$5,0))) -> 0 | P86: =IF(AND(N86<$L$5,N86>0),"can be merged","")
B87: Tourism and Events Mgt (TEM) | C87: 1-1 | E87: 1-1 | G87: =IF($D$75=0,0,IF(AND(F87>0,F87-$D$75<6),ROUNDUP((F87-5)/$D$75,0),ROUNDUP(F87/$D$75,0))) -> 0 | H87: =IF(AND(F87<$D$75,F87>0),"can be merged","") | K87: 3-1 | M87: 3-1 | N87: =ROUNDUP((L86*$J$87)*$J$89,0) -> 0 | O87: =IF($L$5=0,0,IF(AND(N87>0,N87-$L$5<6),ROUNDUP((N87-5)/$L$5,0),ROUNDUP(N87/$L$5,0))) -> 0 | P87: =IF(AND(N87<$L$5,N87>0),"can be merged","")
B88: Retention Rate: | C88: 1-2 | E88: 1-2 | F88: =ROUNDUP((D87*$B$89)*$B$91,0) -> 0 | G88: =IF($D$75=0,0,IF(AND(F88>0,F88-$D$75<6),ROUNDUP((F88-5)/$D$75,0),ROUNDUP(F88/$D$75,0))) -> 0 | H88: =IF(AND(F88<$D$75,F88>0),"can be merged","") | J88: Migration Rate: | K88: 3-2 | M88: 3-2 | N88: =ROUNDUP((L87*$J$87)*$J$89,0) -> 0 | O88: =IF($L$5=0,0,IF(AND(N88>0,N88-$L$5<6),ROUNDUP((N88-5)/$L$5,0),ROUNDUP(N88/$L$5,0))) -> 0 | P88: =IF(AND(N88<$L$5,N88>0),"can be merged","")
C89: 2-1 | E89: 2-1 | F89: =ROUNDUP((D88*$B$89)*$B$91,0) -> 0 | G89: =IF($D$75=0,0,IF(AND(F89>0,F89-$D$75<6),ROUNDUP((F89-5)/$D$75,0),ROUNDUP(F89/$D$75,0))) -> 0 | H89: =IF(AND(F89<$D$75,F89>0),"can be merged","") | K89: 4-1 | M89: 4-1 | N89: =ROUNDUP((L88*$J$87)*$J$89,0) -> 0 | O89: =IF($L$5=0,0,IF(AND(N89>0,N89-$L$5<6),ROUNDUP((N89-5)/$L$5,0),ROUNDUP(N89/$L$5,0))) -> 0 | P89: =IF(AND(N89<$L$5,N89>0),"can be merged","")
B90: Migration Rate: | C90: 2-2 | E90: 2-2 | F90: =ROUNDUP((D89*$B$89)*$B$91,0) -> 0 | G90: =IF($D$75=0,0,IF(AND(F90>0,F90-$D$75<6),ROUNDUP((F90-5)/$D$75,0),ROUNDUP(F90/$D$75,0))) -> 0 | H90: =IF(AND(F90<$D$75,F90>0),"can be merged","") | K90: 4-2 | M90: 4-2 | N90: =ROUNDUP((L89*$J$87)*$J$89,0) -> 0 | O90: =IF($L$5=0,0,IF(AND(N90>0,N90-$L$5<6),ROUNDUP((N90-5)/$L$5,0),ROUNDUP(N90/$L$5,0))) -> 0 | P90: =IF(AND(N90<$L$5,N90>0),"can be merged","")
C91: Total | F91: =SUM(F87:F90) -> 0 | G91: =SUM(G87:G90) -> 0 | K91: Total | N91: =SUM(N83:N90) -> 0 | O91: =SUM(O83:O90) -> 0
B92: Information Technology (IT) | C92: 1-1 | E92: 1-1 | G92: =IF($D$75=0,0,IF(AND(F92>0,F92-$D$75<6),ROUNDUP((F92-5)/$D$75,0),ROUNDUP(F92/$D$75,0))) -> 0 | H92: =IF(AND(F92<$D$75,F92>0),"can be merged","") | J92: BS in Accountancy (BSA) | K92: 1-1 | M92: 1-1 | O92: =IF($L$5=0,0,IF(AND(N92>0,N92-$L$5<6),ROUNDUP((N92-5)/$L$5,0),ROUNDUP(N92/$L$5,0))) -> 0 | P92: =IF(AND(N92<$L$5,N92>0),"can be merged","")
B93: Retention Rate: | C93: 1-2 | E93: 1-2 | F93: =ROUNDUP((D92*$B$94)*$B$96,0) -> 0 | G93: =IF($D$75=0,0,IF(AND(F93>0,F93-$D$75<6),ROUNDUP((F93-5)/$D$75,0),ROUNDUP(F93/$D$75,0))) -> 0 | H93: =IF(AND(F93<$D$75,F93>0),"can be merged","") | K93: 1-2 | M93: 1-2 | N93: =ROUNDUP((L92*$J$96)*$J$98,0) -> 0 | O93: =IF($L$5=0,0,IF(AND(N93>0,N93-$L$5<6),ROUNDUP((N93-5)/$L$5,0),ROUNDUP(N93/$L$5,0))) -> 0 | P93: =IF(AND(N93<$L$5,N93>0),"can be merged","")
C94: 2-1 | E94: 2-1 | F94: =ROUNDUP((D93*$B$94)*$B$96,0) -> 0 | G94: =IF($D$75=0,0,IF(AND(F94>0,F94-$D$75<6),ROUNDUP((F94-5)/$D$75,0),ROUNDUP(F94/$D$75,0))) -> 0 | H94: =IF(AND(F94<$D$75,F94>0),"can be merged","") | K94: 2-1 | M94: 2-1 | N94: =ROUNDUP((L93*$J$96)*$J$98,0) -> 0 | O94: =IF($L$5=0,0,IF(AND(N94>0,N94-$L$5<6),ROUNDUP((N94-5)/$L$5,0),ROUNDUP(N94/$L$5,0))) -> 0 | P94: =IF(AND(N94<$L$5,N94>0),"can be merged","")
B95: Migration Rate: | C95: 2-2 | E95: 2-2 | F95: =ROUNDUP((D94*$B$94)*$B$96,0) -> 0 | G95: =IF($D$75=0,0,IF(AND(F95>0,F95-$D$75<6),ROUNDUP((F95-5)/$D$75,0),ROUNDUP(F95/$D$75,0))) -> 0 | H95: =IF(AND(F95<$D$75,F95>0),"can be merged","") | J95: Retention Rate: | K95: 2-2 | M95: 2-2 | N95: =ROUNDUP((L94*$J$96)*$J$98,0) -> 0 | O95: =IF($L$5=0,0,IF(AND(N95>0,N95-$L$5<6),ROUNDUP((N95-5)/$L$5,0),ROUNDUP(N95/$L$5,0))) -> 0 | P95: =IF(AND(N95<$L$5,N95>0),"can be merged","")
C96: Total | F96: =SUM(F92:F95) -> 0 | G96: =SUM(G92:G95) -> 0 | K96: 3-1 | M96: 3-1 | N96: =ROUNDUP((L95*$J$96)*$J$98,0) -> 0 | O96: =IF($L$5=0,0,IF(AND(N96>0,N96-$L$5<6),ROUNDUP((N96-5)/$L$5,0),ROUNDUP(N96/$L$5,0))) -> 0 | P96: =IF(AND(N96<$L$5,N96>0),"can be merged","")
B97: Assoc in Comp. Tech. (ACT) | C97: 1-1 | E97: 1-1 | G97: =IF($D$75=0,0,IF(AND(F97>0,F97-$D$75<6),ROUNDUP((F97-5)/$D$75,0),ROUNDUP(F97/$D$75,0))) -> 0 | H97: =IF(AND(F97<$D$75,F97>0),"can be merged","") | J97: Migration Rate: | K97: 3-2 | M97: 3-2 | N97: =ROUNDUP((L96*$J$96)*$J$98,0) -> 0 | O97: =IF($L$5=0,0,IF(AND(N97>0,N97-$L$5<6),ROUNDUP((N97-5)/$L$5,0),ROUNDUP(N97/$L$5,0))) -> 0 | P97: =IF(AND(N97<$L$5,N97>0),"can be merged","")
B98: Retention Rate: | C98: 1-2 | E98: 1-2 | F98: =ROUNDUP((D97*$B$99)*$B$101,0) -> 0 | G98: =IF($D$75=0,0,IF(AND(F98>0,F98-$D$75<6),ROUNDUP((F98-5)/$D$75,0),ROUNDUP(F98/$D$75,0))) -> 0 | H98: =IF(AND(F98<$D$75,F98>0),"can be merged","") | K98: 4-1 | M98: 4-1 | N98: =ROUNDUP((L97*$J$96)*$J$98,0) -> 0 | O98: =IF($L$5=0,0,IF(AND(N98>0,N98-$L$5<6),ROUNDUP((N98-5)/$L$5,0),ROUNDUP(N98/$L$5,0))) -> 0 | P98: =IF(AND(N98<$L$5,N98>0),"can be merged","")
C99: 2-1 | E99: 2-1 | F99: =ROUNDUP((D98*$B$99)*$B$101,0) -> 0 | G99: =IF($D$75=0,0,IF(AND(F99>0,F99-$D$75<6),ROUNDUP((F99-5)/$D$75,0),ROUNDUP(F99/$D$75,0))) -> 0 | H99: =IF(AND(F99<$D$75,F99>0),"can be merged","") | K99: 4-2 | M99: 4-2 | N99: =ROUNDUP((L98*$J$96)*$J$98,0) -> 0 | O99: =IF($L$5=0,0,IF(AND(N99>0,N99-$L$5<6),ROUNDUP((N99-5)/$L$5,0),ROUNDUP(N99/$L$5,0))) -> 0 | P99: =IF(AND(N99<$L$5,N99>0),"can be merged","")
B100: Migration Rate: | C100: 2-2 | E100: 2-2 | F100: =ROUNDUP((D99*$B$99)*$B$101,0) -> 0 | G100: =IF($D$75=0,0,IF(AND(F100>0,F100-$D$75<6),ROUNDUP((F100-5)/$D$75,0),ROUNDUP(F100/$D$75,0))) -> 0 | H100: =IF(AND(F100<$D$75,F100>0),"can be merged","") | K100: Total | N100: =SUM(N92:N99) -> 0 | O100: =SUM(O92:O99) -> 0
C101: Total | F101: =SUM(F97:F100) -> 0 | G101: =SUM(G97:G100) -> 0 | J101: BS in Management Accounting (BSMA) | K101: 1-1 | M101: 1-1 | O101: =IF($L$5=0,0,IF(AND(N101>0,N101-$L$5<6),ROUNDUP((N101-5)/$L$5,0),ROUNDUP(N101/$L$5,0))) -> 0 | P101: =IF(AND(N101<$L$5,N101>0),"can be merged","")
B102: Assoc in Retail Tech (ART) | C102: 1-1 | E102: 1-1 | G102: =IF($D$75=0,0,IF(AND(F102>0,F102-$D$75<6),ROUNDUP((F102-5)/$D$75,0),ROUNDUP(F102/$D$75,0))) -> 0 | H102: =IF(AND(F102<$D$75,F102>0),"can be merged","") | K102: 1-2 | M102: 1-2 | N102: =ROUNDUP((L101*$J$105)*$J$107,0) -> 0 | O102: =IF($L$5=0,0,IF(AND(N102>0,N102-$L$5<6),ROUNDUP((N102-5)/$L$5,0),ROUNDUP(N102/$L$5,0))) -> 0 | P102: =IF(AND(N102<$L$5,N102>0),"can be merged","")
...

Sheet 3.1 - Tertiary - Term 1
A1: Program | B1: Year - Term | C1: Course Code | D1: Course Title | E1: Field of Specialization | F1: LEC | G1: LAB | H1: TOTAL | I1: Section Count | J1: Teaching Load
A2: BSIT-24-01
A3: BSIT | B3: 1-1 | C3: CITE1004 | D3: Introduction to Computing | E3: Information Technology | F3: 2 | G3: 1.5 | H3: =SUM(F3:G3) -> 3.5 | I3: 6 | J3: =I3*H3 -> 21 | K3: =IF(I3>0,F3,"") -> 2
A4: BSIT | B4: 1-1 | C4: CITE1003 | D4: Computer Programming 1 | E4: Information Technology | F4: 2 | G4: 1.5 | H4: =SUM(F4:G4) -> 3.5 | I4: 6 | J4: =I4*H4 -> 21 | K4: =IF(I4>0,F4,"") -> 2
A5: BSIT | B5: 1-1 | C5: GEDC1002 | D5: The Contemporary World | F5: 3 | H5: =SUM(F5:G5) -> 3 | I5: 6 | J5: =I5*H5 -> 18 | K5: =IF(I5>0,F5,"") -> 3
A6: BSIT | B6: 1-1 | C6: STIC1002 | D6: Euthenics 1 | F6: 1 | H6: =SUM(F6:G6) -> 1 | I6: 6 | J6: =I6*H6 -> 6 | K6: =IF(I6>0,F6,"") -> 1
A7: BSIT | B7: 1-1 | C7: GEDC1016 | D7: Purposive Communication | E7: English/Foreign Language | F7: 3 | H7: =SUM(F7:G7) -> 3 | I7: 6 | J7: =I7*H7 -> 18 | K7: =IF(I7>0,F7,"") -> 3
A8: BSIT | B8: 1-1 | C8: NSTP1008 | D8: National Service Training Program 1 | F8: 3 | H8: =SUM(F8:G8) -> 3 | I8: 6 | J8: =I8*H8 -> 18 | K8: =IF(I8>0,F8,"") -> 3
A9: BSIT | B9: 1-1 | C9: PHED1005 | D9: P.E./PATHFIT 1: Movement Competency Training | E9: Physical Education | F9: 2 | H9: =SUM(F9:G9) -> 2 | I9: 6 | J9: =I9*H9 -> 12 | K9: =IF(I9>0,F9,"") -> 2
A10: BSIT | B10: 1-1 | C10: GEDC1041 | D10: Philippine Popular Culture | F10: 3 | H10: =SUM(F10:G10) -> 3 | I10: 6 | J10: =I10*H10 -> 18 | K10: =IF(I10>0,F10,"") -> 3
A11: BSIT | B11: 1-1 | C11: GEDC1008 | D11: Understanding the Self | F11: 3 | H11: =SUM(F11:G11) -> 3 | I11: 6 | J11: =I11*H11 -> 18 | K11: =IF(I11>0,F11,"") -> 3
K12: =IF(I12>0,F12,"")
A13: BSIT-22-01 | K13: =IF(I13>0,F13,"")
A14: BSIT | B14: 2-1 | C14: COSC1003 | D14: Data Structures and Algorithms | E14: Information Technology | F14: 2 | G14: 1.5 | H14: =SUM(F14:G14) -> 3.5 | I14: 5 | J14: =I14*H14 -> 17.5 | K14: =IF(I14>0,F14,"") -> 2
A15: BSIT | B15: 2-1 | C15: GEDC1006 | D15: Readings in Philippine History | E15: Social and Behavioral Science | F15: 3 | H15: =SUM(F15:G15) -> 3 | I15: 5 | J15: =I15*H15 -> 15 | K15: =IF(I15>0,F15,"") -> 3
A16: BSIT | B16: 2-1 | C16: PHED1007 | D16: P.E./PATHFIT 3: Individual-Dual Sports | E16: Physical Education | F16: 2 | H16: =SUM(F16:G16) -> 2 | I16: 5 | J16: =I16*H16 -> 10 | K16: =IF(I16>0,F16,"") -> 2
A17: BSIT | B17: 2-1 | C17: GEDC1014 | D17: Rizal's Life and Works | E17: Social and Behavioral Science | F17: 3 | H17: =SUM(F17:G17) -> 3 | I17: 5 | J17: =I17*H17 -> 15 | K17: =IF(I17>0,F17,"") -> 3
A18: BSIT | B18: 2-1 | C18: COSC1007 | D18: Human-Computer Interaction | E18: Information Technology | F18: 2 | G18: 1.5 | H18: =SUM(F18:G18) -> 3.5 | I18: 5 | J18: =I18*H18 -> 17.5 | K18: =IF(I18>0,F18,"") -> 2
A19: BSIT | B19: 2-1 | D19: IT Elective 1 | F19: 2 | G19: 1.5 | H19: =SUM(F19:G19) -> 3.5 | I19: 5 | J19: =I19*H19 -> 17.5 | K19: =IF(I19>0,F19,"") -> 2
A20: BSIT | B20: 2-1 | C20: COSC1001 | D20: Principles of Communication | E20: Information Technology | F20: 3 | H20: =SUM(F20:G20) -> 3 | I20: 5 | J20: =I20*H20 -> 15 | K20: =IF(I20>0,F20,"") -> 3
A21: BSIT | B21: 2-1 | C21: COSC1008 | D21: Platform Technology (Operating Systems) | E21: Information Technology | F21: 2 | G21: 1.5 | H21: =SUM(F21:G21) -> 3.5 | I21: 5 | J21: =I21*H21 -> 17.5 | K21: =IF(I21>0,F21,"") -> 2
K22: =IF(I22>0,F22,"")
A23: BSIT-22-01 | K23: =IF(I23>0,F23,"")
A24: BSIT | B24: 3-1 | C24: CITE1008 | D24: Application Development and Emerging Technologies | E24: Information Technology | F24: 2 | G24: 1.5 | H24: =SUM(F24:G24) -> 3.5 | I24: 4 | J24: =I24*H24 -> 14 | K24: =IF(I24>0,F24,"") -> 2
A25: BSIT | B25: 3-1 | C25: INSY1011 | D25: Advanced Database Systems | E25: Information Technology | F25: 2 | G25: 1.5 | H25: =SUM(F25:G25) -> 3.5 | I25: 4 | J25: =I25*H25 -> 14 | K25: =IF(I25>0,F25,"") -> 2
A26: BSIT | B26: 3-1 | C26: INSY1024 | D26: Event-Driven Programming | E26: Information Technology | F26: 2 | G26: 1.5 | H26: =SUM(F26:G26) -> 3.5 | I26: 4 | J26: =I26*H26 -> 14 | K26: =IF(I26>0,F26,"") -> 2
A27: BSIT | B27: 3-1 | C27: INTE1025 | D27: Data and Digital Communications (Data Communications) | E27: Information Technology | F27: 3 | H27: =SUM(F27:G27) -> 3 | I27: 4 | J27: =I27*H27 -> 12 | K27: =IF(I27>0,F27,"") -> 3
A28: BSIT | B28: 3-1 | C28: INSY1003 | D28: Professional Issues in Information Systems and Technology | E28: Information Technology | F28: 3 | H28: =SUM(F28:G28) -> 3 | I28: 4 | J28: =I28*H28 -> 12 | K28: =IF(I28>0,F28,"") -> 3
A29: BSIT | B29: 3-1 | D29: IT Elective 2 | E29: Information Technology | F29: 2 | G29: 1.5 | H29: =SUM(F29:G29) -> 3.5 | I29: 4 | J29: =I29*H29 -> 14 | K29: =IF(I29>0,F29,"") -> 2
A30: BSIT | B30: 3-1 | C30: INTE1056 | D30: Advanced Systems Integration and Architecture | E30: Information Technology | F30: 2 | G30: 1.5 | H30: =SUM(F30:G30) -> 3.5 | I30: 4 | J30: =I30*H30 -> 14 | K30: =IF(I30>0,F30,"") -> 2
K31: =IF(I31>0,F31,"")
A32: BSIT-20-01 | K32: =IF(I32>0,F32,"")
A33: BSIT | B33: 4-1 | C33: STIC1007 | D33: Euthenics 2 | F33: 1 | H33: =SUM(F33:G33) -> 1 | I33: 3 | J33: =I33*H33 -> 3 | K33: =IF(I33>0,F33,"") -> 1
A34: BSIT | B34: 4-1 | C34: INTE1039 | D34: IT Capstone Project 2 | E34: Information Technology | F34: 2 | H34: =SUM(F34:G34) -> 2 | I34: 3 | J34: =I34*H34 -> 6 | K34: =IF(I34>0,F34,"") -> 2
A35: BSIT | B35: 4-1 | D35: IT Elective 4 | E35: Information Technology | F35: 2 | G35: 1.5 | H35: =SUM(F35:G35) -> 3.5 | I35: 3 | J35: =I35*H35 -> 10.5 | K35: =IF(I35>0,F35,"") -> 2
A36: BSIT | B36: 4-1 | C36: INTE1041 | D36: Computer Graphics Programming | E36: Information Technology | F36: 2 | G36: 1.5 | H36: =SUM(F36:G36) -> 3.5 | I36: 3 | J36: =I36*H36 -> 10.5 | K36: =IF(I36>0,F36,"") -> 2
A37: BSIT | B37: 4-1 | C37: INTE1013 | D37: IT Service Management | E37: Information Technology | F37: 3 | H37: =SUM(F37:G37) -> 3 | I37: 3 | J37: =I37*H37 -> 9 | K37: =IF(I37>0,F37,"") -> 3
A38: BSIT | B38: 4-1 | C38: INSY1005 | D38: Information Assurance and Security (Data Privacy) | E38: Information Technology | F38: 2 | G38: 1.5 | H38: =SUM(F38:G38) -> 3.5 | I38: 3 | J38: =I38*H38 -> 10.5 | K38: =IF(I38>0,F38,"") -> 2
A39: BSIT | B39: 4-1 | C39: INTE1030 | D39: Network Technology 2 | E39: Information Technology | F39: 2 | G39: 1.5 | H39: =SUM(F39:G39) -> 3.5 | I39: 3 | J39: =I39*H39 -> 10.5 | K39: =IF(I39>0,F39,"") -> 2
K40: =IF(I40>0,F40,"")
A41: BSCS-24-01 | K41: =IF(I41>0,F41,"")
A42: BSCS | B42: 1-1 | C42: CITE1004 | D42: Introduction to Computing | E42: Information Technology | F42: 2 | G42: 1.5 | H42: =SUM(F42:G42) -> 3.5 | I42: 1 | J42: =I42*H42 -> 3.5 | K42: =IF(I42>0,F42,"") -> 2
A43: BSCS | B43: 1-1 | C43: CITE1003 | D43: Computer Programming 1 | E43: Information Technology | F43: 2 | G43: 1.5 | H43: =SUM(F43:G43) -> 3.5 | I43: 1 | J43: =I43*H43 -> 3.5 | K43: =IF(I43>0,F43,"") -> 2
A44: BSCS | B44: 1-1 | C44: GEDC1002 | D44: The Contemporary World | F44: 3 | H44: =SUM(F44:G44) -> 3 | I44: 1 | J44: =I44*H44 -> 3 | K44: =IF(I44>0,F44,"") -> 3
A45: BSCS | B45: 1-1 | C45: STIC1002 | D45: Euthenics 1 | F45: 1 | H45: =SUM(F45:G45) -> 1 | I45: 1 | J45: =I45*H45 -> 1 | K45: =IF(I45>0,F45,"") -> 1
A46: BSCS | B46: 1-1 | C46: GEDC1016 | D46: Purposive Communication | E46: English/Foreign Language | F46: 3 | H46: =SUM(F46:G46) -> 3 | I46: 1 | J46: =I46*H46 -> 3 | K46: =IF(I46>0,F46,"") -> 3
A47: BSCS | B47: 1-1 | C47: NSTP1008 | D47: National Service Training Program 1 | F47: 3 | H47: =SUM(F47:G47) -> 3 | I47: 1 | J47: =I47*H47 -> 3 | K47: =IF(I47>0,F47,"") -> 3
A48: BSCS | B48: 1-1 | C48: PHED1005 | D48: P.E./PATHFIT 1: Movement Competency Training | E48: Physical Education | F48: 2 | H48: =SUM(F48:G48) -> 2 | I48: 1 | J48: =I48*H48 -> 2 | K48: =IF(I48>0,F48,"") -> 2
A49: BSCS | B49: 1-1 | C49: GEDC1008 | D49: Understanding the Self | F49: 3 | H49: =SUM(F49:G49) -> 3 | I49: 1 | J49: =I49*H49 -> 3 | K49: =IF(I49>0,F49,"") -> 3
K50: =IF(I50>0,F50,"")
A51: BSCS-22-01 | K51: =IF(I51>0,F51,"")
A52: BSCS | B52: 2-1 | C52: COSC1003 | D52: Data Structures and Algorithms | E52: Information Technology | F52: 2 | G52: 1.5 | H52: =SUM(F52:G52) -> 3.5 | I52: 1 | J52: =I52*H52 -> 3.5 | K52: =IF(I52>0,F52,"") -> 2
A53: BSCS | B53: 2-1 | C53: COSC1006 | D53: Discrete Structures 2 | E53: Information Technology | F53: 3 | H53: =SUM(F53:G53) -> 3 | I53: 1 | J53: =I53*H53 -> 3 | K53: =IF(I53>0,F53,"") -> 3
A54: BSCS | B54: 2-1 | C54: GEDC1003 | D54: The Entrepreneurial Mind | E54: Business and Management | F54: 3 | H54: =SUM(F54:G54) -> 3 | I54: 1 | J54: =I54*H54 -> 3 | K54: =IF(I54>0,F54,"") -> 3
A55: BSCS | B55: 2-1 | C55: PHED1007 | D55: P.E./PATHFIT 3: Individual-Dual Sports | E55: Physical Education | F55: 2 | H55: =SUM(F55:G55) -> 2 | I55: 1 | J55: =I55*H55 -> 2 | K55: =IF(I55>0,F55,"") -> 2
A56: BSCS | B56: 2-1 | C56: GEDC1006 | D56: Readings in Philippine History | E56: Social and Behavioral Science | F56: 3 | H56: =SUM(F56:G56) -> 3 | I56: 1 | J56: =I56*H56 -> 3 | K56: =IF(I56>0,F56,"") -> 3
A57: BSCS | B57: 2-1 | C57: COSC1001 | D57: Principles of Communication | E57: Information Technology | F57: 3 | H57: =SUM(F57:G57) -> 3 | I57: 1 | J57: =I57*H57 -> 3 | K57: =IF(I57>0,F57,"") -> 3
A58: BSCS | B58: 2-1 | C58: CITE1010 | D58: Computer Programming 3 | E58: Information Technology | F58: 2 | G58: 1.5 | H58: =SUM(F58:G58) -> 3.5 | I58: 1 | J58: =I58*H58 -> 3.5 | K58: =IF(I58>0,F58,"") -> 2
A59: BSCS | B59: 2-1 | C59: GEDC1014 | D59: Rizal's Life and Works | E59: Social and Behavioral Science | F59: 3 | H59: =SUM(F59:G59) -> 3 | I59: 1 | J59: =I59*H59 -> 3 | K59: =IF(I59>0,F59,"") -> 3
K60: =IF(I60>0,F60,"")
A61: BSCS-22-01 | K61: =IF(I61>0,F61,"")
A62: BSCS | B62: 3-1 | C62: COSC1014 | D62: Theory of Computations with Automata | E62: Information Technology | F62: 3 | H62: =SUM(F62:G62) -> 3 | I62: 1 | J62: =I62*H62 -> 3 | K62: =IF(I62>0,F62,"") -> 3
A63: BSCS | B63: 3-1 | C63: CITE1008 | D63: Application Development and Emerging Technologies | E63: Information Technology | F63: 2 | G63: 1.5 | H63: =SUM(F63:G63) -> 3.5 | I63: 1 | J63: =I63*H63 -> 3.5 | K63: =IF(I63>0,F63,"") -> 2
A64: BSCS | B64: 3-1 | C64: INSY1010 | D64: Information Assurance and Security (Cybersecurity Fundamentals) | E64: Information Technology | F64: 2 | G64: 1.5 | H64: =SUM(F64:G64) -> 3.5 | I64: 1 | J64: =I64*H64 -> 3.5 | K64: =IF(I64>0,F64,"") -> 2
A65: BSCS | B65: 3-1 | C65: INTE1007 | D65: Quantitative Methods (Data Analysis) | E65: Information Technology | F65: 3 | H65: =SUM(F65:G65) -> 3 | I65: 1 | J65: =I65*H65 -> 3 | K65: =IF(I65>0,F65,"") -> 3
A66: BSCS | B66: 3-1 | D66: CS Elective 2 | E66: Information Technology | F66: 2 | G66: 1.5 | H66: =SUM(F66:G66) -> 3.5 | I66: 1 | J66: =I66*H66 -> 3.5 | K66: =IF(I66>0,F66,"") -> 2
A67: BSCS | B67: 3-1 | C67: COSC1028 | D67: Artificial Intelligence | E67: Information Technology | F67: 3 | H67: =SUM(F67:G67) -> 3 | I67: 1 | J67: =I67*H67 -> 3 | K67: =IF(I67>0,F67,"") -> 3
A68: BSCS | B68: 3-1 | C68: COSC1021 | D68: Software Engineering 1 | E68: Information Technology | F68: 2 | G68: 1.5 | H68: =SUM(F68:G68) -> 3.5 | I68: 1 | J68: =I68*H68 -> 3.5 | K68: =IF(I68>0,F68,"") -> 2
A69: BSCS | B69: 3-1 | C69: COSC1048 | D69: Methods of Research | E69: Information Technology | F69: 3 | H69: =SUM(F69:G69) -> 3 | I69: 1 | J69: =I69*H69 -> 3 | K69: =IF(I69>0,F69,"") -> 3
K70: =IF(I70>0,F70,"")
A71: BSCS-20-01 | K71: =IF(I71>0,F71,"")
A72: BSCS | B72: 4-1 | C72: COSC1008 | D72: Platform Technology (Operating Systems) | E72: Information Technology | F72: 2 | G72: 1.5 | H72: =SUM(F72:G72) -> 3.5 | I72: 1 | J72: =I72*H72 -> 3.5 | K72: =IF(I72>0,F72,"") -> 2
A73: BSCS | B73: 4-1 | C73: INTE1005 | D73: Network Technology | E73: Information Technology | F73: 2 | G73: 1.5 | H73: 2 | I73: 1 | J73: =I73*H73 -> 2 | K73: =IF(I73>0,F73,"") -> 2
A74: BSCS | B74: 4-1 | C74: COSC1050 | D74: CS Thesis 2 | E74: Information Technology | F74: 2 | H74: 2 | I74: 1 | J74: =I74*H74 -> 2 | K74: =IF(I74>0,F74,"") -> 2
A75: BSCS | B75: 4-1 | C75: STIC1007 | D75: Euthenics 2 | F75: 1 | H75: =SUM(F75:G75) -> 1 | I75: 1 | J75: =I75*H75 -> 1 | K75: =IF(I75>0,F75,"") -> 1
A76: BSCS | B76: 4-1 | C76: BUSS1013 | D76: Technopreneurship | E76: Business and Management | F76: 3 | H76: =SUM(F76:G76) -> 3 | I76: 1 | J76: =I76*H76 -> 3 | K76: =IF(I76>0,F76,"") -> 3
A77: BSCS | B77: 4-1 | C77: INSY1003 | D77: Professional Issues in Information Systems and Technology | E77: Information Technology | F77: 3 | H77: =SUM(F77:G77) -> 3 | I77: 1 | J77: =I77*H77 -> 3 | K77: =IF(I77>0,F77,"") -> 3
A78: BSCS | B78: 4-1 | C78: INSY1005 | D78: Information Assurance and Security (Data Privacy) | E78: Information Technology | F78: 2 | G78: 1.5 | H78: =SUM(F78:G78) -> 3.5 | I78: 1 | J78: =I78*H78 -> 3.5 | K78: =IF(I78>0,F78,"") -> 2
A79: BSCS | B79: 4-1 | C79: INSY1027 | D79: Software Quality Assurance | E79: Information Technology | F79: 3 | H79: =SUM(F79:G79) -> 3 | I79: 1 | J79: =I79*H79 -> 3 | K79: =IF(I79>0,F79,"") -> 3
K80: =IF(I80>0,F80,"")
A81: BSCPE-22-01 | K81: =IF(I81>0,F81,"")
A82: BSCPE | B82: 1-1 | C82: ENGR1001 | D82: Programming Logic and Design | E82: Information Technology | G82: 3 | H82: =SUM(F82:G82) -> 3 | I82: 1 | J82: =I82*H82 -> 3 | K82: =IF(I82>0,F82,"") -> 0
A83: BSCPE | B83: 1-1 | C83: GEDC1002 | D83: The Contemporaray World | E83: Social and Behavioral Science | F83: 3 | H83: =SUM(F83:G83) -> 3 | I83: 1 | J83: =I83*H83 -> 3 | K83: =IF(I83>0,F83,"") -> 3
A84: BSCPE | B84: 1-1 | C84: STIC1002 | D84: Euthenics 1 | F84: 1 | H84: =SUM(F84:G84) -> 1 | I84: 1 | J84: =I84*H84 -> 1 | K84: =IF(I84>0,F84,"") -> 1
A85: BSCPE | B85: 1-1 | C85: GEDC1005 | D85: Mathematics in the Modern World | E85: Mathematics | F85: 3 | H85: =SUM(F85:G85) -> 3 | I85: 1 | J85: =I85*H85 -> 3 | K85: =IF(I85>0,F85,"") -> 3
A86: BSCPE | B86: 1-1 | C86: NSTP1008 | D86: National Service Training Program 1 | F86: 3 | H86: =SUM(F86:G86) -> 3 | I86: 1 | J86: =I86*H86 -> 3 | K86: =IF(I86>0,F86,"") -> 3
A87: BSCPE | B87: 1-1 | C87: PHED1005 | D87: P.E./PATHFIT 1: Movement Competency Training | E87: Physical Education | F87: 2 | H87: =SUM(F87:G87) -> 2 | I87: 1 | J87: =I87*H87 -> 2 | K87: =IF(I87>0,F87,"") -> 2
A88: BSCPE | B88: 1-1 | C88: GEDC1008 | D88: Understanding the Self | F88: 3 | H88: =SUM(F88:G88) -> 3 | I88: 1 | J88: =I88*H88 -> 3 | K88: =IF(I88>0,F88,"") -> 3
A89: BSCPE | B89: 1-1 | C89: ENGR1002 | D89: College Calculus (Differential) | E89: Engineering | F89: 3 | H89: =SUM(F89:G89) -> 3 | I89: 1 | J89: =I89*H89 -> 3 | K89: =IF(I89>0,F89,"") -> 3
A90: BSCPE | B90: 1-1 | C90: ENGR1003 | D90: Chemistry for Engineers | E90: Engineering | F90: 3 | G90: 1.5 | H90: =SUM(F90:G90) -> 4.5 | I90: 1 | J90: =I90*H90 -> 4.5 | K90: =IF(I90>0,F90,"") -> 3
A91: BSCPE | B91: 1-1 | C91: ENGR1004 | D91: Computer Engineering as a Discipline | E91: Engineering | F91: 1 | H91: =SUM(F91:G91) -> 1 | I91: 1 | J91: =I91*H91 -> 1 | K91: =IF(I91>0,F91,"") -> 1
K92: =IF(I92>0,F92,"")
A93: BSCPE-22-01 | K93: =IF(I93>0,F93,"")
A94: BSCPE | B94: 2-1 | C94: ENGR1008 | D94: Fundamentals of Electrical Circuits | E94: Engineering | F94: 3 | G94: 1.5 | H94: =SUM(F94:G94) -> 4.5 | I94: 1 | J94: =I94*H94 -> 4.5 | K94: =IF(I94>0,F94,"") -> 3
A95: BSCPE | B95: 2-1 | C95: ENGR1009 | D95: Operating Systems | E95: Information Technology | F95: 3 | H95: =SUM(F95:G95) -> 3 | I95: 1 | J95: =I95*H95 -> 3 | K95: =IF(I95>0,F95,"") -> 3
A96: BSCPE | B96: 2-1 | C96: COSC1004 | D96: Data Structures and Algorithms | E96: Information Technology | G96: 3 | H96: =SUM(F96:G96) -> 3 | I96: 1 | J96: =I96*H96 -> 3 | K96: =IF(I96>0,F96,"") -> 0
A97: BSCPE | B97: 2-1 | C97: ENGR1010 | D97: Emerging Technologies in CpE | E97: Engineering | F97: 3 | H97: =SUM(F97:G97) -> 3 | I97: 1 | J97: =I97*H97 -> 3 | K97: =IF(I97>0,F97,"") -> 3
A98: BSCPE | B98: 2-1 | C98: GEDC1003 | D98: The Entrepreneurial Mind | E98: Business and Management | F98: 3 | H98: =SUM(F98:G98) -> 3 | I98: 1 | J98: =I98*H98 -> 3 | K98: =IF(I98>0,F98,"") -> 3
A99: BSCPE | B99: 2-1 | C99: GEDC1014 | D99: Rizal's Life and Works | E99: Social and Behavioral Science | F99: 3 | H99: =SUM(F99:G99) -> 3 | I99: 1 | J99: =I99*H99 -> 3 | K99: =IF(I99>0,F99,"") -> 3
A100: BSCPE | B100: 2-1 | C100: PHED1007 | D100: P.E./PATHFIT 3: Individual-Dual Sports | E100: Physical Education | F100: 2 | H100: =SUM(F100:G100) -> 2 | I100: 1 | J100: =I100*H100 -> 2 | K100: =IF(I100>0,F100,"") -> 2
...

Sheet 3.2 - Tertiary - Term 2
A1: Program | B1: Year - Term | C1: Course Code | D1: Course Title | E1: Field of Specialization | F1: LEC | G1: LAB | H1: TOTAL | I1: Section Count | J1: Teaching Load
A2: BSIT-24-01
A3: BSIT | B3: 1-2 | C3: CITE1006 | D3: Computer Programming 2 | E3: Information Technology | F3: 2 | G3: 1.5 | H3: =SUM(F3:G3) -> 3.5 | I3: ='2 - Section Count Projection'!$O$12 -> 0 | J3: =I3*H3 -> 0 | K3: =IF(I3>0,F3,"")
A4: BSIT | B4: 1-2 | C4: COSC1002 | D4: Discrete Structures 1 (Discrete Mathematics) | E4: Information Technology | F4: 3 | H4: =SUM(F4:G4) -> 3 | I4: ='2 - Section Count Projection'!$O$12 -> 0 | J4: =I4*H4 -> 0 | K4: =IF(I4>0,F4,"")
A5: BSIT | B5: 1-2 | C5: GEDC1010 | D5: Art Appreciation | E5: Social and Behavioral Science | F5: 3 | H5: =SUM(F5:G5) -> 3 | I5: ='2 - Section Count Projection'!$O$12 -> 0 | J5: =I5*H5 -> 0 | K5: =IF(I5>0,F5,"")
A6: BSIT | B6: 1-2 | C6: NSTP1010 | D6: National Service Training Program 2 | F6: 3 | H6: =SUM(F6:G6) -> 3 | I6: ='2 - Section Count Projection'!$O$12 -> 0 | J6: =I6*H6 -> 0 | K6: =IF(I6>0,F6,"")
A7: BSIT | B7: 1-2 | C7: PHED1006 | D7: PE/PATHFIT 2: Exercise-based Fitness Activities | E7: Physical Education | F7: 2 | H7: =SUM(F7:G7) -> 2 | I7: ='2 - Section Count Projection'!$O$12 -> 0 | J7: =I7*H7 -> 0 | K7: =IF(I7>0,F7,"")
A8: BSIT | B8: 1-2 | C8: GEDC1005 | D8: Mathematics in the Modern World | E8: Mathematics | F8: 3 | H8: =SUM(F8:G8) -> 3 | I8: ='2 - Section Count Projection'!$O$12 -> 0 | J8: =I8*H8 -> 0 | K8: =IF(I8>0,F8,"")
A9: BSIT | B9: 1-2 | C9: GEDC1013 | D9: Science, Technology, and Society | F9: 3 | H9: =SUM(F9:G9) -> 3 | I9: ='2 - Section Count Projection'!$O$12 -> 0 | J9: =I9*H9 -> 0 | K9: =IF(I9>0,F9,"")
A10: BSIT | B10: 1-2 | C10: GEDC1009 | D10: Ethics | E10: Social and Behavioral Science | F10: 3 | H10: =SUM(F10:G10) -> 3 | I10: ='2 - Section Count Projection'!$O$12 -> 0 | J10: =I10*H10 -> 0 | K10: =IF(I10>0,F10,"")
A11: BSIT | B11: 1-2 | C11: INTE1006 | D11: Systems Administration and Maintenance | E11: Information Technology | F11: 2 | G11: 1.5 | H11: =SUM(F11:G11) -> 3.5 | I11: ='2 - Section Count Projection'!$O$12 -> 0 | J11: =I11*H11 -> 0 | K11: =IF(I11>0,F11,"")
K12: =IF(I12>0,F12,"")
A13: BSIT-22-01 | K13: =IF(I13>0,F13,"")
A14: BSIT | B14: 2-2 | C14: CITE1011 | D14: Information Management | E14: Information Technology | F14: 2 | G14: 1.5 | H14: =SUM(F14:G14) -> 3.5 | I14: ='2 - Section Count Projection'!$O$14 -> 0 | J14: =I14*H14 -> 0 | K14: =IF(I14>0,F14,"")
A15: BSIT | B15: 2-2 | C15: GEDC1041 | D15: Philippine Popular Culture | F15: 3 | H15: =SUM(F15:G15) -> 3 | I15: ='2 - Section Count Projection'!$O$14 -> 0 | J15: =I15*H15 -> 0 | K15: =IF(I15>0,F15,"")
A16: BSIT | B16: 2-2 | C16: PHED1008 | D16: P.E./PATHFIT 4: Team Sports | E16: Physical Education | F16: 2 | H16: =SUM(F16:G16) -> 2 | I16: ='2 - Section Count Projection'!$O$14 -> 0 | J16: =I16*H16 -> 0 | K16: =IF(I16>0,F16,"")
A17: BSIT | B17: 2-2 | C17: INTE1005 | D17: Network Technology 1 | E17: Information Technology | F17: 2 | G17: 1.5 | H17: =SUM(F17:G17) -> 3.5 | I17: ='2 - Section Count Projection'!$O$14 -> 0 | J17: =I17*H17 -> 0 | K17: =IF(I17>0,F17,"")
A18: BSIT | B18: 2-2 | C18: INTE1020 | D18: Quantitative Methods | E18: Mathematics | F18: 3 | H18: =SUM(F18:G18) -> 3 | I18: ='2 - Section Count Projection'!$O$14 -> 0 | J18: =I18*H18 -> 0 | K18: =IF(I18>0,F18,"")
A19: BSIT | B19: 2-2 | C19: BUSS1013 | D19: Technopreneurship | E19: Business and Management | F19: 3 | H19: =SUM(F19:G19) -> 3 | I19: ='2 - Section Count Projection'!$O$14 -> 0 | J19: =I19*H19 -> 0 | K19: =IF(I19>0,F19,"")
A20: BSIT | B20: 2-2 | C20: INTE1021 | D20: Systems Integration and Architecture | E20: Information Technology | F20: 2 | G20: 1.5 | H20: =SUM(F20:G20) -> 3.5 | I20: ='2 - Section Count Projection'!$O$14 -> 0 | J20: =I20*H20 -> 0 | K20: =IF(I20>0,F20,"")
A21: BSIT | B21: 2-2 | C21: INTE1010 | D21: Integrative Programming | E21: Information Technology | F21: 2 | G21: 1.5 | H21: =SUM(F21:G21) -> 3.5 | I21: ='2 - Section Count Projection'!$O$14 -> 0 | J21: =I21*H21 -> 0 | K21: =IF(I21>0,F21,"")
K22: =IF(I22>0,F22,"")
A23: BSIT-22-01 | K23: =IF(I23>0,F23,"")
A24: BSIT | B24: 3-2 | C24: INTE1083 | D24: Web Systems and Technologies | E24: Information Technology | F24: 2 | G24: 1.5 | H24: =SUM(F24:G24) -> 3.5 | I24: ='2 - Section Count Projection'!$O$16 -> 0 | J24: =I24*H24 -> 0 | K24: =IF(I24>0,F24,"")
A25: BSIT | B25: 3-2 | C25: INSY1007 | D25: Management Information Systems | E25: Information Technology | F25: 3 | H25: =SUM(F25:G25) -> 3 | I25: ='2 - Section Count Projection'!$O$16 -> 0 | J25: =I25*H25 -> 0 | K25: =IF(I25>0,F25,"")
A26: BSIT | B26: 3-2 | C26: INTE1031 | D26: IT Capstone Project 1 | E26: Information Technology | F26: 2 | H26: 2 | I26: ='2 - Section Count Projection'!$O$16 -> 0 | J26: =I26*H26 -> 0 | K26: =IF(I26>0,F26,"")
A27: BSIT | B27: 3-2 | C27: GEDC1045 | D27: Great Books | E27: English/Foreign Language | F27: 3 | H27: =SUM(F27:G27) -> 3 | I27: ='2 - Section Count Projection'!$O$16 -> 0 | J27: =I27*H27 -> 0 | K27: =IF(I27>0,F27,"")
A28: BSIT | B28: 3-2 | D28: IT Elective 3 | E28: Information Technology | F28: 2 | G28: 1.5 | H28: =SUM(F28:G28) -> 3.5 | I28: ='2 - Section Count Projection'!$O$16 -> 0 | J28: =I28*H28 -> 0 | K28: =IF(I28>0,F28,"")
A29: BSIT | B29: 3-2 | C29: INTE1084 | D29: Mobile Systems and Technologies | E29: Information Technology | F29: 2 | G29: 1.5 | H29: =SUM(F29:G29) -> 3.5 | I29: ='2 - Section Count Projection'!$O$16 -> 0 | J29: =I29*H29 -> 0 | K29: =IF(I29>0,F29,"")
A30: BSIT | B30: 3-2 | C30: INSY1010 | D30: Information Assurance and Security (Cybersecurity Fundamentals ) | E30: Information Technology | F30: 2 | G30: 1.5 | H30: =SUM(F30:G30) -> 3.5 | I30: ='2 - Section Count Projection'!$O$16 -> 0 | J30: =I30*H30 -> 0 | K30: =IF(I30>0,F30,"")
K31: =IF(I31>0,F31,"")
A32: BSIT-20-01 | K32: =IF(I32>0,F32,"")
A33: BSIT | B33: 4-2 | C33: INTE1043 | D33: IT Practicum (486 hours) | E33: Information Technology | F33: 0 | G33: 3 | H33: 3 | I33: ='2 - Section Count Projection'!$O$18 -> 0 | J33: =I33*H33 -> 0 | K33: =IF(I33>0,F33,"")
K34: =IF(I34>0,F34,"")
A35: BSCS-24-01 | K35: =IF(I35>0,F35,"")
A36: BSCS | B36: 1-2 | C36: CITE1006 | D36: Computer Programming 2 | E36: Information Technology | F36: 2 | G36: 1.5 | H36: =SUM(F36:G36) -> 3.5 | I36: ='2 - Section Count Projection'!$O$21 -> 0 | J36: =I36*H36 -> 0 | K36: =IF(I36>0,F36,"")
A37: BSCS | B37: 1-2 | C37: COSC1002 | D37: Discrete Structures 1 (Discrete Mathematics) | E37: Information Technology | F37: 3 | H37: =SUM(F37:G37) -> 3 | I37: ='2 - Section Count Projection'!$O$21 -> 0 | J37: =I37*H37 -> 0 | K37: =IF(I37>0,F37,"")
A38: BSCS | B38: 1-2 | C38: GEDC1010 | D38: Art Appreciation | E38: Social and Behavioral Science | F38: 3 | H38: =SUM(F38:G38) -> 3 | I38: ='2 - Section Count Projection'!$O$21 -> 0 | J38: =I38*H38 -> 0 | K38: =IF(I38>0,F38,"")
A39: BSCS | B39: 1-2 | C39: NSTP1010 | D39: National Service Training Program 2 | F39: 3 | H39: =SUM(F39:G39) -> 3 | I39: ='2 - Section Count Projection'!$O$21 -> 0 | J39: =I39*H39 -> 0 | K39: =IF(I39>0,F39,"")
A40: BSCS | B40: 1-2 | C40: PHED1006 | D40: P.E./PATHFIT 2: Exercise-based Fitness Activities | E40: Physical Education | F40: 2 | H40: =SUM(F40:G40) -> 2 | I40: ='2 - Section Count Projection'!$O$21 -> 0 | J40: =I40*H40 -> 0 | K40: =IF(I40>0,F40,"")
A41: BSCS | B41: 1-2 | C41: GEDC1005 | D41: Mathematics in the Modern World | E41: Mathematics | F41: 3 | H41: =SUM(F41:G41) -> 3 | I41: ='2 - Section Count Projection'!$O$21 -> 0 | J41: =I41*H41 -> 0 | K41: =IF(I41>0,F41,"")
A42: BSCS | B42: 1-2 | C42: GEDC1013 | D42: Science, Technology, and Society | F42: 3 | H42: =SUM(F42:G42) -> 3 | I42: ='2 - Section Count Projection'!$O$21 -> 0 | J42: =I42*H42 -> 0 | K42: =IF(I42>0,F42,"")
A43: BSCS | B43: 1-2 | C43: COSC1046 | D43: College Calculus | E43: Mathematics | F43: 3 | H43: =SUM(F43:G43) -> 3 | I43: ='2 - Section Count Projection'!$O$21 -> 0 | J43: =I43*H43 -> 0 | K43: =IF(I43>0,F43,"")
K44: =IF(I44>0,F44,"")
A45: BSCS-22-01 | K45: =IF(I45>0,F45,"")
A46: BSCS | B46: 2-2 | C46: COSC1009 | D46: Design and Analysis of Algorithms | E46: Information Technology | F46: 3 | H46: =SUM(F46:G46) -> 3 | I46: ='2 - Section Count Projection'!$O$23 -> 0 | J46: =I46*H46 -> 0 | K46: =IF(I46>0,F46,"")
A47: BSCS | B47: 2-2 | C47: CITE1011 | D47: Information Management | E47: Information Technology | F47: 2 | G47: 1.5 | H47: =SUM(F47:G47) -> 3.5 | I47: ='2 - Section Count Projection'!$O$23 -> 0 | J47: =I47*H47 -> 0 | K47: =IF(I47>0,F47,"")
A48: BSCS | B48: 2-2 | C48: GEDC1041 | D48: Philippine Popular Culture | F48: 3 | H48: =SUM(F48:G48) -> 3 | I48: ='2 - Section Count Projection'!$O$23 -> 0 | J48: =I48*H48 -> 0 | K48: =IF(I48>0,F48,"")
A49: BSCS | B49: 2-2 | C49: GEDC1009 | D49: Ethics | E49: Social and Behavioral Science | F49: 3 | H49: =SUM(F49:G49) -> 3 | I49: ='2 - Section Count Projection'!$O$23 -> 0 | J49: =I49*H49 -> 0 | K49: =IF(I49>0,F49,"")
A50: BSCS | B50: 2-2 | C50: PHED1008 | D50: P.E./PATHFIT 4: Team Sports | E50: Physical Education | F50: 2 | H50: =SUM(F50:G50) -> 2 | I50: ='2 - Section Count Projection'!$O$23 -> 0 | J50: =I50*H50 -> 0 | K50: =IF(I50>0,F50,"")
A51: BSCS | B51: 2-2 | C51: INTE1023 | D51: Computer Systems Architecture | E51: Information Technology | F51: 3 | H51: =SUM(F51:G51) -> 3 | I51: ='2 - Section Count Projection'!$O$23 -> 0 | J51: =I51*H51 -> 0 | K51: =IF(I51>0,F51,"")
A52: BSCS | B52: 2-2 | C52: COSC1007 | D52: Human-Computer Interaction | E52: Information Technology | F52: 2 | G52: 1.5 | H52: =SUM(F52:G52) -> 3.5 | I52: ='2 - Section Count Projection'!$O$23 -> 0 | J52: =I52*H52 -> 0 | K52: =IF(I52>0,F52,"")
A53: BSCS | B53: 2-2 | D53: CS Elective 1 | E53: Information Technology | F53: 2 | G53: 1.5 | H53: =SUM(F53:G53) -> 3.5 | I53: ='2 - Section Count Projection'!$O$23 -> 0 | J53: =I53*H53 -> 0 | K53: =IF(I53>0,F53,"")
A54: BSCS | B54: 2-2 | C54: GEDC1045 | D54: Great Books | E54: English/Foreign Language | F54: 3 | H54: =SUM(F54:G54) -> 3 | I54: ='2 - Section Count Projection'!$O$23 -> 0 | J54: =I54*H54 -> 0 | K54: =IF(I54>0,F54,"")
K55: =IF(I55>0,F55,"")
A56: BSCS-22-01 | K56: =IF(I56>0,F56,"")
A57: BSCS | B57: 3-2 | C57: COSC1016 | D57: Modeling and Simulation | E57: Information Technology | F57: 3 | H57: =SUM(F57:G57) -> 3 | I57: ='2 - Section Count Projection'!$O$25 -> 0 | J57: =I57*H57 -> 0 | K57: =IF(I57>0,F57,"")
A58: BSCS | B58: 3-2 | C58: COSC1042 | D58: Game Programming | E58: Information Technology | F58: 2 | G58: 1.5 | H58: =SUM(F58:G58) -> 3.5 | I58: ='2 - Section Count Projection'!$O$25 -> 0 | J58: =I58*H58 -> 0 | K58: =IF(I58>0,F58,"")
A59: BSCS | B59: 3-2 | C59: COSC1020 | D59: Programming Languages | E59: Information Technology | F59: 2 | G59: 1.5 | H59: =SUM(F59:G59) -> 3.5 | I59: ='2 - Section Count Projection'!$O$25 -> 0 | J59: =I59*H59 -> 0 | K59: =IF(I59>0,F59,"")
A60: BSCS | B60: 3-2 | C60: CITE1013 | D60: Computer Organization | E60: Information Technology | F60: 3 | H60: =SUM(F60:G60) -> 3 | I60: ='2 - Section Count Projection'!$O$25 -> 0 | J60: =I60*H60 -> 0 | K60: =IF(I60>0,F60,"")
A61: BSCS | B61: 3-2 | C61: COSC1025 | D61: Software Engineering 2 | E61: Information Technology | F61: 2 | G61: 1.5 | H61: =SUM(F61:G61) -> 3.5 | I61: ='2 - Section Count Projection'!$O$25 -> 0 | J61: =I61*H61 -> 0 | K61: =IF(I61>0,F61,"")
A62: BSCS | B62: 3-2 | D62: CS Elective 3 | E62: Information Technology | F62: 2 | G62: 1.5 | H62: =SUM(F62:G62) -> 3.5 | I62: ='2 - Section Count Projection'!$O$25 -> 0 | J62: =I62*H62 -> 0 | K62: =IF(I62>0,F62,"")
A63: BSCS | B63: 3-2 | C63: COSC1049 | D63: CS Thesis 1 | E63: Information Technology | F63: 2 | H63: 2 | I63: ='2 - Section Count Projection'!$O$25 -> 0 | J63: =I63*H63 -> 0 | K63: =IF(I63>0,F63,"")
K64: =IF(I64>0,F64,"")
A65: BSCS-20-01 | K65: =IF(I65>0,F65,"")
A66: BSCS | B66: 4-2 | C66: COSC1051 | D66: CS Practicum (300 hours) | E66: Information Technology | G66: 3 | H66: 3 | I66: ='2 - Section Count Projection'!$O$27 -> 0 | J66: =I66*H66 -> 0 | K66: =IF(I66>0,F66,"")
K67: =IF(I67>0,F67,"")
A68: BSCPE-22-01 | K68: =IF(I68>0,F68,"")
A69: BSCPE | B69: 1-2 | C69: INTE1001 | D69: Object-Oriented Programming | E69: Information Technology | G69: =2*1.5 -> 3 | H69: =SUM(F69:G69) -> 3 | I69: ='2 - Section Count Projection'!$O$39 -> 0 | J69: =I69*H69 -> 0 | K69: =IF(I69>0,F69,"")
A70: BSCPE | B70: 1-2 | C70: ENGR1048 | D70: Discrete Mathematics | E70: Engineering | F70: 3 | H70: =SUM(F70:G70) -> 3 | I70: ='2 - Section Count Projection'!$O$39 -> 0 | J70: =I70*H70 -> 0 | K70: =IF(I70>0,F70,"")
A71: BSCPE | B71: 1-2 | C71: GEDC1010 | D71: Art Appreciation | E71: Social and Behavioral Science | F71: 3 | H71: =SUM(F71:G71) -> 3 | I71: ='2 - Section Count Projection'!$O$39 -> 0 | J71: =I71*H71 -> 0 | K71: =IF(I71>0,F71,"")
A72: BSCPE | B72: 1-2 | C72: NSTP1010 | D72: National Service Training Program 2 | F72: 3 | H72: =SUM(F72:G72) -> 3 | I72: ='2 - Section Count Projection'!$O$39 -> 0 | J72: =I72*H72 -> 0 | K72: =IF(I72>0,F72,"")
A73: BSCPE | B73: 1-2 | C73: PHED1006 | D73: P.E./PATHFIT 2: Exercise-based Fitness Activities | E73: Physical Education | F73: 2 | H73: =SUM(F73:G73) -> 2 | I73: ='2 - Section Count Projection'!$O$39 -> 0 | J73: =I73*H73 -> 0 | K73: =IF(I73>0,F73,"")
A74: BSCPE | B74: 1-2 | C74: GEDC1016 | D74: Purposive Communication | E74: English/Foreign Language | F74: 3 | H74: =SUM(F74:G74) -> 3 | I74: ='2 - Section Count Projection'!$O$39 -> 0 | J74: =I74*H74 -> 0 | K74: =IF(I74>0,F74,"")
A75: BSCPE | B75: 1-2 | C75: GEDC1013 | D75: Science, Technology, and Society | F75: 3 | H75: =SUM(F75:G75) -> 3 | I75: ='2 - Section Count Projection'!$O$39 -> 0 | J75: =I75*H75 -> 0 | K75: =IF(I75>0,F75,"")
A76: BSCPE | B76: 1-2 | C76: ENGR1005 | D76: College Calculus (Integral) | E76: Engineering | F76: 3 | H76: =SUM(F76:G76) -> 3 | I76: ='2 - Section Count Projection'!$O$39 -> 0 | J76: =I76*H76 -> 0 | K76: =IF(I76>0,F76,"")
A77: BSCPE | B77: 1-2 | C77: ENGR1007 | D77: Physics for Engineers | E77: Engineering | F77: 3 | G77: 1.5 | H77: =SUM(F77:G77) -> 4.5 | I77: ='2 - Section Count Projection'!$O$39 -> 0 | J77: =I77*H77 -> 0 | K77: =IF(I77>0,F77,"")
K78: =IF(I78>0,F78,"")
A79: BSCPE-22-01 | K79: =IF(I79>0,F79,"")
A80: BSCPE | B80: 2-2 | C80: ENGR1012 | D80: Numerical Methods | E80: Engineering | F80: 3 | H80: =SUM(F80:G80) -> 3 | I80: ='2 - Section Count Projection'!$O$41 -> 0 | J80: =I80*H80 -> 0 | K80: =IF(I80>0,F80,"")
A81: BSCPE | B81: 2-2 | C81: ENGR1013 | D81: Fundamentals of Electronic Circuits | E81: Engineering | F81: 3 | G81: 1.5 | H81: =SUM(F81:G81) -> 4.5 | I81: ='2 - Section Count Projection'!$O$41 -> 0 | J81: =I81*H81 -> 0 | K81: =IF(I81>0,F81,"")
A82: BSCPE | B82: 2-2 | C82: ENGR1014 | D82: Software Design | E82: Information Technology | F82: 3 | G82: 1.5 | H82: =SUM(F82:G82) -> 4.5 | I82: ='2 - Section Count Projection'!$O$41 -> 0 | J82: =I82*H82 -> 0 | K82: =IF(I82>0,F82,"")
A83: BSCPE | B83: 2-2 | C83: GEDC1041 | D83: Philippine Popular Culture | F83: 3 | H83: =SUM(F83:G83) -> 3 | I83: ='2 - Section Count Projection'!$O$41 -> 0 | J83: =I83*H83 -> 0 | K83: =IF(I83>0,F83,"")
A84: BSCPE | B84: 2-2 | C84: GED1009 | D84: Ethics | E84: Social and Behavioral Science | F84: 3 | H84: =SUM(F84:G84) -> 3 | I84: ='2 - Section Count Projection'!$O$41 -> 0 | J84: =I84*H84 -> 0 | K84: =IF(I84>0,F84,"")
A85: BSCPE | B85: 2-2 | C85: PHED1008 | D85: P.E./PATHFIT 4: Team Sports | E85: Physical Education | F85: 2 | H85: =SUM(F85:G85) -> 2 | I85: ='2 - Section Count Projection'!$O$41 -> 0 | J85: =I85*H85 -> 0 | K85: =IF(I85>0,F85,"")
A86: BSCPE | B86: 2-2 | C86: BUSS1013 | D86: Technopreneurship | E86: Business and Management | F86: 3 | H86: =SUM(F86:G86) -> 3 | I86: ='2 - Section Count Projection'!$O$41 -> 0 | J86: =I86*H86 -> 0 | K86: =IF(I86>0,F86,"")
A87: BSCPE | B87: 2-2 | C87: GEDC1045 | D87: Great Books | E87: English/Foreign Language | F87: 3 | H87: =SUM(F87:G87) -> 3 | I87: ='2 - Section Count Projection'!$O$41 -> 0 | J87: =I87*H87 -> 0 | K87: =IF(I87>0,F87,"")
A88: BSCPE | B88: 2-2 | C88: ENGR1049 | D88: Engineering Data Analysis | E88: Engineering | F88: 3 | H88: =SUM(F88:G88) -> 3 | I88: ='2 - Section Count Projection'!$O$41 -> 0 | J88: =I88*H88 -> 0 | K88: =IF(I88>0,F88,"")
K89: =IF(I89>0,F89,"")
A90: BSCPE-22-01 | K90: =IF(I90>0,F90,"")
A91: BSCPE | B91: 3-2 | C91: ENGR1022 | D91: Basic Occupational Health and Safety | E91: Engineering | F91: 3 | H91: =SUM(F91:G91) -> 3 | I91: ='2 - Section Count Projection'!$O$43 -> 0 | J91: =I91*H91 -> 0 | K91: =IF(I91>0,F91,"")
A92: BSCPE | B92: 3-2 | C92: ENGR1023 | D92: Microprocessors | E92: Engineering | F92: 3 | G92: 1.5 | H92: =SUM(F92:G92) -> 4.5 | I92: ='2 - Section Count Projection'!$O$43 -> 0 | J92: =I92*H92 -> 0 | K92: =IF(I92>0,F92,"")
A93: BSCPE | B93: 3-2 | D93: CpE Elective 2 | E93: Engineering | F93: 2 | G93: 1.5 | H93: =SUM(F93:G93) -> 3.5 | I93: ='2 - Section Count Projection'!$O$43 -> 0 | J93: =I93*H93 -> 0 | K93: =IF(I93>0,F93,"")
A94: BSCPE | B94: 3-2 | C94: ENGR1025 | D94: Introduction to HDL | E94: Engineering | G94: 1.5 | H94: =SUM(F94:G94) -> 1.5 | I94: ='2 - Section Count Projection'!$O$43 -> 0 | J94: =I94*H94 -> 0 | K94: =IF(I94>0,F94,"")
A95: BSCPE | B95: 3-2 | C95: ENGR1026 | D95: Digital Signal Processing | E95: Engineering | F95: 3 | G95: 1.5 | H95: =SUM(F95:G95) -> 4.5 | I95: ='2 - Section Count Projection'!$O$43 -> 0 | J95: =I95*H95 -> 0 | K95: =IF(I95>0,F95,"")
A96: BSCPE | B96: 3-2 | C96: ENGR1052 | D96: Capstone Design 1 | E96: Engineering | G96: 1.5 | H96: =SUM(F96:G96) -> 1.5 | I96: ='2 - Section Count Projection'!$O$43 -> 0 | J96: =I96*H96 -> 0 | K96: =IF(I96>0,F96,"")
K97: =IF(I97>0,F97,"")
A98: BSCPE-20-01 | K98: =IF(I98>0,F98,"")
A99: BSCPE | B99: 4-2 | C99: ENGR1027 | D99: CpE Practicum (300 hours) | E99: Engineering | G99: 3 | H99: 3 | I99: ='2 - Section Count Projection'!$O$45 -> 0 | J99: =I99*H99 -> 0 | K99: =IF(I99>0,F99,"")
K100: =IF(I100>0,F100,"")
...

Sheet 3.3 - SHS Term 1 
A2: Strand/Track | B2: Grade Level Term | C2: Subject Classification | D2: Subject Title | E2: Field of Specialization | F2: LEC | G2: TOTAL | H2: Section Count | I2: Teaching Load
A3: ABM | B3: 11-1 | C3: Core | D3: Oral Communication | E3: English | F3: 3 | G3: =SUM(F3:F3) -> 3 | H3: 3 | I3: =H3*G3 -> 9 | K3: =IF(I3>0,F3,"") -> 3
A4: ABM | B4: 11-1 | C4: Core | D4: General Mathematics | E4: Mathematics | F4: 3 | G4: =SUM(F4:F4) -> 3 | H4: 3 | I4: =H4*G4 -> 9 | K4: =IF(I4>0,F4,"") -> 3
A5: ABM | B5: 11-1 | C5: Core | D5: 21st Century Literature from the Philippines and the World | E5: English | F5: 3 | G5: =SUM(F5:F5) -> 3 | H5: 3 | I5: =H5*G5 -> 9 | K5: =IF(I5>0,F5,"") -> 3
A6: ABM | B6: 11-1 | C6: Core | D6: Media and Information Literacy | F6: 3 | G6: =SUM(F6:F6) -> 3 | H6: 3 | I6: =H6*G6 -> 9 | K6: =IF(I6>0,F6,"") -> 3
A7: ABM | B7: 11-1 | C7: Core | D7: Introduction to the Philosophy of the Human Person | E7: Social and Behavioral Sciences | F7: 3 | G7: =SUM(F7:F7) -> 3 | H7: 3 | I7: =H7*G7 -> 9 | K7: =IF(I7>0,F7,"") -> 3
A8: ABM | B8: 11-1 | C8: Core | D8: Physical Education and Health 1 | E8: Physical Education | F8: 3 | G8: =SUM(F8:F8) -> 3 | H8: 3 | I8: =H8*G8 -> 9 | K8: =IF(I8>0,F8,"") -> 3
A9: ABM | B9: 11-1 | C9: Specialized | D9: Business Mathematics | E9: Business and Management | F9: 3 | G9: =SUM(F9:F9) -> 3 | H9: 3 | I9: =H9*G9 -> 9 | K9: =IF(I9>0,F9,"") -> 3
A10: ABM | B10: 11-1 | C10: Specialized | D10: Organization and Management | E10: Business and Management | F10: 3 | G10: =SUM(F10:F10) -> 3 | H10: 3 | I10: =H10*G10 -> 9 | K10: =IF(I10>0,F10,"") -> 3
A11: ABM | B11: 11-1 | D11: Homeroom | F11: 1 | G11: =SUM(F11:F11) -> 1 | H11: 3 | I11: =H11*G11 -> 3 | K11: =IF(I11>0,F11,"") -> 1
A12: ABM | B12: 11-1 | D12: Student Club and Org | F12: 1 | G12: =SUM(F12:F12) -> 1 | H12: 3 | I12: =H12*G12 -> 3 | K12: =IF(I12>0,F12,"") -> 1
K13: =IF(I13>0,F13,"")
A14: ABM | B14: 12-1 | C14: Core | D14: Personal Development | E14: Social and Behavioral Sciences | F14: 3 | G14: =SUM(F14:F14) -> 3 | H14: 3 | I14: =H14*G14 -> 9 | K14: =IF(I14>0,F14,"") -> 3
A15: ABM | B15: 12-1 | C15: Core | D15: Pagbasa at Pagsusuri ng Iba't Ibang Teksto Tungo sa Pananaliksik | E15: Filipino | F15: 3 | G15: =SUM(F15:F15) -> 3 | H15: 3 | I15: =H15*G15 -> 9 | K15: =IF(I15>0,F15,"") -> 3
A16: ABM | B16: 12-1 | C16: Core | D16: Physical Science | E16: Sciences | F16: 3 | G16: =SUM(F16:F16) -> 3 | H16: 3 | I16: =H16*G16 -> 9 | K16: =IF(I16>0,F16,"") -> 3
A17: ABM | B17: 12-1 | C17: Core | D17: Physical Education and Health 3 | E17: Physical Education | F17: 3 | G17: =SUM(F17:F17) -> 3 | H17: 3 | I17: =H17*G17 -> 9 | K17: =IF(I17>0,F17,"") -> 3
A18: ABM | B18: 12-1 | C18: Applied | D18: Practical Research 2 | F18: 3 | G18: =SUM(F18:F18) -> 3 | H18: 3 | I18: =H18*G18 -> 9 | K18: =IF(I18>0,F18,"") -> 3
A19: ABM | B19: 12-1 | C19: Applied | D19: Filipino sa Piling Larangan | E19: Filipino | F19: 3 | G19: =SUM(F19:F19) -> 3 | H19: 3 | I19: =H19*G19 -> 9 | K19: =IF(I19>0,F19,"") -> 3
A20: ABM | B20: 12-1 | C20: Applied | D20: English for Academic and Professional Purposes | E20: English | F20: 3 | G20: =SUM(F20:F20) -> 3 | H20: 3 | I20: =H20*G20 -> 9 | K20: =IF(I20>0,F20,"") -> 3
A21: ABM | B21: 12-1 | C21: Specialized | D21: Business Finance | E21: Business and Management | F21: 3 | G21: =SUM(F21:F21) -> 3 | H21: 3 | I21: =H21*G21 -> 9 | K21: =IF(I21>0,F21,"") -> 3
A22: ABM | B22: 12-1 | C22: Specialized | D22: Fundamentals of Accountancy, Business and Management 2 | E22: Business and Management | F22: 3 | G22: =SUM(F22:F22) -> 3 | H22: 3 | I22: =H22*G22 -> 9 | K22: =IF(I22>0,F22,"") -> 3
A23: ABM | B23: 12-1 | D23: Homeroom | F23: 1 | G23: =SUM(F23:F23) -> 1 | H23: 3 | I23: =H23*G23 -> 3 | K23: =IF(I23>0,F23,"") -> 1
A24: ABM | B24: 12-1 | D24: Student Club and Org | F24: 1 | G24: =SUM(F24:F24) -> 1 | H24: 3 | I24: =H24*G24 -> 3 | K24: =IF(I24>0,F24,"") -> 1
K25: =IF(I25>0,F25,"")
A26: STEM | B26: 11-1 | C26: Core | D26: Oral Communication | E26: English | F26: 3 | G26: =SUM(F26:F26) -> 3 | H26: 9 | I26: =H26*G26 -> 27 | K26: =IF(I26>0,F26,"") -> 3
A27: STEM | B27: 11-1 | C27: Core | D27: General Mathematics | E27: Mathematics | F27: 3 | G27: =SUM(F27:F27) -> 3 | H27: 9 | I27: =H27*G27 -> 27 | K27: =IF(I27>0,F27,"") -> 3
A28: STEM | B28: 11-1 | C28: Core | D28: 21st Century Literature from the Philippines and the World | E28: Social and Behavioral Sciences | F28: 3 | G28: =SUM(F28:F28) -> 3 | H28: 9 | I28: =H28*G28 -> 27 | K28: =IF(I28>0,F28,"") -> 3
A29: STEM | B29: 11-1 | C29: Core | D29: Media and Information Literacy | F29: 3 | G29: =SUM(F29:F29) -> 3 | H29: 9 | I29: =H29*G29 -> 27 | K29: =IF(I29>0,F29,"") -> 3
A30: STEM | B30: 11-1 | C30: Core | D30: Introduction to the Philosophy of the Human Person | E30: Social and Behavioral Sciences | F30: 3 | G30: =SUM(F30:F30) -> 3 | H30: 9 | I30: =H30*G30 -> 27 | K30: =IF(I30>0,F30,"") -> 3
A31: STEM | B31: 11-1 | C31: Core | D31: Physical Education and Health 1 | E31: Physical Education | F31: 3 | G31: =SUM(F31:F31) -> 3 | H31: 9 | I31: =H31*G31 -> 27 | K31: =IF(I31>0,F31,"") -> 3
A32: STEM | B32: 11-1 | C32: Specialized | D32: Pre-Calculus | E32: Mathematics | F32: 3 | G32: =SUM(F32:F32) -> 3 | H32: 9 | I32: =H32*G32 -> 27 | K32: =IF(I32>0,F32,"") -> 3
A33: STEM | B33: 11-1 | C33: Specialized | D33: General Biology 1 | E33: Sciences | F33: 3 | G33: =SUM(F33:F33) -> 3 | H33: 9 | I33: =H33*G33 -> 27 | K33: =IF(I33>0,F33,"") -> 3
A34: STEM | B34: 11-1 | D34: Homeroom | F34: 1 | G34: =SUM(F34:F34) -> 1 | H34: 9 | I34: =H34*G34 -> 9 | K34: =IF(I34>0,F34,"") -> 1
A35: STEM | B35: 11-1 | D35: Student Club and Org | F35: 1 | G35: =SUM(F35:F35) -> 1 | H35: 9 | I35: =H35*G35 -> 9 | K35: =IF(I35>0,F35,"") -> 1
K36: =IF(I36>0,F36,"")
A37: STEM | B37: 12-1 | C37: Core | D37: Personal Development | E37: Social and Behavioral Sciences | F37: 3 | G37: =SUM(F37:F37) -> 3 | H37: 8 | I37: =H37*G37 -> 24 | K37: =IF(I37>0,F37,"") -> 3
A38: STEM | B38: 12-1 | C38: Core | D38: Pagbasa at Pagsusuri ng Iba't Ibang Teksto Tungo sa Pananaliksik | E38: Filipino | F38: 3 | G38: =SUM(F38:F38) -> 3 | H38: ='2 - Section Count Projection'!$G$18 -> 0 | I38: =H38*G38 -> 0 | K38: =IF(I38>0,F38,"")
A39: STEM | B39: 12-1 | C39: Core | D39: Disaster Readiness and Risk Reduction | E39: Social and Behavioral Sciences | F39: 3 | G39: =SUM(F39:F39) -> 3 | H39: 8 | I39: =H39*G39 -> 24 | K39: =IF(I39>0,F39,"") -> 3
A40: STEM | B40: 12-1 | C40: Core | D40: Physical Education and Health 3 | E40: Physical Education | F40: 3 | G40: =SUM(F40:F40) -> 3 | H40: 8 | I40: =H40*G40 -> 24 | K40: =IF(I40>0,F40,"") -> 3
A41: STEM | B41: 12-1 | C41: Applied | D41: Practical Research 2 | F41: 3 | G41: =SUM(F41:F41) -> 3 | H41: 8 | I41: =H41*G41 -> 24 | K41: =IF(I41>0,F41,"") -> 3
A42: STEM | B42: 12-1 | C42: Applied | D42: Filipino sa Piling Larangan | E42: Filipino | F42: 3 | G42: =SUM(F42:F42) -> 3 | H42: 8 | I42: =H42*G42 -> 24 | K42: =IF(I42>0,F42,"") -> 3
A43: STEM | B43: 12-1 | C43: Applied | D43: English for Academic and Professional Purposes | E43: English | F43: 3 | G43: =SUM(F43:F43) -> 3 | H43: 8 | I43: =H43*G43 -> 24 | K43: =IF(I43>0,F43,"") -> 3
A44: STEM | B44: 12-1 | C44: Specialized | D44: General Physics 1 | E44: Sciences | F44: 3 | G44: =SUM(F44:F44) -> 3 | H44: 8 | I44: =H44*G44 -> 24 | K44: =IF(I44>0,F44,"") -> 3
A45: STEM | B45: 12-1 | C45: Specialized | D45: General Chemistry 1 | E45: Sciences | F45: 3 | G45: =SUM(F45:F45) -> 3 | H45: 8 | I45: =H45*G45 -> 24 | K45: =IF(I45>0,F45,"") -> 3
A46: STEM | B46: 12-1 | D46: Homeroom | F46: 1 | G46: =SUM(F46:F46) -> 1 | H46: 8 | I46: =H46*G46 -> 8 | K46: =IF(I46>0,F46,"") -> 1
A47: STEM | B47: 12-1 | D47: Student Club and Org | F47: 1 | G47: =SUM(F47:F47) -> 1 | H47: 8 | I47: =H47*G47 -> 8 | K47: =IF(I47>0,F47,"") -> 1
K48: =IF(I48>0,F48,"")
A49: GA | B49: 11-1 | C49: Core | D49: Oral Communication | E49: English | F49: 3 | G49: =SUM(F49:F49) -> 3 | H49: 1 | I49: =H49*G49 -> 3 | K49: =IF(I49>0,F49,"") -> 3
A50: GA | B50: 11-1 | C50: Core | D50: General Mathematics | E50: Mathematics | F50: 3 | G50: =SUM(F50:F50) -> 3 | H50: 1 | I50: =H50*G50 -> 3 | K50: =IF(I50>0,F50,"") -> 3
A51: GA | B51: 11-1 | C51: Core | D51: 21st Century Literature from the Philippines and the World | E51: English | F51: 3 | G51: =SUM(F51:F51) -> 3 | H51: 1 | I51: =H51*G51 -> 3 | K51: =IF(I51>0,F51,"") -> 3
A52: GA | B52: 11-1 | C52: Core | D52: Media and Information Literacy | F52: 3 | G52: =SUM(F52:F52) -> 3 | H52: 1 | I52: =H52*G52 -> 3 | K52: =IF(I52>0,F52,"") -> 3
A53: GA | B53: 11-1 | C53: Core | D53: Introduction to the Philosophy of the Human Person | E53: Social and Behavioral Sciences | F53: 3 | G53: =SUM(F53:F53) -> 3 | H53: 1 | I53: =H53*G53 -> 3 | K53: =IF(I53>0,F53,"") -> 3
A54: GA | B54: 11-1 | C54: Core | D54: Physical Education and Health 1 | E54: Physical Education | F54: 3 | G54: =SUM(F54:F54) -> 3 | H54: 1 | I54: =H54*G54 -> 3 | K54: =IF(I54>0,F54,"") -> 3
A55: GA | B55: 11-1 | C55: Specialized | D55: Organization and Management | E55: Business and Management | F55: 3 | G55: =SUM(F55:F55) -> 3 | H55: 1 | I55: =H55*G55 -> 3 | K55: =IF(I55>0,F55,"") -> 3
A56: GA | B56: 11-1 | C56: Specialized | D56: Humanities 1 Elective (from HUMSS Strand Subjects) | F56: 3 | G56: =SUM(F56:F56) -> 3 | H56: 1 | I56: =H56*G56 -> 3 | K56: =IF(I56>0,F56,"") -> 3
A57: GA | B57: 11-1 | D57: Homeroom | F57: 1 | G57: =SUM(F57:F57) -> 1 | H57: 1 | I57: =H57*G57 -> 1 | K57: =IF(I57>0,F57,"") -> 1
A58: GA | B58: 11-1 | D58: Student Club and Org | F58: 1 | G58: =SUM(F58:F58) -> 1 | H58: 1 | I58: =H58*G58 -> 1 | K58: =IF(I58>0,F58,"") -> 1
K59: =IF(I59>0,F59,"")
A60: GA | B60: 12-1 | C60: Core | D60: Personal Development | E60: Social and Behavioral Sciences | F60: 3 | G60: =SUM(F60:F60) -> 3 | H60: 1 | I60: =H60*G60 -> 3 | K60: =IF(I60>0,F60,"") -> 3
A61: GA | B61: 12-1 | C61: Core | D61: Pagbasa at Pagsusuri ng Iba't Ibang Teksto Tungo sa Pananaliksik | E61: Filipino | F61: 3 | G61: =SUM(F61:F61) -> 3 | H61: 1 | I61: =H61*G61 -> 3 | K61: =IF(I61>0,F61,"") -> 3
A62: GA | B62: 12-1 | C62: Core | D62: Physical Science | E62: Sciences | F62: 3 | G62: 3 | H62: 1 | I62: =H62*G62 -> 3 | K62: =IF(I62>0,F62,"") -> 3
A63: GA | B63: 12-1 | C63: Core | D63: Physical Education and Health 3 | E63: Physical Education | F63: 3 | G63: =SUM(F63:F63) -> 3 | H63: 1 | I63: =H63*G63 -> 3 | K63: =IF(I63>0,F63,"") -> 3
A64: GA | B64: 12-1 | C64: Applied | D64: Practical Research 2 | F64: 3 | G64: =SUM(F64:F64) -> 3 | H64: 1 | I64: =H64*G64 -> 3 | K64: =IF(I64>0,F64,"") -> 3
A65: GA | B65: 12-1 | C65: Applied | D65: Filipino sa Piling Larangan | E65: Filipino | F65: 3 | G65: =SUM(F65:F65) -> 3 | H65: 1 | I65: =H65*G65 -> 3 | K65: =IF(I65>0,F65,"") -> 3
A66: GA | B66: 12-1 | C66: Applied | D66: English for Academic and Professional Purposes | E66: English | F66: 3 | G66: =SUM(F66:F66) -> 3 | H66: 1 | I66: =H66*G66 -> 3 | K66: =IF(I66>0,F66,"") -> 3
A67: GA | B67: 12-1 | C67: Specialized | D67: Disaster Readiness and Risk Reduction | E67: Social and Behavioral Sciences | F67: 3 | G67: =SUM(F67:F67) -> 3 | H67: 1 | I67: =H67*G67 -> 3 | K67: =IF(I67>0,F67,"") -> 3
A68: GA | B68: 12-1 | C68: Specialized | D68: Elective 1 (from any Track/Strand Subjects) | F68: 3 | G68: =SUM(F68:F68) -> 3 | H68: 1 | I68: =H68*G68 -> 3 | K68: =IF(I68>0,F68,"") -> 3
A69: GA | B69: 12-1 | D69: Homeroom | F69: 1 | G69: =SUM(F69:F69) -> 1 | H69: 1 | I69: =H69*G69 -> 1 | K69: =IF(I69>0,F69,"") -> 1
A70: GA | B70: 12-1 | D70: Student Club and Org | F70: 1 | G70: =SUM(F70:F70) -> 1 | H70: 1 | I70: =H70*G70 -> 1 | K70: =IF(I70>0,F70,"") -> 1
K71: =IF(I71>0,F71,"")
A72: HUMSS | B72: 11-1 | C72: Core | D72: Oral Communication | E72: English | F72: 3 | G72: =SUM(F72:F72) -> 3 | H72: 2 | I72: =H72*G72 -> 6 | K72: =IF(I72>0,F72,"") -> 3
A73: HUMSS | B73: 11-1 | C73: Core | D73: General Mathematics | E73: Mathematics | F73: 3 | G73: =SUM(F73:F73) -> 3 | H73: 2 | I73: =H73*G73 -> 6 | K73: =IF(I73>0,F73,"") -> 3
A74: HUMSS | B74: 11-1 | C74: Core | D74: 21st Century Literature from the Philippines and the World | E74: English | F74: 3 | G74: =SUM(F74:F74) -> 3 | H74: 2 | I74: =H74*G74 -> 6 | K74: =IF(I74>0,F74,"") -> 3
A75: HUMSS | B75: 11-1 | C75: Core | D75: Media and Information Literacy | F75: 3 | G75: =SUM(F75:F75) -> 3 | H75: 2 | I75: =H75*G75 -> 6 | K75: =IF(I75>0,F75,"") -> 3
A76: HUMSS | B76: 11-1 | C76: Core | D76: Introduction to the Philosophy of the Human Person | E76: Social and Behavioral Sciences | F76: 3 | G76: =SUM(F76:F76) -> 3 | H76: 2 | I76: =H76*G76 -> 6 | K76: =IF(I76>0,F76,"") -> 3
A77: HUMSS | B77: 11-1 | C77: Core | D77: Physical Education and Health 1 | E77: Physical Education | F77: 3 | G77: =SUM(F77:F77) -> 3 | H77: 2 | I77: =H77*G77 -> 6 | K77: =IF(I77>0,F77,"") -> 3
A78: HUMSS | B78: 11-1 | C78: Specialized | D78: Introduction to World Religions and Belief Systems | E78: Social and Behavioral Sciences | F78: 3 | G78: =SUM(F78:F78) -> 3 | H78: 2 | I78: =H78*G78 -> 6 | K78: =IF(I78>0,F78,"") -> 3
A79: HUMSS | B79: 11-1 | C79: Specialized | D79: Disciplines and Ideas in the Social Sciences | E79: Social and Behavioral Sciences | F79: 3 | G79: =SUM(F79:F79) -> 3 | H79: 2 | I79: =H79*G79 -> 6 | K79: =IF(I79>0,F79,"") -> 3
A80: HUMSS | B80: 11-1 | D80: Homeroom | F80: 1 | G80: =SUM(F80:F80) -> 1 | H80: 2 | I80: =H80*G80 -> 2 | K80: =IF(I80>0,F80,"") -> 1
A81: HUMSS | B81: 11-1 | D81: Student Club and Org | F81: 1 | G81: =SUM(F81:F81) -> 1 | H81: 2 | I81: =H81*G81 -> 2 | K81: =IF(I81>0,F81,"") -> 1
K82: =IF(I82>0,F82,"")
A83: HUMSS | B83: 12-1 | C83: Core | D83: Personal Development | E83: Social and Behavioral Sciences | F83: 3 | G83: =SUM(F83:F83) -> 3 | H83: 2 | I83: =H83*G83 -> 6 | K83: =IF(I83>0,F83,"") -> 3
A84: HUMSS | B84: 12-1 | C84: Core | D84: Pagbasa at Pagsusuri ng Iba't Ibang Teksto Tungo sa Pananaliksik | E84: Filipino | F84: 3 | G84: =SUM(F84:F84) -> 3 | H84: 2 | I84: =H84*G84 -> 6 | K84: =IF(I84>0,F84,"") -> 3
A85: HUMSS | B85: 12-1 | C85: Core | D85: Physical Science | E85: Sciences | F85: 3 | G85: 3 | H85: 2 | I85: =H85*G85 -> 6 | K85: =IF(I85>0,F85,"") -> 3
A86: HUMSS | B86: 12-1 | C86: Core | D86: Physical Education and Health 3 | E86: Physical Education | F86: 3 | G86: =SUM(F86:F86) -> 3 | H86: 2 | I86: =H86*G86 -> 6 | K86: =IF(I86>0,F86,"") -> 3
A87: HUMSS | B87: 12-1 | C87: Applied | D87: Practical Research 2 | F87: 3 | G87: =SUM(F87:F87) -> 3 | H87: 2 | I87: =H87*G87 -> 6 | K87: =IF(I87>0,F87,"") -> 3
A88: HUMSS | B88: 12-1 | C88: Applied | D88: Filipino sa Piling Larangan | E88: Filipino | F88: 3 | G88: =SUM(F88:F88) -> 3 | H88: 2 | I88: =H88*G88 -> 6 | K88: =IF(I88>0,F88,"") -> 3
A89: HUMSS | B89: 12-1 | C89: Applied | D89: English for Academic and Professional Purposes | E89: English | F89: 3 | G89: =SUM(F89:F89) -> 3 | H89: 2 | I89: =H89*G89 -> 6 | K89: =IF(I89>0,F89,"") -> 3
A90: HUMSS | B90: 12-1 | C90: Specialized | D90: Creative Nonfiction | E90: Social and Behavioral Sciences | F90: 3 | G90: =SUM(F90:F90) -> 3 | H90: 2 | I90: =H90*G90 -> 6 | K90: =IF(I90>0,F90,"") -> 3
A91: HUMSS | B91: 12-1 | C91: Specialized | D91: Philippine Politics and Governance | E91: Social and Behavioral Sciences | F91: 3 | G91: =SUM(F91:F91) -> 3 | H91: 2 | I91: =H91*G91 -> 6 | K91: =IF(I91>0,F91,"") -> 3
A92: HUMSS | B92: 12-1 | D92: Homeroom | F92: 1 | G92: =SUM(F92:F92) -> 1 | H92: 2 | I92: =H92*G92 -> 2 | K92: =IF(I92>0,F92,"") -> 1
A93: HUMSS | B93: 12-1 | D93: Student Club and Org | F93: 1 | G93: =SUM(F93:F93) -> 1 | H93: 2 | I93: =H93*G93 -> 2 | K93: =IF(I93>0,F93,"") -> 1
K94: =IF(I94>0,F94,"")
A95: IT-MAWD | B95: 11-1 | C95: Core | D95: Oral Communication | E95: English | F95: 3 | G95: =SUM(F95:F95) -> 3 | H95: 3 | I95: =H95*G95 -> 9 | K95: =IF(I95>0,F95,"") -> 3
A96: IT-MAWD | B96: 11-1 | C96: Core | D96: General Mathematics | E96: Mathematics | F96: 3 | G96: =SUM(F96:F96) -> 3 | H96: 3 | I96: =H96*G96 -> 9 | K96: =IF(I96>0,F96,"") -> 3
A97: IT-MAWD | B97: 11-1 | C97: Core | D97: 21st Century Literature from the Philippines and the World | E97: English | F97: 3 | G97: =SUM(F97:F97) -> 3 | H97: 3 | I97: =H97*G97 -> 9 | K97: =IF(I97>0,F97,"") -> 3
A98: IT-MAWD | B98: 11-1 | C98: Core | D98: Media and Information Literacy | F98: 3 | G98: =SUM(F98:F98) -> 3 | H98: 3 | I98: =H98*G98 -> 9 | K98: =IF(I98>0,F98,"") -> 3
A99: IT-MAWD | B99: 11-1 | C99: Core | D99: Introduction to the Philosophy of the Human Person | E99: Social and Behavioral Sciences | F99: 3 | G99: =SUM(F99:F99) -> 3 | H99: 3 | I99: =H99*G99 -> 9 | K99: =IF(I99>0,F99,"") -> 3
A100: IT-MAWD | B100: 11-1 | C100: Core | D100: Physical Education and Health 1 | E100: Physical Education | F100: 3 | G100: =SUM(F100:F100) -> 3 | H100: 3 | I100: =H100*G100 -> 9 | K100: =IF(I100>0,F100,"") -> 3
A101: IT-MAWD | B101: 11-1 | C101: Specialized | D101: Computer/Web Programming 1 | E101: Information Technology | F101: 3 | G101: =SUM(F101:F101) -> 3 | H101: 3 | I101: =H101*G101 -> 9 | K101: =IF(I101>0,F101,"") -> 3
...

Sheet 3.4 - SHS Term 2
A2: Strand/Track | B2: Grade Level Term | C2: Subject Classification | D2: Subject Title | E2: Field of Specialization | F2: LEC | G2: TOTAL | H2: Section Count | I2: Teaching Load
A3: ABM | B3: 11-2 | C3: Core | D3: Reading and Writing | E3: English | F3: 3 | G3: =SUM(F3:F3) -> 3 | H3: 0 | I3: =H3*G3 -> 0 | K3: =IF(I3>0,F3,"")
A4: ABM | B4: 11-2 | C4: Core | D4: Statistics and Probability | E4: Mathematics | F4: 3 | G4: =SUM(F4:F4) -> 3 | H4: 0 | I4: =H4*G4 -> 0 | K4: =IF(I4>0,F4,"")
A5: ABM | B5: 11-2 | C5: Core | D5: Understanding Culture, Society and Politics | E5: Social and Behavioral Sciences | F5: 3 | G5: =SUM(F5:F5) -> 3 | H5: 0 | I5: =H5*G5 -> 0 | K5: =IF(I5>0,F5,"")
A6: ABM | B6: 11-2 | C6: Core | D6: Earth and Life Science | E6: Sciences | F6: 3 | G6: =SUM(F6:F6) -> 3 | H6: 0 | I6: =H6*G6 -> 0 | K6: =IF(I6>0,F6,"")
A7: ABM | B7: 11-2 | C7: Core | D7: Komunikasyon at Pananaliksik sa Wika at Kulturang Pilipino | E7: Filipino | F7: 3 | G7: =SUM(F7:F7) -> 3 | H7: 0 | I7: =H7*G7 -> 0 | K7: =IF(I7>0,F7,"")
A8: ABM | B8: 11-2 | C8: Core | D8: Physical Education and Health 2 | E8: Physical Education | F8: 2 | G8: =SUM(F8:F8) -> 2 | H8: 0 | I8: =H8*G8 -> 0 | K8: =IF(I8>0,F8,"")
A9: ABM | B9: 11-2 | C9: Applied | D9: Practical Research 1 | F9: 3 | G9: =SUM(F9:F9) -> 3 | H9: 0 | I9: =H9*G9 -> 0 | K9: =IF(I9>0,F9,"")
A10: ABM | B10: 11-2 | C10: Specialized | D10: Principles of Marketing | E10: Business and Management | F10: 3 | G10: =SUM(F10:F10) -> 3 | H10: 0 | I10: =H10*G10 -> 0 | K10: =IF(I10>0,F10,"")
A11: ABM | B11: 11-2 | C11: Specialized | D11: Fundamentals of Accountancy, Business and Management 1 | E11: Business and Management | F11: 3 | G11: =SUM(F11:F11) -> 3 | H11: 0 | I11: =H11*G11 -> 0 | K11: =IF(I11>0,F11,"")
A12: ABM | B12: 11-2 | D12: Homeroom | F12: 1 | G12: =SUM(F12:F12) -> 1 | H12: 0 | I12: =H12*G12 -> 0 | K12: =IF(I12>0,F12,"")
A13: ABM | B13: 11-2 | D13: Student Club and Org | E13: Filipino | F13: 1 | G13: =SUM(F13:F13) -> 1 | H13: 0 | I13: =H13*G13 -> 0 | K13: =IF(I13>0,F13,"")
K14: =IF(I14>0,F14,"")
A15: ABM | B15: 12-2 | C15: Core | D15: Contemporary Philippine Arts from the Regions | E15: Social and Behavioral Sciences | F15: 3 | G15: =SUM(F15:F15) -> 3 | H15: 0 | I15: =H15*G15 -> 0 | K15: =IF(I15>0,F15,"")
A16: ABM | B16: 12-2 | C16: Core | D16: Physical Education and Health 4 | E16: Physical Education | F16: 2 | G16: =SUM(F16:F16) -> 2 | H16: 0 | I16: =H16*G16 -> 0 | K16: =IF(I16>0,F16,"")
A17: ABM | B17: 12-2 | C17: Applied | D17: Empowerment Technologies | E17: Information Technology | F17: 3 | G17: =SUM(F17:F17) -> 3 | H17: 0 | I17: =H17*G17 -> 0 | K17: =IF(I17>0,F17,"")
A18: ABM | B18: 12-2 | C18: Applied | D18: Entrepreneurship | E18: Business and Management | F18: 3 | G18: =SUM(F18:F18) -> 3 | H18: 0 | I18: =H18*G18 -> 0 | K18: =IF(I18>0,F18,"")
A19: ABM | B19: 12-2 | C19: Applied | D19: Inquiries, Investigations and Immersion | F19: 3 | G19: =SUM(F19:F19) -> 3 | H19: 0 | I19: =H19*G19 -> 0 | K19: =IF(I19>0,F19,"")
A20: ABM | B20: 12-2 | C20: Specialized | D20: Work Immersion/Research/Career Advocacy/Culminating Activity (Business Enterprise Simulation) | F20: 2 | G20: =SUM(F20:F20) -> 2 | H20: 0 | I20: =H20*G20 -> 0 | K20: =IF(I20>0,F20,"")
A21: ABM | B21: 12-2 | C21: Specialized | D21: Applied Economics | E21: Business and Management | F21: 3 | G21: =SUM(F21:F21) -> 3 | H21: 0 | I21: =H21*G21 -> 0 | K21: =IF(I21>0,F21,"")
A22: ABM | B22: 12-2 | C22: Specialized | D22: Business Ethics and Social Responsibility | E22: Business and Management | F22: 3 | G22: =SUM(F22:F22) -> 3 | H22: 0 | I22: =H22*G22 -> 0 | K22: =IF(I22>0,F22,"")
A23: ABM | B23: 12-2 | D23: Homeroom | F23: 1 | G23: =SUM(F23:F23) -> 1 | H23: 0 | I23: =H23*G23 -> 0 | K23: =IF(I23>0,F23,"")
A24: ABM | B24: 12-2 | D24: Student Club and Org | F24: 1 | G24: =SUM(F24:F24) -> 1 | H24: 0 | I24: =H24*G24 -> 0 | K24: =IF(I24>0,F24,"")
K25: =IF(I25>0,F25,"")
A26: STEM | B26: 11-2 | C26: Core | D26: Reading and Writing | E26: English | F26: 3 | G26: =SUM(F26:F26) -> 3 | H26: 0 | I26: =H26*G26 -> 0 | K26: =IF(I26>0,F26,"")
A27: STEM | B27: 11-2 | C27: Core | D27: Statistics and Probability | E27: Mathematics | F27: 3 | G27: =SUM(F27:F27) -> 3 | H27: 0 | I27: =H27*G27 -> 0 | K27: =IF(I27>0,F27,"")
A28: STEM | B28: 11-2 | C28: Core | D28: Understanding Culture, Society and Politics | E28: Social and Behavioral Sciences | F28: 3 | G28: =SUM(F28:F28) -> 3 | H28: 0 | I28: =H28*G28 -> 0 | K28: =IF(I28>0,F28,"")
A29: STEM | B29: 11-2 | C29: Core | D29: Earth Science | E29: Sciences | F29: 3 | G29: =SUM(F29:F29) -> 3 | H29: 0 | I29: =H29*G29 -> 0 | K29: =IF(I29>0,F29,"")
A30: STEM | B30: 11-2 | C30: Core | D30: Komunikasyon at Pananaliksik sa Wika at Kulturang Pilipino | E30: Filipino | F30: 3 | G30: =SUM(F30:F30) -> 3 | H30: 0 | I30: =H30*G30 -> 0 | K30: =IF(I30>0,F30,"")
A31: STEM | B31: 11-2 | C31: Core | D31: Physical Education and Health 2 | E31: Physical Education | F31: 2 | G31: =SUM(F31:F31) -> 2 | H31: 0 | I31: =H31*G31 -> 0 | K31: =IF(I31>0,F31,"")
A32: STEM | B32: 11-2 | C32: Applied | D32: Practical Research 1 | F32: 3 | G32: =SUM(F32:F32) -> 3 | H32: 0 | I32: =H32*G32 -> 0 | K32: =IF(I32>0,F32,"")
A33: STEM | B33: 11-2 | C33: Specialized | D33: Basic Calculus | E33: Mathematics | F33: 3 | G33: =SUM(F33:F33) -> 3 | H33: 0 | I33: =H33*G33 -> 0 | K33: =IF(I33>0,F33,"")
A34: STEM | B34: 11-2 | C34: Specialized | D34: General Biology 2 | E34: Sciences | F34: 3 | G34: =SUM(F34:F34) -> 3 | H34: 0 | I34: =H34*G34 -> 0 | K34: =IF(I34>0,F34,"")
A35: STEM | B35: 11-2 | D35: Homeroom | F35: 1 | G35: =SUM(F35:F35) -> 1 | H35: 0 | I35: =H35*G35 -> 0 | K35: =IF(I35>0,F35,"")
A36: STEM | B36: 11-2 | D36: Student Club and Org | F36: 1 | G36: =SUM(F36:F36) -> 1 | H36: 9 | I36: =H36*G36 -> 9 | K36: =IF(I36>0,F36,"") -> 1
K37: =IF(I37>0,F37,"")
A38: STEM | B38: 12-2 | C38: Core | D38: Contemporary Philippine Arts from the Regions | E38: Social and Behavioral Sciences | F38: 3 | G38: =SUM(F38:F38) -> 3 | H38: 0 | I38: =H38*G38 -> 0 | K38: =IF(I38>0,F38,"")
A39: STEM | B39: 12-2 | C39: Core | D39: Physical Education and Health 4 | E39: Physical Education | F39: 2 | G39: =SUM(F39:F39) -> 2 | H39: 0 | I39: =H39*G39 -> 0 | K39: =IF(I39>0,F39,"")
A40: STEM | B40: 12-2 | C40: Applied | D40: Empowerment Technologies | E40: Information Technology | F40: 3 | G40: =SUM(F40:F40) -> 3 | H40: 0 | I40: =H40*G40 -> 0 | K40: =IF(I40>0,F40,"")
A41: STEM | B41: 12-2 | C41: Applied | D41: Entrepreneurship | E41: Business and Management | F41: 3 | G41: =SUM(F41:F41) -> 3 | H41: 0 | I41: =H41*G41 -> 0 | K41: =IF(I41>0,F41,"")
A42: STEM | B42: 12-2 | C42: Applied | D42: Inquiries, Investigations and Immersion | F42: 3 | G42: =SUM(F42:F42) -> 3 | H42: 0 | I42: =H42*G42 -> 0 | K42: =IF(I42>0,F42,"")
A43: STEM | B43: 12-2 | C43: Specialized | D43: Work Immersion/Research/Career Advocacy/Culminating Activity (Capstone Project) | F43: 2 | G43: =SUM(F43:F43) -> 2 | H43: 0 | I43: =H43*G43 -> 0 | K43: =IF(I43>0,F43,"")
A44: STEM | B44: 12-2 | C44: Specialized | D44: General Physics 2 | E44: Sciences | F44: 3 | G44: =SUM(F44:F44) -> 3 | H44: 0 | I44: =H44*G44 -> 0 | K44: =IF(I44>0,F44,"")
A45: STEM | B45: 12-2 | C45: Specialized | D45: General Chemistry 2 | E45: Sciences | F45: 3 | G45: =SUM(F45:F45) -> 3 | H45: 0 | I45: =H45*G45 -> 0 | K45: =IF(I45>0,F45,"")
A46: STEM | B46: 12-2 | D46: Homeroom | F46: 1 | G46: =SUM(F46:F46) -> 1 | H46: 0 | I46: =H46*G46 -> 0 | K46: =IF(I46>0,F46,"")
A47: STEM | B47: 12-2 | D47: Student Club and Org | F47: 1 | G47: =SUM(F47:F47) -> 1 | H47: 0 | I47: =H47*G47 -> 0 | K47: =IF(I47>0,F47,"")
K48: =IF(I48>0,F48,"")
A49: GA | B49: 11-2 | C49: Core | D49: Reading and Writing | E49: English | F49: 3 | G49: =SUM(F49:F49) -> 3 | H49: ='2 - Section Count Projection'!$G$27 -> 0 | I49: =H49*G49 -> 0 | K49: =IF(I49>0,F49,"")
A50: GA | B50: 11-2 | C50: Core | D50: Statistics and Probability | E50: Mathematics | F50: 3 | G50: =SUM(F50:F50) -> 3 | H50: ='2 - Section Count Projection'!$G$27 -> 0 | I50: =H50*G50 -> 0 | K50: =IF(I50>0,F50,"")
A51: GA | B51: 11-2 | C51: Core | D51: Understanding Culture, Society and Politics | E51: Social and Behavioral Sciences | F51: 3 | G51: =SUM(F51:F51) -> 3 | H51: ='2 - Section Count Projection'!$G$27 -> 0 | I51: =H51*G51 -> 0 | K51: =IF(I51>0,F51,"")
A52: GA | B52: 11-2 | C52: Core | D52: Earth and Life Science | E52: Sciences | F52: 3 | G52: =SUM(F52:F52) -> 3 | H52: ='2 - Section Count Projection'!$G$27 -> 0 | I52: =H52*G52 -> 0 | K52: =IF(I52>0,F52,"")
A53: GA | B53: 11-2 | C53: Core | D53: Komunikasyon at Pananaliksik sa Wika at Kulturang Pilipino | E53: Filipino | F53: 3 | G53: =SUM(F53:F53) -> 3 | H53: ='2 - Section Count Projection'!$G$27 -> 0 | I53: =H53*G53 -> 0 | K53: =IF(I53>0,F53,"")
A54: GA | B54: 11-2 | C54: Core | D54: Physical Education and Health 2 | E54: Physical Education | F54: 2 | G54: =SUM(F54:F54) -> 2 | H54: ='2 - Section Count Projection'!$G$27 -> 0 | I54: =H54*G54 -> 0 | K54: =IF(I54>0,F54,"")
A55: GA | B55: 11-2 | C55: Applied | D55: Practical Research 1 | F55: 3 | G55: =SUM(F55:F55) -> 3 | H55: ='2 - Section Count Projection'!$G$27 -> 0 | I55: =H55*G55 -> 0 | K55: =IF(I55>0,F55,"")
A56: GA | B56: 11-2 | C56: Specialized | D56: Humanities 2 Elective (from HUMSS Strand Subjects) | F56: 3 | G56: =SUM(F56:F56) -> 3 | H56: ='2 - Section Count Projection'!$G$27 -> 0 | I56: =H56*G56 -> 0 | K56: =IF(I56>0,F56,"")
A57: GA | B57: 11-2 | C57: Specialized | D57: Social Science 1 Elective (from HUMSS Strand Subjects) | F57: 3 | G57: =SUM(F57:F57) -> 3 | H57: ='2 - Section Count Projection'!$G$27 -> 0 | I57: =H57*G57 -> 0 | K57: =IF(I57>0,F57,"")
A58: GA | B58: 11-2 | D58: Homeroom | F58: 1 | G58: =SUM(F58:F58) -> 1 | H58: ='2 - Section Count Projection'!$G$21 -> 0 | I58: =H58*G58 -> 0 | K58: =IF(I58>0,F58,"")
A59: GA | B59: 11-2 | D59: Student Club and Org | F59: 1 | G59: =SUM(F59:F59) -> 1 | H59: ='2 - Section Count Projection'!$G$21 -> 0 | I59: =H59*G59 -> 0 | K59: =IF(I59>0,F59,"")
K60: =IF(I60>0,F60,"")
A61: GA | B61: 12-2 | C61: Core | D61: Contemporary Philippine Arts from the Regions | E61: Social and Behavioral Sciences | F61: 3 | G61: =SUM(F61:F61) -> 3 | H61: 0 | I61: =H61*G61 -> 0 | K61: =IF(I61>0,F61,"")
A62: GA | B62: 12-2 | C62: Core | D62: Physical Education and Health 4 | E62: Physical Education | F62: 2 | G62: =SUM(F62:F62) -> 2 | H62: 0 | I62: =H62*G62 -> 0 | K62: =IF(I62>0,F62,"")
A63: GA | B63: 12-2 | C63: Applied | D63: Empowerment Technologies | E63: Information Technology | F63: 3 | G63: =SUM(F63:F63) -> 3 | H63: 0 | I63: =H63*G63 -> 0 | K63: =IF(I63>0,F63,"")
A64: GA | B64: 12-2 | C64: Applied | D64: Entrepreneurship | E64: Business and Management | F64: 3 | G64: =SUM(F64:F64) -> 3 | H64: 0 | I64: =H64*G64 -> 0 | K64: =IF(I64>0,F64,"")
A65: GA | B65: 12-2 | C65: Applied | D65: Inquiries, Investigations and Immersion | F65: 3 | G65: =SUM(F65:F65) -> 3 | H65: 0 | I65: =H65*G65 -> 0 | K65: =IF(I65>0,F65,"")
A66: GA | B66: 12-2 | C66: Specialized | D66: Work Immersion/Research/Career Advocacy/Culminating Activity | F66: 2 | G66: =SUM(F66:F66) -> 2 | H66: 0 | I66: =H66*G66 -> 0 | K66: =IF(I66>0,F66,"")
A67: GA | B67: 12-2 | C67: Specialized | D67: Applied Economics | E67: Business and Management | F67: 3 | G67: =SUM(F67:F67) -> 3 | H67: 0 | I67: =H67*G67 -> 0 | K67: =IF(I67>0,F67,"")
A68: GA | B68: 12-2 | C68: Specialized | D68: Elective 2 (from any Track/Strand Subjects) | E68: Business and Management | F68: 3 | G68: =SUM(F68:F68) -> 3 | H68: 0 | I68: =H68*G68 -> 0 | K68: =IF(I68>0,F68,"")
A69: GA | B69: 12-2 | D69: Homeroom | F69: 1 | G69: =SUM(F69:F69) -> 1 | H69: 0 | I69: =H69*G69 -> 0 | K69: =IF(I69>0,F69,"")
A70: GA | B70: 12-2 | D70: Student Club and Org | F70: 1 | G70: =SUM(F70:F70) -> 1 | H70: 0 | I70: =H70*G70 -> 0 | K70: =IF(I70>0,F70,"")
K71: =IF(I71>0,F71,"")
A72: HUMSS | B72: 11-2 | C72: Core | D72: Reading and Writing | E72: English | F72: 3 | G72: =SUM(F72:F72) -> 3 | H72: 0 | I72: =H72*G72 -> 0 | K72: =IF(I72>0,F72,"")
A73: HUMSS | B73: 11-2 | C73: Core | D73: Statistics and Probability | E73: Mathematics | F73: 3 | G73: =SUM(F73:F73) -> 3 | H73: 0 | I73: =H73*G73 -> 0 | K73: =IF(I73>0,F73,"")
A74: HUMSS | B74: 11-2 | C74: Core | D74: Understanding Culture, Society and Politics | E74: Social and Behavioral Sciences | F74: 3 | G74: =SUM(F74:F74) -> 3 | H74: 0 | I74: =H74*G74 -> 0 | K74: =IF(I74>0,F74,"")
A75: HUMSS | B75: 11-2 | C75: Core | D75: Earth and Life Science | E75: Sciences | F75: 3 | G75: =SUM(F75:F75) -> 3 | H75: 0 | I75: =H75*G75 -> 0 | K75: =IF(I75>0,F75,"")
A76: HUMSS | B76: 11-2 | C76: Core | D76: Komunikasyon at Pananaliksik sa Wika at Kulturang Pilipino | E76: Filipino | F76: 3 | G76: =SUM(F76:F76) -> 3 | H76: 0 | I76: =H76*G76 -> 0 | K76: =IF(I76>0,F76,"")
A77: HUMSS | B77: 11-2 | C77: Core | D77: Physical Education and Health 2 | E77: Physical Education | F77: 2 | G77: =SUM(F77:F77) -> 2 | H77: 0 | I77: =H77*G77 -> 0 | K77: =IF(I77>0,F77,"")
A78: HUMSS | B78: 11-2 | C78: Applied | D78: Practical Research 1 | F78: 3 | G78: =SUM(F78:F78) -> 3 | H78: 0 | I78: =H78*G78 -> 0 | K78: =IF(I78>0,F78,"")
A79: HUMSS | B79: 11-2 | C79: Specialized | D79: Creative Writing | E79: Social and Behavioral Sciences | F79: 3 | G79: =SUM(F79:F79) -> 3 | H79: 0 | I79: =H79*G79 -> 0 | K79: =IF(I79>0,F79,"")
A80: HUMSS | B80: 11-2 | C80: Specialized | D80: Disciplines and Ideas in the Applied Social Sciences | E80: Social and Behavioral Sciences | F80: 3 | G80: =SUM(F80:F80) -> 3 | H80: 0 | I80: =H80*G80 -> 0 | K80: =IF(I80>0,F80,"")
A81: HUMSS | B81: 11-2 | D81: Homeroom | F81: 1 | G81: =SUM(F81:F81) -> 1 | H81: 0 | I81: =H81*G81 -> 0 | K81: =IF(I81>0,F81,"")
A82: HUMSS | B82: 11-2 | D82: Student Club and Org | F82: 1 | G82: =SUM(F82:F82) -> 1 | H82: 0 | I82: =H82*G82 -> 0 | K82: =IF(I82>0,F82,"")
K83: =IF(I83>0,F83,"")
A84: HUMSS | B84: 12-2 | C84: Core | D84: Contemporary Philippine Arts from the Regions | E84: Social and Behavioral Sciences | F84: 3 | G84: =SUM(F84:F84) -> 3 | H84: 0 | I84: =H84*G84 -> 0 | K84: =IF(I84>0,F84,"")
A85: HUMSS | B85: 12-2 | C85: Core | D85: Physical Education and Health 4 | E85: Physical Education | F85: 2 | G85: =SUM(F85:F85) -> 2 | H85: 0 | I85: =H85*G85 -> 0 | K85: =IF(I85>0,F85,"")
A86: HUMSS | B86: 12-2 | C86: Applied | D86: Empowerment Technologies | E86: Information Technology | F86: 3 | G86: =SUM(F86:F86) -> 3 | H86: 0 | I86: =H86*G86 -> 0 | K86: =IF(I86>0,F86,"")
A87: HUMSS | B87: 12-2 | C87: Applied | D87: Entrepreneurship | E87: Business and Management | F87: 3 | G87: =SUM(F87:F87) -> 3 | H87: 0 | I87: =H87*G87 -> 0 | K87: =IF(I87>0,F87,"")
A88: HUMSS | B88: 12-2 | C88: Applied | D88: Inquiries, Investigations and Immersion | F88: 3 | G88: =SUM(F88:F88) -> 3 | H88: 0 | I88: =H88*G88 -> 0 | K88: =IF(I88>0,F88,"")
A89: HUMSS | B89: 12-2 | C89: Specialized | D89: Work Immersion/Research/Career Advocacy/Culminating Activity | F89: 2 | G89: =SUM(F89:F89) -> 2 | H89: 0 | I89: =H89*G89 -> 0 | K89: =IF(I89>0,F89,"")
A90: HUMSS | B90: 12-2 | C90: Specialized | D90: Trends, Networks, and Critical Thinking in the 21st Century | E90: Social and Behavioral Sciences | F90: 3 | G90: =SUM(F90:F90) -> 3 | H90: 0 | I90: =H90*G90 -> 0 | K90: =IF(I90>0,F90,"")
A91: HUMSS | B91: 12-2 | C91: Specialized | D91: Community Engagement, Solidarity and Citizenship | E91: Social and Behavioral Sciences | F91: 3 | G91: =SUM(F91:F91) -> 3 | H91: 0 | I91: =H91*G91 -> 0 | K91: =IF(I91>0,F91,"")
A92: HUMSS | B92: 12-2 | D92: Homeroom | F92: 1 | G92: =SUM(F92:F92) -> 1 | H92: 0 | I92: =H92*G92 -> 0 | K92: =IF(I92>0,F92,"")
A93: HUMSS | B93: 12-2 | D93: Student Club and Org | F93: 1 | G93: =SUM(F93:F93) -> 1 | H93: 0 | I93: =H93*G93 -> 0 | K93: =IF(I93>0,F93,"")
K94: =IF(I94>0,F94,"")
A95: IT-MAWD | B95: 11-2 | C95: Core | D95: Reading and Writing | E95: English | F95: 3 | G95: =SUM(F95:F95) -> 3 | H95: 0 | I95: =H95*G95 -> 0 | K95: =IF(I95>0,F95,"")
A96: IT-MAWD | B96: 11-2 | C96: Core | D96: Statistics and Probability | E96: Mathematics | F96: 3 | G96: =SUM(F96:F96) -> 3 | H96: 0 | I96: =H96*G96 -> 0 | K96: =IF(I96>0,F96,"")
A97: IT-MAWD | B97: 11-2 | C97: Core | D97: Understanding Culture, Society and Politics | E97: Social and Behavioral Sciences | F97: 3 | G97: =SUM(F97:F97) -> 3 | H97: 0 | I97: =H97*G97 -> 0 | K97: =IF(I97>0,F97,"")
A98: IT-MAWD | B98: 11-2 | C98: Core | D98: Earth and Life Science | E98: Sciences | F98: 3 | G98: =SUM(F98:F98) -> 3 | H98: 0 | I98: =H98*G98 -> 0 | K98: =IF(I98>0,F98,"")
A99: IT-MAWD | B99: 11-2 | C99: Core | D99: Komunikasyon at Pananaliksik sa Wika at Kulturang Pilipino | E99: Filipino | F99: 3 | G99: =SUM(F99:F99) -> 3 | H99: 0 | I99: =H99*G99 -> 0 | K99: =IF(I99>0,F99,"")
A100: IT-MAWD | B100: 11-2 | C100: Core | D100: Physical Education and Health 2 | E100: Physical Education | F100: 2 | G100: =SUM(F100:F100) -> 2 | H100: 0 | I100: =H100*G100 -> 0 | K100: =IF(I100>0,F100,"")
A101: IT-MAWD | B101: 11-2 | C101: Applied | D101: Practical Research 1 | F101: 3 | G101: =SUM(F101:F101) -> 3 | H101: 0 | I101: =H101*G101 -> 0 | K101: =IF(I101>0,F101,"")
...

Sheet Faculty Count Projection
B1: =_xlfn.CONCAT("STI College ",'1 - Top Sheet'!D6:E6) -> STI College Novaliches
B2: Projected Faculty Count
B3: =_xlfn.CONCAT("School Year ",'1 - Top Sheet'!D7:E7," Term ", '1 - Top Sheet'!D8:E8) -> School Year 2024-2025 Term 1
B5: Tertiary Level | H5: High School Level
B7: Field of Specialization | C7: Teaching Load Term 1 | D7: Teaching Load Term 2 | E7: Fulltime FM 24 units | F7: Excess Units | H7: Field of Specialization | I7: Teaching Load Term 1 | J7: Teaching Load Term 2 | K7: Fulltime FM | L7: Excess Units
F8: For PT or Overload | K8: 27 units | L8: For PT or Overload
B9: Accounting | C9: =SUMIF(TER1FIELD,$B9,TER1LOAD) -> 28.5 | D9: =SUMIF(TER2FIELD,$B9,TER2LOAD) -> 0 | E9: =ROUNDDOWN((C9+D9)/24,0) -> 1 | F9: =(C9+D9)-(24*E9) -> 4.5 | H9: Business and Management | I9: =SUMIF(SHS1FIELD,$H9,SHS1LOAD) -> 39 | J9: =SUMIF(SHS2FIELD,$H9,SHS2LOAD) -> 0 | K9: =ROUNDDOWN((I9+J9)/27,0) -> 1 | L9: =(I9+J9)-(27*K9) -> 12
B10: Biological Sciences | C10: =SUMIF(TER1FIELD,$B10,TER1LOAD) -> 0 | D10: =SUMIF(TER2FIELD,$B10,TER2LOAD) -> 0 | E10: =ROUNDDOWN((C10+D10)/24,0) -> 0 | F10: =(C10+D10)-(24*E10) -> 0 | H10: Electrical/Electronics | I10: =SUMIF(SHS1FIELD,$H10,SHS1LOAD) -> 0 | J10: =SUMIF(SHS2FIELD,$H10,SHS2LOAD) -> 0 | K10: =ROUNDDOWN((I10+J10)/27,0) -> 0 | L10: =(I10+J10)-(27*K10) -> 0
B11: Business and Management | C11: =SUMIF(TER1FIELD,$B11,TER1LOAD) -> 0 | D11: =SUMIF(TER2FIELD,$B11,TER2LOAD) -> 0 | E11: =ROUNDDOWN((C11+D11)/24,0) -> 0 | F11: =(C11+D11)-(24*E11) -> 0 | H11: English | I11: =SUMIF(SHS1FIELD,$H11,SHS1LOAD) -> 168 | J11: =SUMIF(SHS2FIELD,$H11,SHS2LOAD) -> 0 | K11: =ROUNDDOWN((I11+J11)/27,0) -> 6 | L11: =(I11+J11)-(27*K11) -> 6
B12: Chemistry | C12: =SUMIF(TER1FIELD,$B12,TER1LOAD) -> 0 | D12: =SUMIF(TER2FIELD,$B12,TER2LOAD) -> 0 | E12: =ROUNDDOWN((C12+D12)/24,0) -> 0 | F12: =(C12+D12)-(24*E12) -> 0 | H12: Filipino | I12: =SUMIF(SHS1FIELD,$H12,SHS1LOAD) -> 102 | J12: =SUMIF(SHS2FIELD,$H12,SHS2LOAD) -> 0 | K12: =ROUNDDOWN((I12+J12)/27,0) -> 3 | L12: =(I12+J12)-(27*K12) -> 21
B13: Communications | C13: =SUMIF(TER1FIELD,$B13,TER1LOAD) -> 0 | D13: =SUMIF(TER2FIELD,$B13,TER2LOAD) -> 0 | E13: =ROUNDDOWN((C13+D13)/24,0) -> 0 | F13: =(C13+D13)-(24*E13) -> 0 | H13: Hospitality/Culinary Mgt | I13: =SUMIF(SHS1FIELD,$H13,SHS1LOAD) -> 24 | J13: =SUMIF(SHS2FIELD,$H13,SHS2LOAD) -> 0 | K13: =ROUNDDOWN((I13+J13)/27,0) -> 0 | L13: =(I13+J13)-(27*K13) -> 24
B14: Computer Graphics | C14: =SUMIF(TER1FIELD,$B14,TER1LOAD) -> 0 | D14: =SUMIF(TER2FIELD,$B14,TER2LOAD) -> 0 | E14: =ROUNDDOWN((C14+D14)/24,0) -> 0 | F14: =(C14+D14)-(24*E14) -> 0 | H14: Information Technology | I14: =SUMIF(SHS1FIELD,$H14,SHS1LOAD) -> 36 | J14: =SUMIF(SHS2FIELD,$H14,SHS2LOAD) -> 0 | K14: =ROUNDDOWN((I14+J14)/27,0) -> 1 | L14: =(I14+J14)-(27*K14) -> 9
B15: Criminology | C15: =SUMIF(TER1FIELD,$B15,TER1LOAD) -> 0 | D15: =SUMIF(TER2FIELD,$B15,TER2LOAD) -> 0 | E15: =ROUNDDOWN((C15+D15)/24,0) -> 0 | F15: =(C15+D15)-(24*E15) -> 0 | H15: Mathematics | I15: =SUMIF(SHS1FIELD,$H15,SHS1LOAD) -> 93 | J15: =SUMIF(SHS2FIELD,$H15,SHS2LOAD) -> 0 | K15: =ROUNDDOWN((I15+J15)/27,0) -> 3 | L15: =(I15+J15)-(27*K15) -> 12
B16: Engineering | C16: =SUMIF(TER1FIELD,$B16,TER1LOAD) -> 62 | D16: =SUMIF(TER2FIELD,$B16,TER2LOAD) -> 0 | E16: =ROUNDDOWN((C16+D16)/24,0) -> 2 | F16: =(C16+D16)-(24*E16) -> 14 | H16: Physical Education | I16: =SUMIF(SHS1FIELD,$H16,SHS1LOAD) -> 129 | J16: =SUMIF(SHS2FIELD,$H16,SHS2LOAD) -> 0 | K16: =ROUNDDOWN((I16+J16)/27,0) -> 4 | L16: =(I16+J16)-(27*K16) -> 21
B17: English/Foreign Language | C17: =SUMIF(TER1FIELD,$B17,TER1LOAD) -> 84 | D17: =SUMIF(TER2FIELD,$B17,TER2LOAD) -> 0 | E17: =ROUNDDOWN((C17+D17)/24,0) -> 3 | F17: =(C17+D17)-(24*E17) -> 12 | H17: Sciences | I17: =SUMIF(SHS1FIELD,$H17,SHS1LOAD) -> 114 | J17: =SUMIF(SHS2FIELD,$H17,SHS2LOAD) -> 0 | K17: =ROUNDDOWN((I17+J17)/27,0) -> 4 | L17: =(I17+J17)-(27*K17) -> 6
B18: Filipino | C18: =SUMIF(TER1FIELD,$B18,TER1LOAD) -> 0 | D18: =SUMIF(TER2FIELD,$B18,TER2LOAD) -> 0 | E18: =ROUNDDOWN((C18+D18)/24,0) -> 0 | F18: =(C18+D18)-(24*E18) -> 0 | H18: Social and Behavioral Sciences | I18: =SUMIF(SHS1FIELD,$H18,SHS1LOAD) -> 207 | J18: =SUMIF(SHS2FIELD,$H18,SHS2LOAD) -> 0 | K18: =ROUNDDOWN((I18+J18)/27,0) -> 7 | L18: =(I18+J18)-(27*K18) -> 18
B19: Hospitality/Culinary Mgt | C19: =SUMIF(TER1FIELD,$B19,TER1LOAD) -> 89 | D19: =SUMIF(TER2FIELD,$B19,TER2LOAD) -> 0 | E19: =ROUNDDOWN((C19+D19)/24,0) -> 3 | F19: =(C19+D19)-(24*E19) -> 17 | H19: Tourism Management | I19: =SUMIF(SHS1FIELD,$H19,SHS1LOAD) -> 24 | J19: =SUMIF(SHS2FIELD,$H19,SHS2LOAD) -> 0 | K19: =ROUNDDOWN((I19+J19)/27,0) -> 0 | L19: =(I19+J19)-(27*K19) -> 24
B20: Information Technology | C20: =SUMIF(TER1FIELD,$B20,TER1LOAD) -> 340.5 | D20: =SUMIF(TER2FIELD,$B20,TER2LOAD) -> 0 | E20: =ROUNDDOWN((C20+D20)/24,0) -> 14 | F20: =(C20+D20)-(24*E20) -> 4.5
B21: Law | C21: =SUMIF(TER1FIELD,$B21,TER1LOAD) -> 0 | D21: =SUMIF(TER2FIELD,$B21,TER2LOAD) -> 0 | E21: =ROUNDDOWN((C21+D21)/24,0) -> 0 | F21: =(C21+D21)-(24*E21) -> 0
B22: Mathematics | C22: =SUMIF(TER1FIELD,$B22,TER1LOAD) -> 51 | D22: =SUMIF(TER2FIELD,$B22,TER2LOAD) -> 0 | E22: =ROUNDDOWN((C22+D22)/24,0) -> 2 | F22: =(C22+D22)-(24*E22) -> 3
B23: Multimedia Arts | C23: =SUMIF(TER1FIELD,$B23,TER1LOAD) -> 153.5 | D23: =SUMIF(TER2FIELD,$B23,TER2LOAD) -> 0 | E23: =ROUNDDOWN((C23+D23)/24,0) -> 6 | F23: =(C23+D23)-(24*E23) -> 9.5
B24: Philosophy | C24: =SUMIF(TER1FIELD,$B24,TER1LOAD) -> 0 | D24: =SUMIF(TER2FIELD,$B24,TER2LOAD) -> 0 | E24: =ROUNDDOWN((C24+D24)/24,0) -> 0 | F24: =(C24+D24)-(24*E24) -> 0
B25: Physical Education | C25: =SUMIF(TER1FIELD,$B25,TER1LOAD) -> 92 | D25: =SUMIF(TER2FIELD,$B25,TER2LOAD) -> 0 | E25: =ROUNDDOWN((C25+D25)/24,0) -> 3 | F25: =(C25+D25)-(24*E25) -> 20
B26: Physical Sciences | C26: =SUMIF(TER1FIELD,$B26,TER1LOAD) -> 0 | D26: =SUMIF(TER2FIELD,$B26,TER2LOAD) -> 0 | E26: =ROUNDDOWN((C26+D26)/24,0) -> 0 | F26: =(C26+D26)-(24*E26) -> 0
B27: Psychology | C27: =SUMIF(TER1FIELD,$B27,TER1LOAD) -> 0 | D27: =SUMIF(TER2FIELD,$B27,TER2LOAD) -> 0 | E27: =ROUNDDOWN((C27+D27)/24,0) -> 0 | F27: =(C27+D27)-(24*E27) -> 0
B28: Social and Behavioral Science | C28: =SUMIF(TER1FIELD,$B28,TER1LOAD) -> 162 | D28: =SUMIF(TER2FIELD,$B28,TER2LOAD) -> 0 | E28: =ROUNDDOWN((C28+D28)/24,0) -> 6 | F28: =(C28+D28)-(24*E28) -> 18
B29: Tourism Management | C29: =SUMIF(TER1FIELD,$B29,TER1LOAD) -> 25 | D29: =SUMIF(TER2FIELD,$B29,TER2LOAD) -> 0 | E29: =ROUNDDOWN((C29+D29)/24,0) -> 1 | F29: =(C29+D29)-(24*E29) -> 1

Sheet 4.2 - SHS Schedule
A1: =_xlfn.CONCAT("STI College ",'1 - Top Sheet'!C6:D6) -> STI College Novaliches
A2: SHS Schedule
A3: =_xlfn.CONCAT("School Year ",'1 - Top Sheet'!C7:D7," Term ", '1 - Top Sheet'!C8:D8) -> School Year 2024-2025 Term 1
A5: SECTION | B5: SUBJECT CODE | C5: SUBJECT DESCRIPTION | D5: DAY | E5: TIME | H5: ROOM | I5: TEACHER
A6: ABM101 | C6: 21st Century Literature | D6: M/TH | E6: 0.29166667 | G6: 0.35416667 | H6: 501 | I6: Mark Joseph Tan
C7: General Mathematics | D7: M/TH | E7: 0.35416667 | G7: 0.41666667 | H7: 501 | I7: John Paul Cabanero
C8: Intro to the Philo of Human | D8: M/TH | E8: 0.47916667 | G8: 0.54166667 | H8: 501 | I8: Elvira Sigua
C9: Business Mathematics | D9: T/F | E9: 0.29166667 | G9: 0.35416667 | H9: 501 | I9: Math PTFL
C10: Oral Communication | D10: T/F | E10: 0.35416667 | G10: 0.41666667 | H10: 501 | I10: Mark Joseph Tan
C11: Physical Education & Health 1 | D11: T/F | E11: 0.47916667 | G11: 0.54166667 | H11: COURT | I11: Mary Rose Batan
C12: Homeroom G11-1st Term | D12: M | E12: 0.54166667 | G12: 0.58333333
C13: Organization & Management | D13: W | E13: 0.29166667 | G13: 0.41666667 | H13: 501 | I13: Joshua Uclusin
C14: Media and Information Literarcy | D14: W | E14: 0.47916667 | G14: 0.60416667 | H14: 501 | I14: Aiza Mae Akkang
A19: SECTION | B19: SUBJECT CODE | C19: SUBJECT DESCRIPTION | D19: DAY | E19: TIME | H19: ROOM | I19: TEACHER
A20: ABM102 | C20: 21st Century Literature | D20: M/TH | E20: 0.35416667 | G20: 0.41666667 | H20: 502
C21: General Mathematics | D21: M/TH | E21: 0.41666667 | G21: 0.97916667 | H21: 502
C22: Intro to the Philo of Human | D22: M/TH | E22: 0.54166667 | G22: 0.60416667 | H22: 502
C23: Oral Communication | D23: T/F | E23: 0.35416667 | G23: 0.41666667 | H23: 502
C24: Organization & Management | D24: T/F | E24: 0.41666667 | G24: 0.97916667 | H24: 502
C25: Media and Information Literarcy | D25: T/F | E25: 0.54166667 | G25: 0.60416667 | H25: 502
C26: Business Mathematics | D26: W | E26: 0.29166667 | G26: 0.41666667 | H26: 502
C27: Homeroom G11-1st Term | D27: W | E27: 0.5625 | G27: 0.60416667
C28: Business Mathematics | D28: W | E28: 0.29166667 | G28: 0.41666667 | H28: 502
C29: Physical Education & Health 1 | D29: W | E29: 0.47916667 | G29: 0.5625 | H29: COURT
A33: SECTION | B33: SUBJECT CODE | C33: SUBJECT DESCRIPTION | D33: DAY | E33: TIME | H33: ROOM | I33: TEACHER
A34: ABM103 | C34: 21st Century Literature | D34: M/TH | E34: 0.35416667 | G34: 0.41666667 | H34: 503 | I34: Mark Joseph Tan
C35: General Mathematics | D35: M/TH | E35: 0.47916667 | G35: 0.54166667 | H35: 503 | I35: John Paul Cabanero
C36: Intro to the Philo of Human | D36: T/F | E36: 0.29166667 | G36: 0.35416667 | H36: 503 | I36: Elvira Sigua
C37: Oral Communication | D37: T/F | E37: 0.47916667 | G37: 0.54166667 | H37: 503 | I37: English PTFL
C38: Organization & Management | D38: W | E38: 0.47916667 | G38: 0.60416667 | H38: 303 | I38: Joshua Uclusin
C39: Media and Information Literarcy | D39: T/F | E39: 0.35416667 | G39: 0.41666667 | H39: 503 | I39: Aiza Mae Akkang
C40: Business Mathematics | D40: M/TH | E40: 0.29166667 | G40: 0.35416667 | H40: 503 | I40: Math PTFL
C41: Homeroom G11-1st Term | D41: W | E41: 0.60416667 | G41: 0.64583333
C42: Physical Education & Health 1 | D42: W | E42: 0.33333333 | G42: 0.41666667 | H42: COURT | I42: Mary Rose Batan
A47: SECTION | B47: SUBJECT CODE | C47: SUBJECT DESCRIPTION | D47: DAY | E47: TIME | H47: ROOM | I47: TEACHER
A48: CULART101 | C48: 21st Century Literature | D48: M/TH | E48: 0.47916667 | G48: 0.54166667 | H48: 504 | I48: Evelyn Quarteros
C49: Oral Communication | D49: T/F | E49: 0.54166667 | G49: 0.60416667 | H49: 504
C50: Media and Information Literacy | D50: T/F | E50: 0.41666667 | G50: 0.47916667 | H50: 504 | I50: Aiza Mae Akkang
C51: Intro to the Philo of Human | D51: T/F | E51: 0.35416667 | G51: 0.41666667 | H51: 504 | I51: Elvira Sigua
C52: General Mathematics | D52: M/TH | E52: 0.54166667 | G52: 0.60416667 | H52: 504 | I52: John Paul Cabanero
C53: Homeroom G11-1st Term | D53: W | E53: 0.5625 | G53: 0.60416667
C54: Physical Education & Health 1 | D54: W | E54: 0.47916667 | G54: 0.5625 | H54: COURT | I54: Mary Rose Batan
C55: Basic Food Production 101 | D55: M/TH | E55: 0.35416667 | G55: 0.41666667 | H55: 504 | I55: Ramon Alila
C56: Intro to Culinary Operations | D56: W | E56: 0.29166667 | G56: 0.41666667 | H56: 504 | I56: Ramon Alila
A61: SECTION | B61: SUBJECT CODE | C61: SUBJECT DESCRIPTION | D61: DAY | E61: TIME | H61: ROOM | I61: TEACHER
A62: CULART102 | B62: CORE1013 | C62: Physical Education & Health 1 | I62: PE PTFL
B63: CORE1021 | C63: Homeroom G11-1st Term
B64: SPECIAL1008 | C64: Basic Food Production 101 | D64: MTh | E64: 0.41666667 | G64: 0.47916667 | H64: RM505 | I64: Ramon Alila
B65: CORE1001 | C65: 21st Century Literature | D65: MTh | E65: 0.54166667 | G65: 0.60416667 | H65: RM505 | I65: Mark Joseph Tan
B66: CORE1006 | C66: General Mathematics | D66: TF | E66: 0.29166667 | G66: 0.35416667 | H66: RM505 | I66: John Paul Cabanero
B67: CORE1007 | C67: Intro to the Philo of Human | D67: TF | E67: 0.35416667 | G67: 0.41666667 | H67: RM505 | I67: Jeramie Poche
B68: CORE1009 | C68: Media and Information Literacy | D68: TF | E68: 0.47916667 | G68: 0.54166667 | H68: RM505 | I68: Reychelle Finez
B69: CORE1010 | C69: Oral Communication | D69: W | E69: 0.29166667 | G69: 0.41666667 | H69: RM505 | I69: English PTFL
B70: SPECIAL1054 | C70: Intro to Culinary Operations | D70: W | E70: 0.47916667 | G70: 0.60416667 | H70: RM504 | I70: Ramon Alila
A75: SECTION | B75: SUBJECT CODE | C75: SUBJECT DESCRIPTION | D75: DAY | E75: TIME | H75: ROOM | I75: TEACHER
A76: DIGI101 | B76: CORE1021 | C76: Homeroom G11-1st Term
B77: SPECIAL1001 | C77: 2D Concepts | D77: MTh | E77: 0.29166667 | G77: 0.35416667 | H77: MO2 | I77: Cyrus Barquilla
B78: SPECIAL1007 | C78: Basic Drawing & Drafting | D78: MTh | E78: 0.35416667 | G78: 0.41666667 | H78: RM512 | I78: IT PTFL
B79: CORE1001 | C79: 21st Century Literature | D79: TF | E79: 0.29166667 | G79: 0.35416667 | H79: RM506 | I79: English PTFL
B80: CORE1006 | C80: General Mathematics | D80: TF | E80: 0.35416667 | G80: 0.41666667 | H80: RM506 | I80: John Paul Cabanero
B81: CORE1007 | C81: Intro to the Philo of Human | D81: TF | E81: 0.47916667 | G81: 0.54166667 | H81: RM506 | I81: Elvira Sigua
B82: CORE1009 | C82: Media and Information Literacy | D82: TF | E82: 0.54166667 | G82: 0.60416667 | H82: RM506 | I82: SOCSCI PTFL
B83: CORE1013 | C83: Physical Education & Health 1 | D83: W | E83: 0.33333333 | G83: 0.41666667 | H83: COURT | I83: PE PTFL
B84: CORE1010 | C84: Oral Communication | D84: W | E84: 0.47916667 | G84: 0.60416667 | H84: RM502 | I84: English PTFL
A89: SECTION | B89: SUBJECT CODE | C89: SUBJECT DESCRIPTION | D89: DAY | E89: TIME | H89: ROOM | I89: TEACHER
A90: HUMSS101 | B90: CORE1013 | C90: Physical Education & Health 1 | D90: TH | E90: 0.625 | G90: 0.70833333 | H90: COURT | I90: Daryl Eunice Cabauatan
B91: CORE1021 | C91: Homeroom G11-1st Term
B92: SPECIAL1057 | C92: Intro to World Rel & BS | D92: MTh | E92: 0.54166667 | G92: 0.60416667 | H92: RM507 | I92: SOCSCI PTFL
B93: CORE1010 | C93: Oral Communication | D93: MTh | E93: 0.35416667 | G93: 0.41666667 | H93: RM507 | I93: English PTFL
B94: SPECIAL1034 | C94: Disciplines & Ideas in the SS | D94: MTh | E94: 0.41666667 | G94: 0.47916667 | H94: RM507 | I94: Reychelle Finez
B95: CORE1009 | C95: Media and Information Literacy | D95: TF | E95: 0.60416667 | G95: 0.66666667 | H95: RM507 | I95: SOCSCI PTFL
B96: CORE1001 | C96: 21st Century Literature | D96: TF | E96: 0.35416667 | G96: 0.41666667 | H96: RM507 | I96: Mark Joseph Tan
B97: CORE1006 | C97: General Mathematics | D97: TF | E97: 0.41666667 | G97: 0.47916667 | H97: RM507 | I97: MATH PTFL
B98: CORE1007 | C98: Intro to the Philo of Human | D98: TF | E98: 0.54166667 | G98: 0.60416667 | H98: RM507 | I98: Jeramie Poche
A103: SECTION | B103: SUBJECT CODE | C103: SUBJECT DESCRIPTION | D103: DAY | E103: TIME | H103: ROOM | I103: TEACHER
A104: HUMSS102 | B104: CORE1013 | C104: Physical Education & Health 1 | D104: M | E104: 0.60416667 | G104: 0.6875 | H104: COURT | I104: PE PTFL
B105: CORE1021 | C105: Homeroom G11-1st Term
B106: CORE1010 | C106: Oral Communication | D106: MTh | E106: 0.35416667 | G106: 0.41666667 | H106: RM508 | I106: English PTFL
B107: SPECIAL1057 | C107: Intro to World Rel & BS | D107: MTh | E107: 0.47916667 | G107: 0.54166667 | H107: RM508 | I107: Reychelle Finez
B108: CORE1001 | C108: 21st Century Literature | D108: TF | E108: 0.35416667 | G108: 0.41666667 | H108: RM508 | I108: Monalyn Fedelino
B109: CORE1006 | C109: General Mathematics | D109: TF | E109: 0.47916667 | G109: 0.54166667 | H109: RM508 | I109: John Paul Cabanero
B110: SPECIAL1034 | C110: Disciplines & Ideas in the SS | D110: TF | E110: 0.54166667 | G110: 0.60416667 | H110: RM508 | I110: Reychelle Finez
B111: CORE1007 | C111: Intro to the Philo of Human | D111: W | E111: 0.29166667 | G111: 0.41666667 | H111: RM508 | I111: Jeramie Poche
B112: CORE1009 | C112: Media and Information Literacy | D112: W | E112: 0.47916667 | G112: 0.60416667 | H112: RM508 | I112: Carel Macalinao
A117: SECTION | B117: SUBJECT CODE | C117: SUBJECT DESCRIPTION | D117: DAY | E117: TIME | H117: ROOM | I117: TEACHER
A118: HUMSS103 | B118: CORE1013 | C118: Physical Education & Health 1 | D118: T | E118: 0.60416667 | G118: 0.64583333 | H118: COURT | I118: Daryl Eunice Cabauatan
B119: CORE1021 | C119: Homeroom G11-1st Term
B120: CORE1010 | C120: Oral Communication | D120: T/F | E120: 0.41666667 | G120: 0.47916667 | H120: RM506 | I120: Sharmaine Villasenor
B121: SPECIAL1057 | C121: Intro to World Rel & BS | D121: W | E121: 0.47916667 | G121: 0.60416667 | H121: RM504 | I121: Reychelle Finez
B122: CORE1001 | C122: 21st Century Literature | D122: T/F | E122: 0.54166667 | G122: 0.60416667 | H122: RM503 | I122: Mark Joseph Tan
B123: CORE1006 | C123: General Mathematics | D123: W | E123: 0.29166667 | G123: 0.41666667 | H123: RM503 | I123: Nilidyn Donio
B124: SPECIAL1034 | C124: Disciplines & Ideas in the SS | D124: M/TH | E124: 0.29166667 | G124: 0.35416667 | H124: RM508 | I124: Reychelle Finez
B125: CORE1007 | C125: Intro to the Philo of Human | D125: M/TH | E125: 0.35416667 | G125: 0.41666667 | H125: RM506 | I125: Reychelle Finez
B126: CORE1009 | C126: Media and Information Literacy | D126: M/TH | E126: 0.47916667 | G126: 0.54166667 | H126: RM506 | I126: Aiza Mae Akkang
A131: SECTION | B131: SUBJECT CODE | C131: SUBJECT DESCRIPTION | D131: DAY | E131: TIME | H131: ROOM | I131: TEACHER
A132: IT101 | B132: CORE1013 | C132: Physical Education & Health 1 | D132: F | E132: 0.54166667 | G132: 0.625 | H132: COURT | I132: Daryl Eunice Cabauatan
B133: CORE1021 | C133: Homeroom G11-1st Term
B134: SPECIAL1093 | C134: Computer/Web Programming 1 | D134: MTh | E134: 0.29166667 | G134: 0.35416667 | H134: RM509/LAB209 | I134: Cyrus Barquilla
B135: SPECIAL1094 | C135: Computer/Web Programming 2 | D135: MTh | E135: 0.35416667 | G135: 0.41666667 | H135: LAB209/RM509 | I135: Cyrus Barquilla
B136: CORE1010 | C136: Oral Communication | D136: MTh | E136: 0.47916667 | G136: 0.54166667 | H136: RM509 | I136: English PTFL
...

Sheet 4.1 - TER Schedule
A1: =_xlfn.CONCAT("STI College ",'1 - Top Sheet'!C6:D6) -> STI College Novaliches
A2: Tertiary Schedule
A3: =_xlfn.CONCAT("School Year ",'1 - Top Sheet'!C7:D7," Term ", '1 - Top Sheet'!C8:D8) -> School Year 2024-2025 Term 1
A5: SECTION | B5: COURSE CODE | C5: COURSE DESCRIPTION | D5: DAY | E5: TIME | H5: ROOM | I5: INSTRUCTOR
A6: BT101 | B6: CITE1004 | C6: Introduction to Computing | D6: TF | E6: 4:00PM | G6: 6:00PM | H6: 203/LAB209 | I6: ITFT1
B7: CITE1003 | C7: Computer Programming 1 | D7: M | E7: 0.33333333 | G7: 0.41666667 | H7: 201 | I7: Eugene
B8: CITE1003 | C8: Computer Programming 1 | D8: M | E8: 0.41666667 | G8: 0.54166667 | H8: LAB210 | I8: Eugene
B9: GEDC1002 | C9: The Contemporary World | D9: S | E9: 12:30PM | G9: 3:30PM | H9: 306 | I9: SOC SCI FT4
B10: STIC1002 | C10: Euthenics 1 | D10: S | E10: 3:30PM | G10: 4:30PM | H10: 306 | I10: SOC SCI FT4
B11: GEDC1016 | C11: Purposive Communication | D11: MTH | E11: 0.60416667 | G11: 0.66666667 | H11: 301 | I11: BONCAN
B12: NSTP1008 | C12: National Service Training Program 1 | D12: TF | E12: 0.54166667 | G12: 0.60416667 | H12: 302 | I12: PALMERO
B13: PHED1005 | C13: P.E./PATHFIT 1: Movement Competency Training | D13: TH | E13: 0.5 | G13: 0.58333333 | H13: COURT | I13: SABORIENDO-GARCIA
B14: GEDC1041 | C14: Philippine Popular Culture | D14: TF | E14: 0.60416667 | G14: 0.66666667 | H14: 407 | I14: SOC SCI FT2
B15: GEDC1008 | C15: Understanding the Self | D15: MTH | E15: 0.60416667 | G15: 0.66666667 | H15: 301 | I15: BONCAN
A19: SECTION | B19: COURSE CODE | C19: COURSE DESCRIPTION | D19: DAY | E19: TIME | H19: ROOM | I19: INSTRUCTOR
A20: BT102 | B20: CITE1004 | C20: Introduction to Computing | D20: F | E20: 0.5 | G20: 2:00PM | H20: 207/LAB211 | I20: AGUILA
B21: CITE1003 | C21: Computer Programming 1 | D21: T | E21: 0.33333333 | G21: 0.41666667 | H21: 201 | I21: RESULLAR
B22: CITE1003 | C22: Computer Programming 1 | D22: T | E22: 0.41666667 | G22: 0.54166667 | H22: LAB210 | I22: RESULLAR
B23: GEDC1002 | C23: The Contemporary World | D23: MTH | E23: 0.35416667 | G23: 0.41666667 | H23: 302 | I23: SOC SCI FT4
B24: STIC1002 | C24: Euthenics 1 | D24: MTH | E24: 0.66666667 | G24: 0.70833333 | H24: 204 | I24: ROSALES
B25: GEDC1016 | C25: Purposive Communication | D25: MTH | E25: 0.47916667 | G25: 0.54166667 | H25: 308 | I25: BONCAN
B26: NSTP1008 | C26: National Service Training Program 1 | D26: MTH | E26: 0.29166667 | G26: 0.35416667 | H26: 306 | I26: PALMERO
B27: PHED1005 | C27: P.E./PATHFIT 1: Movement Competency Training | D27: T | E27: 0.60416667 | G27: 0.6875 | H27: COURT | I27: SABORIENDO-GARCIA
B28: GEDC1041 | C28: Philippine Popular Culture | D28: W | E28: 0.29166667 | G28: 0.41666667 | H28: 302 | I28: CAGADO
B29: GEDC1008 | C29: Understanding the Self | D29: MTH | E29: 0.60416667 | G29: 0.66666667 | H29: 307 | I29: BAGOL
A33: SECTION | B33: COURSE CODE | C33: COURSE DESCRIPTION | D33: DAY | E33: TIME | H33: ROOM | I33: INSTRUCTOR
A34: BT103 | B34: CITE1004 | C34: Introduction to Computing | D34: TH | E34: 0.29166667 | G34: 8:30AM | H34: LAB210/M02 | I34: IT FT1
B35: CITE1003 | C35: Computer Programming 1 | D35: M | E35: 0.41666667 | G35: 0 | H35: 201 | I35: IT FT 2
B36: CITE1003 | C36: Computer Programming 1 | D36: M | E36: 0.29166667 | G36: 0.41666667 | H36: LAB210 | I36: IT FT 2
B37: GEDC1002 | C37: The Contemporary World | D37: W | E37: 0.3125 | G37: 0.4375 | H37: 308 | I37: MAGABILIN
B38: STIC1002 | C38: Euthenics 1 | D38: W | E38: 0.4375 | G38: 0.47916667 | H38: 308 | I38: MAGABILIN
B39: GEDC1016 | C39: Purposive Communication | D39: TF | E39: 0.47916667 | G39: 0.54166667 | H39: 306 | I39: SINDICO
B40: NSTP1008 | C40: National Service Training Program 1 | D40: TF | E40: 0.41666667 | G40: 0.47916667 | H40: 407 | I40: ROSALES
B41: PHED1005 | C41: P.E./PATHFIT 1: Movement Competency Training | D41: F | E41: 0.5625 | G41: 0.64583333 | H41: COURT | I41: SABORIENDO-GARCIA
B42: GEDC1041 | C42: Philippine Popular Culture | D42: W | E42: 0.54166667 | G42: 0.66666667 | H42: 201 | I42: CAGADO
B43: GEDC1008 | C43: Understanding the Self | D43: TF | E43: 0.29166667 | G43: 0.35416667 | H43: 410 | I43: BAGOL
A47: SECTION | B47: COURSE CODE | C47: COURSE DESCRIPTION | D47: DAY | E47: TIME | H47: ROOM | I47: INSTRUCTOR
A48: BT104 | B48: CITE1004 | C48: Introduction to Computing | D48: T | E48: 8:00AM | G48: 10:00AM | H48: M01/LAB211 | I48: AGUILA
B49: CITE1003 | C49: Computer Programming 1 | D49: W | E49: 0.29166667 | G49: 0.41666667 | H49: LAB209 | I49: IT FT 2
B50: CITE1003 | C50: Computer Programming 1 | D50: W | E50: 0.41666667 | G50: 0.5 | H50: 201 | I50: IT FT 2
B51: GEDC1002 | C51: The Contemporary World | D51: MTH | E51: 0.60416667 | G51: 0.66666667 | H51: 306 | I51: SOC SCI FT1
B52: STIC1002 | C52: Euthenics 1 | D52: W | E52: 0.5625 | G52: 0.60416667 | H52: 410 | I52: BAGOL
B53: GEDC1016 | C53: Purposive Communication | D53: MTH | E53: 0.54166667 | G53: 0.60416667 | H53: 306 | I53: ENGLISH FT
B54: NSTP1008 | C54: National Service Training Program 1 | D54: TF | E54: 0.60416667 | G54: 0.66666667 | H54: 303 | I54: PALMERO
B55: PHED1005 | C55: P.E./PATHFIT 1: Movement Competency Training | D55: TH | E55: 0.35416667 | G55: 0.4375 | H55: COURT | I55: TAGURMACON
B56: GEDC1041 | C56: Philippine Popular Culture | D56: TF | E56: 0.52083333 | G56: 0.58333333 | H56: 202 | I56: SOC SCI FT2
B57: GEDC1008 | C57: Understanding the Self | D57: W | E57: 0.60416667 | G57: 0.72916667 | H57: 410 | I57: BAGOL
A61: SECTION | B61: COURSE CODE | C61: COURSE DESCRIPTION | D61: DAY | E61: TIME | H61: ROOM | I61: INSTRUCTOR
A62: BT105 | B62: CITE1004 | C62: Introduction to Computing | D62: THF | E62: 8:30AM | G62: 10:00AM | H62: LAB211/M01 | I62: IT FT2
B63: CITE1003 | C63: Computer Programming 1 | D63: W | E63: 0.41666667 | G63: 0.54166667 | H63: LAB210 | I63: RESULLAR
B64: CITE1003 | C64: Computer Programming 1 | D64: W | E64: 0.33333333 | G64: 0.41666667 | H64: 201 | I64: RESULLAR
B65: GEDC1002 | C65: The Contemporary World | D65: TF | E65: 0.66666667 | G65: 0.72916667 | H65: 206 | I65: SOC SCI FT4
B66: STIC1002 | C66: Euthenics 1 | D66: S | E66: 0.66666667 | G66: 0.70833333 | H66: 307 | I66: CASTILLO
B67: GEDC1016 | C67: Purposive Communication | D67: TF | E67: 0.60416667 | G67: 0.66666667 | H67: 206 | I67: ENGLISH FT
B68: NSTP1008 | C68: National Service Training Program 1 | D68: S | E68: 0.54166667 | G68: 0.66666667 | H68: 307 | I68: CASTILLO
B69: PHED1005 | C69: P.E./PATHFIT 1: Movement Competency Training | D69: TH | E69: 0.47916667 | G69: 0.5625 | H69: COURT | I69: TAGURMACON
B70: GEDC1041 | C70: Philippine Popular Culture | D70: TH | E70: 0.60416667 | G70: 0.72916667 | H70: 302 | I70: SOC SCI FT2
B71: GEDC1008 | C71: Understanding the Self | D71: W | E71: 2:30PM | G71: 5:30PM | H71: 308 | I71: MAGABILIN
A75: SECTION | B75: COURSE CODE | C75: COURSE DESCRIPTION | D75: DAY | E75: TIME | H75: ROOM | I75: INSTRUCTOR
A76: BT106 | B76: CITE1004 | C76: Introduction to Computing
B77: CITE1003 | C77: Computer Programming 1 | D77: TH | E77: 0.41666667 | G77: 0.54166667 | H77: LAB210 | I77: RESULLAR
B78: CITE1003 | C78: Computer Programming 1 | D78: TH | E78: 0.33333333 | G78: 0.41666667 | H78: 201 | I78: RESULLAR
B79: GEDC1002 | C79: The Contemporary World
B80: STIC1002 | C80: Euthenics 1
B81: GEDC1016 | C81: Purposive Communication
B82: NSTP1008 | C82: National Service Training Program 1
B83: PHED1005 | C83: P.E./PATHFIT 1: Movement Competency Training
B84: GEDC1041 | C84: Philippine Popular Culture
B85: GEDC1008 | C85: Understanding the Self
A89: SECTION | B89: COURSE CODE | C89: COURSE DESCRIPTION | D89: DAY | E89: TIME | H89: ROOM | I89: INSTRUCTOR
A90: BT301 | B90: COSC1003 | C90: Data Structures and Algorithms | D90: W | E90: 0.58333333 | G90: 0.66666667 | H90: 205 | I90: DOMINGUEZ
B91: COSC1003 | C91: Data Structures and Algorithms | D91: S | E91: 0.54166667 | G91: 0.66666667 | H91: 210 | I91: DOMINGUEZ
B92: GEDC1006 | C92: Readings in Philippine History | D92: S | E92: 0.35416667 | G92: 0.47916667 | H92: 204 | I92: CONDINO
B93: PHED1007 | C93: P.E./PATHFIT 3: Individual-Dual Sports | D93: F | E93: 0.29166667 | G93: 0.375 | H93: COURT | I93: TAGURMACON
B94: GEDC1014 | C94: Rizal's Life and Works | D94: TF | E94: 0.66666667 | G94: 0.72916667 | H94: 602 | I94: BAGOL
B95: COSC1007 | C95: Human-Computer Interaction | D95: M | E95: 0.97916667 | G95: 0.54166667 | H95: 211 | I95: FELICEN
B96: COSC1007 | C96: Human-Computer Interaction | D96: M | E96: 0.58333333 | G96: 0.66666667 | H96: 204 | I96: FELICEN
B97: INTE1015 | C97: IT Elective 1 | D97: T | E97: 0.91666667 | G97: 0.5 | H97: 204 | I97: GAID
B98: INTE1015 | C98: IT Elective 1 | D98: T | E98: 0.58333333 | G98: 0.66666667 | H98: 209 | I98: GAID
B99: COSC1001 | C99: Principles of Communication | D99: MTH | E99: 0.41666667 | G99: 11:30AM | H99: M01 | I99: COE FT1
B100: COSC1008 | C100: Platform Technology (Operating Systems) | D100: T | E100: 0.91666667 | G100: 0.5 | H100: 204 | I100: LLENO
B101: COSC1008 | C101: Platform Technology (Operating Systems) | D101: T | E101: 0.58333333 | G101: 0.66666667 | H101: 211 | I101: LLENO
A103: SECTION | B103: COURSE CODE | C103: COURSE DESCRIPTION | D103: DAY | E103: TIME | H103: ROOM | I103: INSTRUCTOR
A104: BT302 | B104: COSC1003 | C104: Data Structures and Algorithms | D104: W | E104: 0.33333333 | G104: 0.41666667 | H104: 202 | I104: DOMINGUEZ
B105: COSC1003 | C105: Data Structures and Algorithms | D105: W | E105: 0.41666667 | G105: 0.54166667 | H105: 211 | I105: DOMINGUEZ
B106: GEDC1006 | C106: Readings in Philippine History | D106: TF | E106: 0.54166667 | G106: 0.60416667 | H106: 306 | I106: CONDINO
B107: PHED1007 | C107: P.E./PATHFIT 3: Individual-Dual Sports | D107: TH | E107: 0.39583333 | G107: 0.47916667 | H107: COURT | I107: PE PT
B108: GEDC1014 | C108: Rizal's Life and Works | D108: MTH | E108: 0.47916667 | G108: 0.54166667 | H108: 402 | I108: BAGOL
B109: COSC1007 | C109: Human-Computer Interaction | D109: M | E109: 0.33333333 | G109: 0.41666667 | H109: 203 | I109: FELICEN
B110: COSC1007 | C110: Human-Computer Interaction | D110: M | E110: 0.41666667 | G110: 0.47916667 | H110: 211 | I110: FELICEN
C111: IT Elective 1 | D111: F | E111: 0.33333333 | G111: 0.41666667 | H111: 205 | I111: GAID
C112: IT Elective 1 | D112: F | E112: 0.41666667 | G112: 0.5 | H112: 211 | I112: GAID
B113: COSC1001 | C113: Principles of Communication | D113: TTH | E113: 4:00PM | G113: 5:30PM | H113: 207 | I113: COE FT1
B114: COSC1008 | C114: Platform Technology (Operating Systems) | D114: T | E114: 0.33333333 | G114: 0.41666667 | H114: 203 | I114: LLENO
B115: COSC1008 | C115: Platform Technology (Operating Systems) | D115: T | E115: 0.41666667 | G115: 0.54166667 | H115: 211 | I115: LLENO
A117: SECTION | B117: COURSE CODE | C117: COURSE DESCRIPTION | D117: DAY | E117: TIME | H117: ROOM | I117: INSTRUCTOR
A118: BT303 | B118: COSC1003 | C118: Data Structures and Algorithms | D118: T | E118: 0.41666667 | G118: 0.54166667 | H118: 208 | I118: FELICEN
B119: COSC1003 | C119: Data Structures and Algorithms | D119: T | E119: 0.58333333 | G119: 0.66666667 | H119: 206 | I119: FELICEN
B120: GEDC1006 | C120: Readings in Philippine History | D120: S | E120: 0.58333333 | G120: 0.70833333 | H120: 307 | I120: CONDINO
B121: PHED1007 | C121: P.E./PATHFIT 3: Individual-Dual Sports | D121: TH | E121: 0.29166667 | G121: 0.375 | H121: COURT | I121: SABORIENDO
...

Sheet MONDAY
A2: MONDAY
A3: TIME | B3: SAMPLE | C3: 201 | D3: 202 | E3: 203 | F3: 204 | G3: 205 | H3: 206 | I3: 207 | J3: 212 | K3: 301 | L3: 302 | M3: 303 | N3: 304 | O3: 305 | P3: 306 | Q3: 307 | R3: 308 | S3: 402 | T3: 407 | U3: 410 | V3: 501 | W3: 502 | X3: 503 | Y3: 504 | Z3: 505 | AA3: 506 | AB3: 507 | AC3: 508 | AD3: 509 | AE3: 510 | AF3: 511 | AG3: 512 | AH3: 601 | AI3: 602 | AJ3: 603 | AK3: 604 | AL3: 605 | AM3: 606 | AN3: 607 | AO3: 608 | AS3: <Room> | AT3: <Room> | AU3: M01 | AV3: M02 | AW3: 101 | AX3: 208 | AY3: 209 | AZ3: 210 | BA3: 211 | BB3: 401 | BC3: 408 | BD3: 409 | BE3: KITCHEN 1 | BF3: KITCHEN 2 | BG3: BAR | BH3: SUITE ROOM | BI3: <Lab> | BJ3: <Lab> | BK3: <Lab>
A4: 7:00 - 7:30 AM | B4: <SUBJECT> <SECTION> <INSTRUCTOR> | C4: Euthenics 1 BMA102 MATH FT | D4: VACANT | E4: Human-Computer Interaction LEC BT302 FELICEN | F4: VACANT | G4: Mathematics in the Modern World BH102 JOTOJOT | H4: VACANT | I4: VACANT | J4: VACANT | K4: Rizal's Life & Works BA301 REFUERZO | L4: The Entrepreneurial Mind BAOM302 RM 302 | M4: Science, Technology and Society BSA101 SOC SCI FT1 | N4: The Contemporary World BA101 SOC SCI FT4 | O4: Macro Perspective of Tourism and Hospitality BH104 | P4: National Service Training Program 1 BT102 PALMERO | Q4: Readings in Philippine History BT305 CONDINO | R4: VACANT | S4: VACANT | T4: VACANT | U4: Macro Perspective of Tourism and Hospitality TM101 | V4: 21st Century Lit ABM101 <INSTRUCTOR> | X4: Business Mathematics ABM103 <INSTRUCTOR> | AA4: 2D Concepts DIGI101 <INSTRUCTOR> | AD4: Comp Prog 1 IT101 <INSTRUCTOR> | AH4: General Mathematics STEM101 <INSTRUCTOR> | AI4: 21st Century Lit STEM102 <INSTRUCTOR> | AM4: Oral Communication STEM106 <INSTRUCTOR> | AU4: VACANT | AV4: NO CLASS | AW4: Color Theory LAB BMA302 BMA FT1 | AX4: Embedded Systems LAB COE701 LLENO | AY4: Computer/Web Programming 2 IT102 | AZ4: Computer Programming 1 LAB BT103 IT FT1 | BA4: VACANT | BB4: Disaster Readiness & Risk Redu STEM206 | BC4: National Service Training Program 1 BH103 ROSALES | BD4: Disaster Readiness & Risk Redu STEM207 | BE4: VACANT | BF4: VACANT | BG4: NO CLASS | BH4: Fundamentals in Lodging Operations LEC BH301
A5: 7:30 - 8:00 AM | D5: VACANT | F5: VACANT | H5: VACANT | I5: VACANT | J5: VACANT | R5: VACANT | S5: VACANT | T5: VACANT | AU5: VACANT | BA5: VACANT | BE5: VACANT | BF5: VACANT
A6: 8:00 - 8:30 AM | C6: Computer Programming 1 LEC BT101 RESULLAR | D6: 2D Animation LEC BMA301 MANALO | F6: VACANT | H6: VACANT | I6: VACANT | J6: VACANT | R6: VACANT | S6: VACANT | T6: VACANT | AU6: VACANT | BA6: VACANT | BE6: Philippine Regional Cuisines with Food Styling and Design LEC BH303 | BF6: VACANT
A7: 8:30 - 9:00 AM | B7: <SUBJECT> <SECTION> <INSTRUCTOR> | F7: Readings in Philippine History BH102 CONDINO | G7: Mathematics in the Modern World BH101 JOTOJOT | H7: Personal Development TOP201 | I7: Introduction to Multimedia Arts BMA101 BMA PT2 | J7: Basic Microeconomics BAOM101 RM 212 | K7: Mathematics in the Modern World BMA104 MATH FT | L7: The Contemporary World BT102 SOC SCI FT4 | M7: The Entrepreneurial Mind BAOM301 RM 303 MATEO | N7: Understanding the Self TM101 CAGADO | O7: Mathematics in the Modern World BMA102 BURGOS | P7: Philippine Popular Culture BSA101 SOC SCI FT2 | Q7: Entrepreneurial Management BAOM702 RM 307 MANALANG | R7: Rizal's Life & Works BA302 BAGOL" | S7: Macro Perspective of Tourism and Hospitality TM102 | T7: Understanding the Self BH104 MAGABILIN | U7: The Contemporary World BA102 SOC SCI FT1 | V7: General Mathematics ABM101 <INSTRUCTOR> | W7: 21st Century Lit ABM102 <INSTRUCTOR> | X7: 21st Century Lit ABM103 <INSTRUCTOR> | Y7: Basic Food Production 101 CULART101 <INSTRUCTOR> | Z7: Media and Info Literacy STEM109 <INSTRUCTOR> | AA7: Intro to Philosophy TOP102 <INSTRUCTOR> | AB7: Oral Communication HUMSS101 <INSTRUCTOR> | AC7: Oral Communication HUMSS102 <INSTRUCTOR> | AD7: Computer Animation DIGI201 <INSTRUCTOR> | AE7: Comp Prog 1 IT102 <INSTRUCTOR> | AF7: Intro to Philo IT103 <INSTRUCTOR> | AG7: Basic Drawing DIGI101 <INSTRUCTOR> | AI7: General Mathematics STEM102 <INSTRUCTOR> | AJ7: 21st Century Lit STEM103 <INSTRUCTOR> | AK7: Pre-Calculus STEM104 <INSTRUCTOR> | AL7: Personal Development IT201 <INSTRUCTOR> | AN7: Oral Communication STEM107 <INSTRUCTOR> | AO7: Media and Info Literacy STEM108 <INSTRUCTOR> | AU7: VACANT | AY7: Computer/Web Programming 2 IT101 | BA7: VACANT | BB7: General Biology 1 STEM101 | BC7: Physical Science IT202 | BD7: General Physics 1 STEM207 | BF7: VACANT
A8: 9:00 - 9:30 AM | E8: Euthenics 1 COE101 SOC SCI FT3 | AU8: VACANT | BA8: VACANT | BE8: Philippine Regional Cuisines with Food Styling and Design LAB BH303 | BF8: VACANT | BH8: Fundamentals in Lodging Operations LAB BH301
A9: 9:30 - 10:00 AM | AU9: VACANT | BA9: VACANT | BF9: VACANT
A10: 10:00 - 10:30 AM | B10: <SUBJECT> <SECTION> <INSTRUCTOR> | C10: Computer Programming 1 LEC BT103 IT FT1 | D10: 2D Animation LEC BMA303 | E10: Advanced Database Systems LEC BT502 DOMINGUEZ | F10: Interactive Media Design LEC BMA703 BARRIENTOS | G10: Applied Business Tools and Technologies in Tourism LEC BH502 | H10: Software Engineering 1 BS501 CIFRA | I10: Introduction to Multimedia Arts BMA102 BMA PT2 | J10: Basic Microeconomics BAOM102 RM 212 | K10: Understanding the Self BMA103 MAGABILIN | L10: International Business & Trade BAOM502 RM 302 | M10: Readings in Philippine History TM102 SOC SCI FT3 | N10: Rizal's Life and Works BT305 BAGOL | O10: Understanding the Self BH103 SOC SCI FT2 | P10: Mathematics in the Modern World BMA101 MATH FT | Q10: Great Books BAOM501 RM 307 ENGLISH FT | R10: Macro Perspective of Tourism and Hospitality BH101 | S10: Macro Perspective of Tourism and Hospitality TM103 | T10: Feasibility Study BAOM702 RM 407 ALMAZAR | U10: Pastry Arts and Bakery Management LEC BH501 ALILA | V10: Pagbasa at Pagsusuri ABM201 <INSTRUCTOR> | W10: General Mathematics ABM102 <INSTRUCTOR> | X10: Funda of Accountancy ABM103 <INSTRUCTOR> | Y10: Practical Research 2 CULART201 <INSTRUCTOR> | Z10: Basic Food Production 101 CULART102 <INSTRUCTOR> | AA10: Media and Info Literacy TOP101 <INSTRUCTOR> | AB10: Discipline & Ideas HUMSS101 <INSTRUCTOR> | AE10: Fil sa Piling Larang HUMSS201 <INSTRUCTOR> | AF10: Comp Prog 1 IT103 <INSTRUCTOR> | AH10: Pagbasa at Pagsusuri IT203 <INSTRUCTOR> | AI10: Pagbasa at Pagsusuri STEM201 <INSTRUCTOR> | AJ10: General Mathematics STEM103 <INSTRUCTOR> | AO10: Oral Communication STEM108 <INSTRUCTOR> | AU10: Principles of Communication BT301 COE FT1 | AW10: 2D Animation LAB BMA301 | AX10: Programming Logic and Design LAB RM208 GAID | AY10: Digital Photography DIGI201 | AZ10: Computer Programming 1 LAB BT101 RESULLAR | BA10: Human-Computer Interaction LAB BT302 FELICEN | BB10: Physical Science TOP201 | BC10: Physical Science HUMSS202 | BD10: General Chemistry 1 STEM203 | BF10: VACANT
A11: 10:30 - 11:00 AM | BF11: VACANT
A12: 11:00 - 11:30 AM | BF12: VACANT
A13: 11:30 - 12:00 PM | B13: <SUBJECT> <SECTION> <INSTRUCTOR> | H13: The Contemporary World BT104 SOC SCI FT1 | I13: Artificial Intelligence BS501 CIFRA | J13: National Service Training Program 1 BH104 PALMERO | K13: Readings in Philippine History TM101 CONDINO | L13: National Service Training Program 1 BSA201 PALMERO | M13: Mathematics in the Modern World BA301 JOTOJOT | N13: Understanding the Self BMA102 CAGADO | O13: Macro Perspective of Tourism and Hospitality TM104 | P13: Technopreneurship BS701 RM 306 SAN DIEGO | Q13: Business Research BAOM501 RM 307 SAN DIEGO | R13: Purposive Communication BT102 BONCAN | S13: Rizal's Life and Works BT302 BAGOL | T13: Principles of Communication BS301 COE FT1 | V13: Intro to Philosophy ABM101 <INSTRUCTOR> | W13: Pagbasa at Pagsusuri ABM202 <INSTRUCTOR> | X13: General Mathematics ABM103 <INSTRUCTOR> | Y13: 21st Century Lit CULART101 <INSTRUCTOR> | Z13: Oral Communication STEM109 <INSTRUCTOR> | AA13: Media and Info Literacy TOP102 <INSTRUCTOR> | AB13: Fil sa Piling Larang CULART202 <INSTRUCTOR> | AC13: Intro to World Religion HUMSS102 <INSTRUCTOR> | AD13: Oral Communication IT101 <INSTRUCTOR> | AE13: Media and Info Literacy IT102 <INSTRUCTOR> | AF13: Personal Development HUMSS202 <INSTRUCTOR> | AH13: Intro to Philo STEM101 <INSTRUCTOR> | AI13: Pagbasa at Pagsusuri STEM202 <INSTRUCTOR> | AJ13: Computer Prog 4 IT201 <INSTRUCTOR> | AK13: General Mathematics STEM104 <INSTRUCTOR> | AL13: Pre-Calculus STEM105 <INSTRUCTOR> | AM13: 21st Century Lit STEM106 <INSTRUCTOR> | AN13: 21st Century Lit STEM107 <INSTRUCTOR> | AO13: Fil sa Piling Larang STEM203 <INSTRUCTOR> | AU13: National Service Training Program 1 BMA103 ROSALES | AY13: Computer/Web Programming 4 IT202 | BA13: Human-Computer Interaction LAB RM209 FELICEN | BB13: General Biology 1 STEM102 | BC13: Physical Science IT203 | BD13: Logic Circuits and Design COE501 LLENO | BF13: VACANT
A14: 12:00 - 12:30 PM | C14: VACANT | D14: VACANT | E14: VACANT | F14: VACANT | G14: VACANT | U14: VACANT | BE14: NO CLASS | BF14: VACANT | BH14: VACANT
A15: 12:30 - 1:00 PM | C15: VACANT | D15: VACANT | E15: VACANT | F15: VACANT | G15: VACANT | U15: VACANT | BF15: VACANT | BH15: VACANT
A16: 1:00 - 1:30 PM | B16: VACANT | C16: Fil sa Piling Larang (Akad) STEM206 | D16: VACANT | E16: Personal Development STEM208 | F16: Euthenics 1 BSA101 PALMERO | G16: Understanding the Self TM104 SOC SCI FT2 | H16: Purposive Communication BT104 ENGLISH FT | I16: Introduction to Multimedia Arts BMA103 BAUTISTA | J16: Readings in Philippine History TM103 SOC SCI FT3 | K16: Mathematics in the Modern World COE101 MATH FT | L16: Business Research BAOM502 RM 302 ESPIRITU | M16: Purposive Communication BS101 BONCAN | N16: Rizal's Life and Works BS301 REFUERZO | O16: Rizal's Life and Works BSA301 BUSTALINIO | P16: Art Appreciation BH303 CONDINO | Q16: Risk Management as Applied to Safety, Security, and Sanitation BH101 | R16: Euthenics 2 BA702/BS701 MAGABILIN | S16: Tourism and Hospitality Marketing TM501 | T16: Quality Service Management in Tourism and Hospitality BH302 | U16: Mathematics in the Modern World TM102 JOTOJOT | V16: Personal Development ABM201 <INSTRUCTOR> | W16: Intro to Philosophy ABM102 <INSTRUCTOR> | X16: Pagbasa at Pagsusuri ABM203 <INSTRUCTOR> | Y16: General Mathematics CULART101 <INSTRUCTOR> | Z16: 21st Century Lit CULART102 <INSTRUCTOR> | AA16: Oral Communication TOP101 <INSTRUCTOR> | AB16: Intro to World Religion HUMSS101 <INSTRUCTOR> | AC16: Front Office Services 2 TOP102 <INSTRUCTOR> | AD16: Pagbasa at Pagsusuri CULART201 <INSTRUCTOR> | AE16: Local and Intl Cuisines CULART202 <INSTRUCTOR> | AF16: Media and Info Literacy IT103 <INSTRUCTOR> | AH16: Eng for Acad & Prof DIGI201 <INSTRUCTOR> | AI16: Eng for Acad & Prof HJUMSS201 <INSTRUCTOR> | AJ16: Computer Prog 5 IT201 <INSTRUCTOR> | AL16: General Mathematics STEM105 <INSTRUCTOR> | AO16: Pre-Calculus STEM108 <INSTRUCTOR> | AU16: NO CLASS | AW16: Interactive Media Design LAB BMA703 BARRIENTOS | AX16: Advanced Database Systems LAB BT502 DOMINGUEZ | AY16: Computer/Web Programming 4 IT202 | AZ16: IT Elective 2: Introduction to Computer Animation LAB BT503 IT FT2 | BA16: Information Assurance and Security (Data Privacy) LAB BT702 CIFRA | BB16: General Biology 1 STEM103 | BC16: Disaster Readiness & Risk Redu STEM201 | BD16: General Chemistry 1 STEM204 | BF16: Pastry Arts and Bakery Management LAB BH501 ALILA | BH16: Research in Hospitality LEC TM702
A17: 1:30 - 2:00 PM | D17: VACANT
A18: 2:00 - 2:30 PM | D18: 2D Animation LEC BMA303 MANALO | F18: Human-Computer Interaction LEC BT301 FELICEN | R18: Computer Network and Security LEC COE701 COE FT1
A19: 2:30 - 3:00 PM | B19: <SUBJECT> <SECTION> <INSTRUCTOR> | C19: Operations Management (TQM) BAOM501 RM 201 ALMAZAR | E19: Accommodation Operations and Management TM302 | G19: Platform Technology (Operating Systems) LEC BS701 LLENO | H19: international Business & Trade BAOM501 RM 206 ALMAZAR | I19: Great Books BMA501 ENGLISH FT | J19: Basic Accounting BSA101 RM 212 MATEO | K19: Purposive Communication BT101 BONCAN | L19: Business Ventures in Multimedia BMA503 BARRIENTOS | M19: Business Analytics BSA701 RM 303 ESPIRITU | N19: Discrete Structures 2 BS301 MATH FT | O19: Art Appreciation BH302 SOC SCI FT4 | P19: Data and Digital Communications (Data Communications) COE501 AGUILA | Q19: Understanding the Self BT102 BAGOL | T19: Quality Service Management in Tourism and Hospitality TM301 | U19: Accommodation Operations and Management TM303 | V19: Practical Research 2 ABM201 <INSTRUCTOR> | W19: Personal Development ABM202 <INSTRUCTOR> | X19: Personal Development ABM203 <INSTRUCTOR> | Y19: Personal Development CULART201 <INSTRUCTOR> | AA19: Front Office Services 2 TOP101 <INSTRUCTOR> | AF19: Fil sa Piling Larang HUMSS202 <INSTRUCTOR> | AH19: Eng for Acad & Prof IT203 <INSTRUCTOR> | AI19: Phil Politics and Governance HJUMSS201 <INSTRUCTOR> | AJ19: Eng for Acad & Prof STEM201 <INSTRUCTOR> | AO19: Pagbasa at Pagsusuri STEM203 <INSTRUCTOR> | AY19: Information Assurance & Security (Cybersecurity Fundamentals) LAB BS501 MORAL | BB19: General Chemistry 1 STEM205 | BC19: Disaster Readiness & Risk Redu STEM202 | BD19: National Service Training Program 1 TM103 ROSALES
A20: 3:00 - 3:30 PM | BH20: Research in Hospitality LAB TM702
A21: 3:30 - 4:00 PM
A22: 4:00 - 4:30 PM | B22: NO CLASS | C22: Information Assurance and Security (Data Privacy) LEC BT702 CIFRA | D22: Information Assurance & Security (Cybersecurity Fundamentals) LEC BS501 MORAL | E22: Understanding the Self BT101 MAGABILIN | F22: Euthenics 1 BT102 PALMERO | H22: Network Technology 2 LEC BT701 IT FT3 | J22: Management Science BSA701 RM 212 | K22: Business Ventures in Multimedia BMA503 BARRIENTOS | M22: NO CLASS | N22: NO CLASS | O22: Great Books BH501 BONCAN | P22: NO CLASS | Q22: NO CLASS | R22: NO CLASS | S22: Readings in Philippine History BT304 SOC SCI FT3 | T22: Quality Service Management in Tourism and Hospitality TM303 | U22: Accommodation Operations and Management TM301 | W22: Practical Research 2 ABM202 <INSTRUCTOR> | Y22: Pagbasa at Pagsusuri CULART202 <INSTRUCTOR> | AF22: Eng for Acad & Prof HUMSS202 <INSTRUCTOR> | AI22: Eng for Acad & Prof STEM202 <INSTRUCTOR> | AW22: 2D Animation LAB BMA303 MANALO | AX22: Advanced Database Systems LAB BT501 DOMINGUEZ | AY22: IT Elective 4: Game Development LAB BT703 RESULLAR | AZ22: Advanced Systems Integration and Architecture LAB BT503 FELICEN | BA22: Computer Network and Security LAB COE701 COE FT1 | BB22: NO CLASS | BC22: Disaster Readiness & Risk Redu STEM203 | BD22: NO CLASS | BF22: NO CLASS
A23: 4:30 - 5:00 PM | G23: NO CLASS
A24: 5:00 - 5:30 PM | F24: NO CLASS
A25: 5:30 - 6:00 PM | E25: NO CLASS | I25: NO CLASS | J25: NO CLASS | L25: NO CLASS | O25: NO CLASS | S25: NO CLASS | T25: NO CLASS | U25: NO CLASS | W25: NO CLASS | BC25: NO CLASS
A26: 6:00 - 6:30 PM | C26: NO CLASS | D26: NO CLASS | H26: NO CLASS | BH26: NO CLASS
A27: 6:30 - 7:00 PM
A28: 7:00 - 7:30 PM | K28: NO CLASS | AW28: NO CLASS | AX28: NO CLASS | AY28: NO CLASS | AZ28: NO CLASS | BA28: NO CLASS
A29: 7:30 - 8:00 PM
A30: 8:00 - 8:30 PM
A31: 8:30 - 9:00 PM
A32: Utilization % | B32: =IF(COUNTA(B$4:B$31)=0,"",(COUNTA(TIME)-COUNTIF(B$33:B$60,TRUE))/COUNTA(TIME)) -> 1 | C32: =IF(COUNTA(C$4:C$31)=0,"",(COUNTA(TIME)-COUNTIF(C$33:C$60,TRUE))/COUNTA(TIME)) -> 1 | D32: =IF(COUNTA(D$4:D$31)=0,"",(COUNTA(TIME)-COUNTIF(D$33:D$60,TRUE))/COUNTA(TIME)) -> 1 | E32: =IF(COUNTA(E$4:E$31)=0,"",(COUNTA(TIME)-COUNTIF(E$33:E$60,TRUE))/COUNTA(TIME)) -> 1 | F32: =IF(COUNTA(F$4:F$31)=0,"",(COUNTA(TIME)-COUNTIF(F$33:F$60,TRUE))/COUNTA(TIME)) -> 1 | G32: =IF(COUNTA(G$4:G$31)=0,"",(COUNTA(TIME)-COUNTIF(G$33:G$60,TRUE))/COUNTA(TIME)) -> 1 | H32: =IF(COUNTA(H$4:H$31)=0,"",(COUNTA(TIME)-COUNTIF(H$33:H$60,TRUE))/COUNTA(TIME)) -> 1 | I32: =IF(COUNTA(I$4:I$31)=0,"",(COUNTA(TIME)-COUNTIF(I$33:I$60,TRUE))/COUNTA(TIME)) -> 1 | ... BK32: =IF(COUNTA(BK$4:BK$31)=0,"",(COUNTA(TIME)-COUNTIF(BK$33:BK$60,TRUE))/COUNTA(TIME))
B33: {=Notmerged(B4)} -> #NAME? | C33: {=Notmerged(C4)} -> #NAME? | D33: {=Notmerged(D4)} -> #NAME? | E33: {=Notmerged(E4)} -> #NAME? | F33: {=Notmerged(F4)} -> #NAME? | G33: {=Notmerged(G4)} -> #NAME? | H33: {=Notmerged(H4)} -> #NAME? | I33: {=Notmerged(I4)} -> #NAME? | ... BK33: {=Notmerged(BK4)} -> #NAME?
B34: {=Notmerged(B5)} -> #NAME? | C34: {=Notmerged(C5)} -> #NAME? | D34: {=Notmerged(D5)} -> #NAME? | E34: {=Notmerged(E5)} -> #NAME? | F34: {=Notmerged(F5)} -> #NAME? | G34: {=Notmerged(G5)} -> #NAME? | H34: {=Notmerged(H5)} -> #NAME? | I34: {=Notmerged(I5)} -> #NAME? | ... BK34: {=Notmerged(BK5)} -> #NAME?
B35: {=Notmerged(B6)} -> #NAME? | C35: {=Notmerged(C6)} -> #NAME? | D35: {=Notmerged(D6)} -> #NAME? | E35: {=Notmerged(E6)} -> #NAME? | F35: {=Notmerged(F6)} -> #NAME? | G35: {=Notmerged(G6)} -> #NAME? | H35: {=Notmerged(H6)} -> #NAME? | I35: {=Notmerged(I6)} -> #NAME? | ... BK35: {=Notmerged(BK6)} -> #NAME?
B36: {=Notmerged(B7)} -> #NAME? | C36: {=Notmerged(C7)} -> #NAME? | D36: {=Notmerged(D7)} -> #NAME? | E36: {=Notmerged(E7)} -> #NAME? | F36: {=Notmerged(F7)} -> #NAME? | G36: {=Notmerged(G7)} -> #NAME? | H36: {=Notmerged(H7)} -> #NAME? | I36: {=Notmerged(I7)} -> #NAME? | ... BK36: {=Notmerged(BK7)} -> #NAME?
B37: {=Notmerged(B8)} -> #NAME? | C37: {=Notmerged(C8)} -> #NAME? | D37: {=Notmerged(D8)} -> #NAME? | E37: {=Notmerged(E8)} -> #NAME? | F37: {=Notmerged(F8)} -> #NAME? | G37: {=Notmerged(G8)} -> #NAME? | H37: {=Notmerged(H8)} -> #NAME? | I37: {=Notmerged(I8)} -> #NAME? | ... BK37: {=Notmerged(BK8)} -> #NAME?
B38: {=Notmerged(B9)} -> #NAME? | C38: {=Notmerged(C9)} -> #NAME? | D38: {=Notmerged(D9)} -> #NAME? | E38: {=Notmerged(E9)} -> #NAME? | F38: {=Notmerged(F9)} -> #NAME? | G38: {=Notmerged(G9)} -> #NAME? | H38: {=Notmerged(H9)} -> #NAME? | I38: {=Notmerged(I9)} -> #NAME? | ... BK38: {=Notmerged(BK9)} -> #NAME?
B39: {=Notmerged(B10)} -> #NAME? | C39: {=Notmerged(#REF!)} -> #NAME? | D39: {=Notmerged(D10)} -> #NAME? | E39: {=Notmerged(E10)} -> #NAME? | F39: {=Notmerged(F10)} -> #NAME? | G39: {=Notmerged(G10)} -> #NAME? | H39: {=Notmerged(H10)} -> #NAME? | I39: {=Notmerged(I10)} -> #NAME? | J39: {=Notmerged(J10)} -> #NAME? | K39: {=Notmerged(K10)} -> #NAME? | ... BK39: {=Notmerged(BK10)} -> #NAME?
B40: {=Notmerged(B11)} -> #NAME? | C40: {=Notmerged(C10)} -> #NAME? | D40: {=Notmerged(D11)} -> #NAME? | E40: {=Notmerged(E11)} -> #NAME? | F40: {=Notmerged(F11)} -> #NAME? | G40: {=Notmerged(G11)} -> #NAME? | H40: {=Notmerged(H11)} -> #NAME? | I40: {=Notmerged(I11)} -> #NAME? | J40: {=Notmerged(J11)} -> #NAME? | K40: {=Notmerged(K11)} -> #NAME? | ... BK40: {=Notmerged(BK11)} -> #NAME?
B41: {=Notmerged(B12)} -> #NAME? | C41: {=Notmerged(C12)} -> #NAME? | D41: {=Notmerged(D12)} -> #NAME? | E41: {=Notmerged(E12)} -> #NAME? | F41: {=Notmerged(F12)} -> #NAME? | G41: {=Notmerged(G12)} -> #NAME? | H41: {=Notmerged(H12)} -> #NAME? | I41: {=Notmerged(I12)} -> #NAME? | ... BK41: {=Notmerged(BK12)} -> #NAME?
B42: {=Notmerged(B13)} -> #NAME? | C42: {=Notmerged(C13)} -> #NAME? | D42: {=Notmerged(D13)} -> #NAME? | E42: {=Notmerged(E13)} -> #NAME? | F42: {=Notmerged(F13)} -> #NAME? | G42: {=Notmerged(G13)} -> #NAME? | H42: {=Notmerged(H13)} -> #NAME? | I42: {=Notmerged(I13)} -> #NAME? | ... BK42: {=Notmerged(BK13)} -> #NAME?
B43: {=Notmerged(B14)} -> #NAME? | C43: {=Notmerged(C14)} -> #NAME? | D43: {=Notmerged(D14)} -> #NAME? | E43: {=Notmerged(E14)} -> #NAME? | F43: {=Notmerged(F14)} -> #NAME? | G43: {=Notmerged(G14)} -> #NAME? | H43: {=Notmerged(H14)} -> #NAME? | I43: {=Notmerged(I14)} -> #NAME? | ... BK43: {=Notmerged(BK14)} -> #NAME?
B44: {=Notmerged(B15)} -> #NAME? | C44: {=Notmerged(C15)} -> #NAME? | D44: {=Notmerged(D15)} -> #NAME? | E44: {=Notmerged(E15)} -> #NAME? | F44: {=Notmerged(F15)} -> #NAME? | G44: {=Notmerged(G15)} -> #NAME? | H44: {=Notmerged(H15)} -> #NAME? | I44: {=Notmerged(I15)} -> #NAME? | ... BK44: {=Notmerged(BK15)} -> #NAME?
B45: {=Notmerged(B16)} -> #NAME? | C45: {=Notmerged(C16)} -> #NAME? | D45: {=Notmerged(D16)} -> #NAME? | E45: {=Notmerged(E16)} -> #NAME? | F45: {=Notmerged(F16)} -> #NAME? | G45: {=Notmerged(G16)} -> #NAME? | H45: {=Notmerged(H16)} -> #NAME? | I45: {=Notmerged(I16)} -> #NAME? | ... BK45: {=Notmerged(BK16)} -> #NAME?
B46: {=Notmerged(B17)} -> #NAME? | C46: {=Notmerged(C17)} -> #NAME? | D46: {=Notmerged(D17)} -> #NAME? | E46: {=Notmerged(E17)} -> #NAME? | F46: {=Notmerged(F17)} -> #NAME? | G46: {=Notmerged(G17)} -> #NAME? | H46: {=Notmerged(H17)} -> #NAME? | I46: {=Notmerged(I17)} -> #NAME? | ... BK46: {=Notmerged(BK17)} -> #NAME?
B47: {=Notmerged(B18)} -> #NAME? | C47: {=Notmerged(C18)} -> #NAME? | D47: {=Notmerged(D18)} -> #NAME? | E47: {=Notmerged(E18)} -> #NAME? | F47: {=Notmerged(F18)} -> #NAME? | G47: {=Notmerged(G18)} -> #NAME? | H47: {=Notmerged(H18)} -> #NAME? | I47: {=Notmerged(I18)} -> #NAME? | ... BK47: {=Notmerged(BK18)} -> #NAME?
B48: {=Notmerged(B19)} -> #NAME? | C48: {=Notmerged(#REF!)} -> #NAME? | D48: {=Notmerged(D19)} -> #NAME? | E48: {=Notmerged(E19)} -> #NAME? | F48: {=Notmerged(F19)} -> #NAME? | G48: {=Notmerged(G19)} -> #NAME? | H48: {=Notmerged(H19)} -> #NAME? | I48: {=Notmerged(I19)} -> #NAME? | J48: {=Notmerged(J19)} -> #NAME? | K48: {=Notmerged(K19)} -> #NAME? | ... BK48: {=Notmerged(BK19)} -> #NAME?
B49: {=Notmerged(B20)} -> #NAME? | C49: {=Notmerged(#REF!)} -> #NAME? | D49: {=Notmerged(D20)} -> #NAME? | E49: {=Notmerged(E20)} -> #NAME? | F49: {=Notmerged(F20)} -> #NAME? | G49: {=Notmerged(G20)} -> #NAME? | H49: {=Notmerged(H20)} -> #NAME? | I49: {=Notmerged(I20)} -> #NAME? | J49: {=Notmerged(J20)} -> #NAME? | K49: {=Notmerged(K20)} -> #NAME? | ... BK49: {=Notmerged(BK20)} -> #NAME?
B50: {=Notmerged(B21)} -> #NAME? | C50: {=Notmerged(C21)} -> #NAME? | D50: {=Notmerged(D21)} -> #NAME? | E50: {=Notmerged(E21)} -> #NAME? | F50: {=Notmerged(F21)} -> #NAME? | G50: {=Notmerged(G21)} -> #NAME? | H50: {=Notmerged(H21)} -> #NAME? | I50: {=Notmerged(I21)} -> #NAME? | ... BK50: {=Notmerged(BK21)} -> #NAME?
B51: {=Notmerged(#REF!)} -> #NAME? | C51: {=Notmerged(C22)} -> #NAME? | D51: {=Notmerged(D22)} -> #NAME? | E51: {=Notmerged(E22)} -> #NAME? | F51: {=Notmerged(F22)} -> #NAME? | G51: {=Notmerged(G22)} -> #NAME? | H51: {=Notmerged(H22)} -> #NAME? | I51: {=Notmerged(I22)} -> #NAME? | J51: {=Notmerged(J22)} -> #NAME? | ... BK51: {=Notmerged(BK22)} -> #NAME?
B52: {=Notmerged(B23)} -> #NAME? | C52: {=Notmerged(#REF!)} -> #NAME? | D52: {=Notmerged(D23)} -> #NAME? | E52: {=Notmerged(E23)} -> #NAME? | F52: {=Notmerged(F23)} -> #NAME? | G52: {=Notmerged(G23)} -> #NAME? | H52: {=Notmerged(H23)} -> #NAME? | I52: {=Notmerged(I23)} -> #NAME? | J52: {=Notmerged(J23)} -> #NAME? | K52: {=Notmerged(K23)} -> #NAME? | ... BK52: {=Notmerged(BK23)} -> #NAME?
B53: {=Notmerged(B22)} -> #NAME? | C53: {=Notmerged(C23)} -> #NAME? | D53: {=Notmerged(D24)} -> #NAME? | E53: {=Notmerged(E24)} -> #NAME? | F53: {=Notmerged(F24)} -> #NAME? | G53: {=Notmerged(G24)} -> #NAME? | H53: {=Notmerged(H24)} -> #NAME? | I53: {=Notmerged(I24)} -> #NAME? | J53: {=Notmerged(J24)} -> #NAME? | K53: {=Notmerged(K24)} -> #NAME? | ... BK53: {=Notmerged(BK24)} -> #NAME?
B54: {=Notmerged(#REF!)} -> #NAME? | C54: {=Notmerged(C25)} -> #NAME? | D54: {=Notmerged(D25)} -> #NAME? | E54: {=Notmerged(E25)} -> #NAME? | F54: {=Notmerged(F25)} -> #NAME? | G54: {=Notmerged(G25)} -> #NAME? | H54: {=Notmerged(H25)} -> #NAME? | I54: {=Notmerged(I25)} -> #NAME? | J54: {=Notmerged(J25)} -> #NAME? | ... BK54: {=Notmerged(BK25)} -> #NAME?
B55: {=Notmerged(B26)} -> #NAME? | C55: {=Notmerged(C26)} -> #NAME? | D55: {=Notmerged(D26)} -> #NAME? | E55: {=Notmerged(E26)} -> #NAME? | F55: {=Notmerged(F26)} -> #NAME? | G55: {=Notmerged(G26)} -> #NAME? | H55: {=Notmerged(H26)} -> #NAME? | I55: {=Notmerged(I26)} -> #NAME? | ... BK55: {=Notmerged(BK26)} -> #NAME?
B56: {=Notmerged(B25)} -> #NAME? | C56: {=Notmerged(C27)} -> #NAME? | D56: {=Notmerged(D27)} -> #NAME? | E56: {=Notmerged(E27)} -> #NAME? | F56: {=Notmerged(F27)} -> #NAME? | G56: {=Notmerged(G27)} -> #NAME? | H56: {=Notmerged(H27)} -> #NAME? | I56: {=Notmerged(I27)} -> #NAME? | J56: {=Notmerged(J27)} -> #NAME? | ... BK56: {=Notmerged(BK27)} -> #NAME?
B57: {=Notmerged(B28)} -> #NAME? | C57: {=Notmerged(C19)} -> #NAME? | D57: {=Notmerged(D28)} -> #NAME? | E57: {=Notmerged(E28)} -> #NAME? | F57: {=Notmerged(F28)} -> #NAME? | G57: {=Notmerged(G28)} -> #NAME? | H57: {=Notmerged(H28)} -> #NAME? | I57: {=Notmerged(I28)} -> #NAME? | J57: {=Notmerged(J28)} -> #NAME? | K57: {=Notmerged(K28)} -> #NAME? | ... BK57: {=Notmerged(BK28)} -> #NAME?
B58: {=Notmerged(B29)} -> #NAME? | C58: {=Notmerged(C29)} -> #NAME? | D58: {=Notmerged(D29)} -> #NAME? | E58: {=Notmerged(E29)} -> #NAME? | F58: {=Notmerged(F29)} -> #NAME? | G58: {=Notmerged(G29)} -> #NAME? | H58: {=Notmerged(H29)} -> #NAME? | I58: {=Notmerged(I29)} -> #NAME? | ... BK58: {=Notmerged(BK29)} -> #NAME?
B59: {=Notmerged(B30)} -> #NAME? | C59: {=Notmerged(C30)} -> #NAME? | D59: {=Notmerged(D30)} -> #NAME? | E59: {=Notmerged(E30)} -> #NAME? | F59: {=Notmerged(F30)} -> #NAME? | G59: {=Notmerged(G30)} -> #NAME? | H59: {=Notmerged(H30)} -> #NAME? | I59: {=Notmerged(I30)} -> #NAME? | ... BK59: {=Notmerged(BK30)} -> #NAME?
B60: {=Notmerged(B31)} -> #NAME? | C60: {=Notmerged(C31)} -> #NAME? | D60: {=Notmerged(D31)} -> #NAME? | E60: {=Notmerged(E31)} -> #NAME? | F60: {=Notmerged(F31)} -> #NAME? | G60: {=Notmerged(G31)} -> #NAME? | H60: {=Notmerged(H31)} -> #NAME? | I60: {=Notmerged(I31)} -> #NAME? | ... BK60: {=Notmerged(BK31)} -> #NAME?

Sheet TUESDAY
A2: TUESDAY
A3: TIME | B3: SAMPLE | C3: =MONDAY!C3 -> 201 | D3: =MONDAY!D3 -> 202 | E3: =MONDAY!E3 -> 203 | F3: =MONDAY!F3 -> 204 | G3: =MONDAY!G3 -> 205 | H3: =MONDAY!H3 -> 206 | I3: =MONDAY!I3 -> 207 | J3: =MONDAY!J3 -> 212 | ... BK3: =MONDAY!BK3 -> <Lab>
A4: 7:00 - 7:30 AM | B4: <SUBJECT> <SECTION> <INSTRUCTOR> | C4: Euthenics 1 BMA103 MATH FT | D4: VACANT | E4: VACANT | F4: VACANT | G4: VACANT | H4: VACANT | I4: Human Resource Management BSA701 RM 207 PASION | J4: VACANT | K4: VACANT | L4: VACANT | M4: Digital Sound Production LEC RM303 ARGUELLES | N4: VACANT | O4: Readings in Philippine History BA201 REFUERZO | P4: Understanding the Self BH101 MAGABILIN | Q4: Rizal's Life and Works BMA303 SOC SCI FT3 | R4: Mathematics in the Modern World BA302 JOTOJOT | S4: Risk Management as Applied to Safety, Security, and Sanitation TM101 | T4: Understanding the Self BT103 BAGOL | U4: Understanding the Self BT103 BAGOL | V4: Oral Communication ABM101 <INSTRUCTOR> | X4: Intro to Philosophy ABM103 <INSTRUCTOR> | Z4: General Mathematics CULART102 <INSTRUCTOR> | AA4: 21st Century Lit DIGI101 <INSTRUCTOR> | AD4: Media and Info Literacy IT101 <INSTRUCTOR> | AE4: Oral Communication IT102 <INSTRUCTOR> | AF4: Computer Programming 2 IT103 <INSTRUCTOR> | AG4: Drawing 1 LAB BMA101 BARRIENTOS | AH4: Media and Info Literacy STEM101 <INSTRUCTOR> | AK4: Intro to Philosophy STEM104 <INSTRUCTOR> | AM4: 21st Century Lit STEM106 <INSTRUCTOR> | AU4: VACANT | AV4: NO CLASS | AW4: Digital Photography LAB BMA501 BMA FT1 | AX4: Advanced Systems Integration and Architecture LAB BT504 FELICEN | AY4: Advanced Systems Integration and Architecture LAB BT504 FELICEN | AZ4: IT Elective 1: Object-Oriented Programming LAB BT305 GAID" | BA4: Managerial Accounting LAB BAOM502 RM 208 CANGAO | BB4: Disaster Readiness & Risk Redu STEM206 | BC4: National Service Training Program 1 BH102 PALMERO | BD4: General Physics 1 STEM208 | BE4: NO CLASS | BF4: NO CLASS | BG4: NO CLASS | BH4: Fundamentals in Lodging Operations LEC BH302 BARRIENTOS
A5: 7:30 - 8:00 AM | D5: VACANT | E5: VACANT | F5: VACANT | G5: VACANT | H5: VACANT | J5: VACANT | K5: VACANT | L5: VACANT | N5: VACANT | AU5: VACANT
A6: 8:00 - 8:30 AM | C6: Computer Programming 1 LEC BT102 RESULLAR | D6: Data Structures and Algorithms LEC BS301 DOMINGUEZ | E6: Platform Technology (Operating Systems) LEC BT302 LLENO | F6: VACANT | G6: VACANT | H6: VACANT | J6: VACANT | K6: Costing & Pricing LECTURE BAOM301 RM 301 | L6: Readings in Philippine History BA102 BAGOL | N6: VACANT | AU6: Introduction to Computing LEC BT104 RM MO1
A7: 8:30 - 9:00 AM | B7: <SUBJECT> <SECTION> <INSTRUCTOR> | F7: Understanding the Self BH102 SOC SCI FT2 | G7: The Contemporary World COE101 MAGABILIN | H7: Readings in Philippine History BH101 CONDINO | J7: The Contemporary World BSA101 SOC SCI FT1 | N7: Understanding the Self BA101 BADENAS | O7: Managerial Economics BSA301 RM 305 LAZARIN | P7: Risk Management as Applied to Safety, Security, and Sanitation BH104 | Q7: The Entrepreneurial Mind BMA303 UCLUSIN | R7: Risk Management as Applied to Safety, Security, and Sanitation TM102 | S7: Readings in Philippine History BH103 REFUERZO | T7: Disaster Readiness & Risk Redu STEM208 | U7: Rizal's Life and Works BT303 SOC SCI FT3 | V7: Business Mathematics ABM101 <INSTRUCTOR> | W7: Oral Communication ABM102 <INSTRUCTOR> | X7: Media and Info Literacy ABM103 <INSTRUCTOR> | Y7: Intro to Philosophy CULART101 <INSTRUCTOR> | Z7: Intro to Philosophy CULART102 <INSTRUCTOR> | AA7: General Mathematics DIGI101 <INSTRUCTOR> | AB7: 21st Century Lit HUMSS101 <INSTRUCTOR> | AC7: 21st Century Lit HUMSS102 <INSTRUCTOR> | AD7: Pre-Calculus STEM109 <INSTRUCTOR> | AE7: Computer Programming 3 IT202 <INSTRUCTOR> | AF7: Oral Communication IT103 <INSTRUCTOR> | AH7: Oral Communication STEM101 <INSTRUCTOR> | AI7: Media and Info Literacy STEM102 <INSTRUCTOR> | AJ7: Media and Info Literacy STEM103 <INSTRUCTOR> | AK7: General Mathematics IT101 <INSTRUCTOR> | AL7: Intro to Philosophy STEM105 <INSTRUCTOR> | AM7: Eng for Acad & Prof IT202 <INSTRUCTOR> | AN7: General Mathematics STEM107 <INSTRUCTOR> | AO7: Pagbasa at Pagsusuri IT201 <INSTRUCTOR> | BB7: General Biology 1 STEM101 | BC7: Physical Science HUMSS201 | BD7: National Service Training Program 1 TM101 CASTILLO
A8: 9:00 - 9:30 AM | M8: Drawing 1 LEC BMA105 MANALO | BH8: Fundamentals in Lodging Operations LAB BH302 BARRIENTOS
A9: 9:30 - 10:00 AM | L9: Facilities Management BAOM302 RM 302
A10: 10:00 - 10:30 AM | B10: <SUBJECT> <SECTION> <INSTRUCTOR> | C10: Computer Programming 1 LEC BS101 IT FT1 | D10: Interactive Media Design LEC BMA701 BARRIENTOS | E10: Event-Driven Programming LEC BT501 DOMONDON | F10: IT Elective 1: Object-Oriented Programming LEC BT301 GAID | G10: Readings in Philippine History COE301 | H10: Art Appreciation TM303 BUSTALINIO | I10: Digital Photography LEC BMA501 BMA FT1 | J10: Readings in the Philippine History BSA101 BADENAS | K10: Managerial Economics BSA301 RM 301 | M10: Managerial Accounting LECTURE BAOM502 RM 303 | N10: The Contemporary World BMA104 SOC SCI FT4 | O10: Mathematics in the Modern World BH103 JOTOJOT | P10: Special Topics in Operations Management BAOM701 RM 306 SAN DIEGO | Q10: Understanding the Self BMA101 CAGADO | R10: National Service Training Program 1 BMA102 PALMERO | S10: Strategic Management BSA301 RM 402 MANALANG | T10: National Service Training Program 1 BT103 ROSALES | U10: Euthenics 1 BH104 MATH FT | V10: Eng for Acad & Prof ABM201 <INSTRUCTOR> | W10: Org and Management ABM102 <INSTRUCTOR> | X10: Intro to Philosophy IT102 <INSTRUCTOR> | Y10: Media and Info Literacy CULART101 <INSTRUCTOR> | Z10: 21st Century Lit STEM109 <INSTRUCTOR> | AA10: Oral Communication TOP102 <INSTRUCTOR> | AB10: General Mathematics HUMSS101 <INSTRUCTOR> | AD10: Pagbasa at Pagsusuri DIGI201 <INSTRUCTOR> | AE10: Practical Research 2 HUMSS201 <INSTRUCTOR> | AF10: Computer Programming 4 IT202 <INSTRUCTOR> | AG10: Drawing 1 LAB BMA105 MANALO | AH10: Personal Development STEM202 <INSTRUCTOR> | AI10: Oral Communication STEM102 <INSTRUCTOR> | AJ10: Fil sa Piling Larang STEM201 <INSTRUCTOR> | AK10: Fil sa Piling Larang IT202 <INSTRUCTOR> | AM10: Pre-Calculus STEM106 <INSTRUCTOR> | AO10: General Mathematics STEM108 <INSTRUCTOR> | AU10: VACANT | AW10: 2D Animation LAB BMA302 | AX10: Data Structures and Algorithms LAB BT303 FELICEN | AY10: Data Structures and Algorithms LAB BT303 FELICEN | AZ10: Computer Programming 1 LAB BT102 RESULLAR | BA10: Platform Technology (Operating Systems) LAB BT302 LLENO | BB10: Physical Science TOP201 | BC10: Physical Science IT201 | BD10: Physical Science CULART201
A11: 10:30 - 11:00 AM | AU11: VACANT
A12: 11:00 - 11:30 AM | L12: Mathematics in the Modern World BMA103 MATH FT | U12: CpE Elective 1: Computer Systems Architecture LAB COE501 COE FT1 | AU12: Introduction to Computing LEC BT105 IT FT2
A13: 11:30 - 12:00 PM | B13: <SUBJECT> <SECTION> <INSTRUCTOR> | G13: Understanding the Self TM103 MAGABILIN | H13: Readings in Philippine History BMA102 SOC SCI FT3 | J13: Pagbasa at Pagsusuri TOP202 | K13: Facilities Management BAOM301 RM 301 | N13: Operations Management (TQM) BH502 ESPIRITU | O13: Pagbasa at Pagsusuri STEM207 | P13: Purposive Communication BT103 SINDICO | Q13: Personal Development STEM206 | R13: Great Books BMA502 ENGLISH FT | S13: Tour and Travel Management TM301 | T13: Introduction to Multimedia Arts BMA104 BAUTISTA | V13: Fil sa Piling Larang ABM201 <INSTRUCTOR> | W13: Eng for Acad & Prof ABM202 <INSTRUCTOR> | X13: Oral Communication ABM103 <INSTRUCTOR> | Y13: Practical Research 2 ABM203 <INSTRUCTOR> | Z13: Media and Info Literacy CULART102 <INSTRUCTOR> | AA13: Intro to Philosophy DIGI101 <INSTRUCTOR> | AB13: 21st Century Lit TOP101 <INSTRUCTOR> | AC13: General Mathematics HUMSS102 <INSTRUCTOR> | AD13: 21st Century Lit IT101 <INSTRUCTOR> | AE13: 21st Century Lit IT102 <INSTRUCTOR> | AF13: Eng for Acad & Prof CULART201 <INSTRUCTOR> | AH13: Personal Development CULART202 <INSTRUCTOR> | AI13: Phil Politics and Governance HUMSS202 <INSTRUCTOR> | AJ13: Pre-Calculus STEM103 <INSTRUCTOR> | AK13: Media and Info Literacy STEM104 <INSTRUCTOR> | AM13: Fil sa Piling Larang STEM202 <INSTRUCTOR> | BA13: Introduction to Computing LAB BT104 AGUILA | BB13: General Biology 1 STEM102 | BC13: Pagbasa at Pagsusuri STEM201 | BD13: General Physics 1 STEM203
A14: 12:00 - 12:30 PM | C14: Differential Equations COE301 JOTOJOT | D14: VACANT | E14: VACANT | F14: Costing & Pricing LECTURE BAOM302 RM204 MATEO | I14: VACANT | M14: VACANT | BH14: VACANT
A15: 12:30 - 1:00 PM | D15: Philippine Popular Culture BT104 SOC SCI FT2 | E15: VACANT | I15: VACANT | L15: National Service Training Program 1 BT101 PALMERO | M15: VACANT | BH15: VACANT
A16: 1:00 - 1:30 PM | B16: VACANT | E16: Fil sa Piling Larang (Akad) STEM207 | G16: VACANT | H16: The Contemporary World BMA103 SOC SCI FT1 | I16: VACANT | J16: The Contemporary World BS101 SOC SCI FT4 | K16: NO CLASS | M16: Multicultural Diversity in Workplace for the Tourism Professional TM501 | N16: Understanding the Self BSA101 MAGABILIN | O16: English for Academic &Prof STEM206 | P16: Readings in Philippine History BT302 CONDINO | Q16: Readings in Philippine History TM104 BADENAS | R16: Rizal's Life and Works BMA301 REFUERZO | S16: Marketing Management BAOM702 RM 402 ALMAZAR | T16: Understanding the Self COE101 CAGADO | U16: Business Finance GAS201 | V16: Practical Research 2 CULART202 <INSTRUCTOR> | W16: Media and Info Literacy ABM102 <INSTRUCTOR> | X16: 21st Century Lit TOP102 <INSTRUCTOR> | Y16: Oral Communication CULART101 <INSTRUCTOR> | Z16: General Mathematics STEM109 <INSTRUCTOR> | AA16: Media and Info Literacy DIGI101 <INSTRUCTOR> | AB16: Intro to Philosophy HUMSS101 <INSTRUCTOR> | AC16: Discipline & Ideas HUMSS102 <INSTRUCTOR> | AD16: Personal Development DIGI201 <INSTRUCTOR> | AE16: Personal Development IT203 <INSTRUCTOR> | AF16: General Mathematics TOP101 <INSTRUCTOR> | AG16: National Service Training Program 1 BMA101 ROSALES | AH16: Pagbasa at Pagsusuri HUMSS201 <INSTRUCTOR> | AI16: Intro to Philosophy STEM102 <INSTRUCTOR> | AJ16: Eng for Acad & Prof IT201 <INSTRUCTOR> | AK16: Personal Development IT202 <INSTRUCTOR> | AL16: Media and Info Literacy STEM105 <INSTRUCTOR> | AN16: Pre-Calculus STEM107 <INSTRUCTOR> | AU16: Philippine Popular Culture BT104 SOC SCI FT2 | AW16: Interactive Media Design LAB BMA701 BARRIENTOS | AX16: Event-Driven Programming LAB BT501 DOMONDON | AY16: Event-Driven Programming LAB BT501 DOMONDON | AZ16: IT Application Tools in Business LAB BSA301 RM 210 | BA16: CpE Elective 1: Computer Systems Architecture LAB COE501 COE FT1 | BB16: General Biology 1 STEM103 | BC16: General Physics 1 STEM203 | BD16: Disaster Readiness & Risk Redu GAS201 | BH16: Research in Hospitality LEC BH702
A17: 1:30 - 2:00 PM | C17: VACANT | G17: VACANT | I17: VACANT
A18: 2:00 - 2:30 PM | C18: Typography and Layout LEC BMA503 BAUTISTA | D18: 2D Animation LEC BMA304 MANALO | F18: Network Technology 1 LEC BS701 IT FT3 | G18: MMA Free Elective 1: Web Programming BMA502 DOMINGUEZ | I18: VACANT | L18: VACANT
A19: 2:30 - 3:00 PM | B19: <SUBJECT> <SECTION> <INSTRUCTOR> | E19: Sustainable Tourism TM302 | H19: Purposive Communication BT105 ENGLISH FT | I19: Operating Systems COE301 LLENO | J19: Mathematics in the Modern World TM103 JOTOJOT | L19: VACANT | M19: National Service Training Program 1 BT104 PALMERO | N19: Rizal's Life and Works BMA302 BAGOL | O19: The Entrepreneurial Mind BMA301 MANALANG | P19: Rizal's Life and Works TM702 REFUERZO | Q19: Special Topics in Operations Management BAOM701 RM 307 | R19: Art Appreciation TM301 BUSTALINIO | S19: Multicultural Diversity in Workplace for the Tourism Professional TM502 | T19: Philippine Popular Culture BT101 SOC SCI FT2 | U19: Professional Development and Applied Ethics BH502 | V19: Fund of Accountancy ABM201 <INSTRUCTOR> | W19: Fil sa Piling Larang ABM202 <INSTRUCTOR> | X19: Eng for Acad & Prof ABM203 <INSTRUCTOR> | Y19: Fil sa Piling Larang CULART201 <INSTRUCTOR> | Z19: Practical Research 2 DIGI201 <INSTRUCTOR> | AB19: Media and Info Literacy HUMSS101 <INSTRUCTOR> | AE19: Fil sa Piling Larang IT203 <INSTRUCTOR> | AF19: Pagbasa at Pagsusuri HUMSS202 <INSTRUCTOR> | AG19: International Business and Trade BSA501 RM 512 ESPIRITU | AI19: Personal Development HUMSS201 <INSTRUCTOR> | AJ19: Fil sa Piling Larang IT201 <INSTRUCTOR> | AK19: Practical Research 2 IT202 <INSTRUCTOR> | AU19: NO CLASS | BB19: General Chemistry 1 STEM205 | BC19: General Chemistry 1 STEM201 | BD19: General Physics 1 STEM202
A20: 3:00 - 3:30 PM | L20: Foreign Language 1 TM303 RM302 | BH20: Research in Hospitality LAB BH702
A21: 3:30 - 4:00 PM
A22: 4:00 - 4:30 PM | B22: NO CLASS | C22: IT Application Tools in Business BSA301 LEC RM 201 | D22: Advanced Systems Integration and Architecture LEC BT503 FELICEN | E22: NO CLASS | F22: NO CLASS | G22: NO CLASS | H22: The Contemporary World BT105 SOC SCI FT4 | I22: NO CLASS | J22: Tourism and Hospitality Marketing BH501 | M22: IT Elective 4: Game Development LEC BT702 RESULLAR | N22: Professional Development and Applied Ethics TM502 | O22: The Contemporary World TM702 SOC SCI FT | P22: Art Appreciation TM302 CONDINO | Q22: Marketing Management BAOM701 RM 307 ALMAZAR | R22: The Entrepreneurial Mind BH502 UCLUSIN | S22: Professional Development and Applied Ethics TM501 | T22: Sustainable Tourism TM301 | U22: Risk Management as Applied to Safety, Security, and Sanitation TM103 | V22: Business Finance ABM201 <INSTRUCTOR> | W22: Fund of Accountancy ABM202 <INSTRUCTOR> | X22: Fil sa Piling Larang ABM203 <INSTRUCTOR> | Y22: Local and Int'l Cuisine CULART201 <INSTRUCTOR> | Z22: Eng for Acad & Prof CULART202 <INSTRUCTOR> | AF22: Personal Development HUMSS202 <INSTRUCTOR> | AJ22: Personal Development STEM201 <INSTRUCTOR> | AW22: 2D Animation LAB BMA304 MANALO | AX22: MMA Free Elective 1: Web Programming LAB BMA502 DOMINGUEZ | AY22: MMA Free Elective 1: Web Programming LAB BMA502 DOMINGUEZ | AZ22: Network Technology 1 LAB BS401 IT FT3 | BA22: IT Elective 2: Introduction to Computer Animation LAB BT501 IT FT3 | BB22: NO CLASS | BC22: General Chemistry 1 STEM202 | BD22: General Chemistry 1 STEM206
A23: 4:30 - 5:00 PM
A24: 5:00 - 5:30 PM
A25: 5:30 - 6:00 PM | H25: NO CLASS | J25: NO CLASS | N25: NO CLASS | O25: Euthenics 2 TM702 SOC SCI FT1 | P25: NO CLASS | Q25: NO CLASS | R25: NO CLASS | S25: NO CLASS | T25: NO CLASS | U25: NO CLASS | AG25: NO CLASS | BC25: NO CLASS | BD25: NO CLASS
A26: 6:00 - 6:30 PM | C26: NO CLASS | D26: NO CLASS | L26: NO CLASS | M26: NO CLASS | BH26: NO CLASS
A27: 6:30 - 7:00 PM | O27: NO CLASS
A28: 7:00 - 7:30 PM | AW28: NO CLASS | AX28: NO CLASS | AY28: NO CLASS | AZ28: NO CLASS | BA28: NO CLASS
A29: 7:30 - 8:00 PM
A30: 8:00 - 8:30 PM
A31: 8:30 - 9:00 PM
A32: Utilization % | B32: =IF(COUNTA(B$4:B$31)=0,"",(COUNTA(TIME)-COUNTIF(B$33:B$60,TRUE))/COUNTA(TIME)) -> 1 | C32: =IF(COUNTA(C$4:C$31)=0,"",(COUNTA(TIME)-COUNTIF(C$33:C$60,TRUE))/COUNTA(TIME)) -> 1 | D32: =IF(COUNTA(D$4:D$31)=0,"",(COUNTA(TIME)-COUNTIF(D$33:D$60,TRUE))/COUNTA(TIME)) -> 1 | E32: =IF(COUNTA(E$4:E$31)=0,"",(COUNTA(TIME)-COUNTIF(E$33:E$60,TRUE))/COUNTA(TIME)) -> 1 | F32: =IF(COUNTA(F$4:F$31)=0,"",(COUNTA(TIME)-COUNTIF(F$33:F$60,TRUE))/COUNTA(TIME)) -> 1 | G32: =IF(COUNTA(G$4:G$31)=0,"",(COUNTA(TIME)-COUNTIF(G$33:G$60,TRUE))/COUNTA(TIME)) -> 1 | H32: =IF(COUNTA(H$4:H$31)=0,"",(COUNTA(TIME)-COUNTIF(H$33:H$60,TRUE))/COUNTA(TIME)) -> 1 | I32: =IF(COUNTA(I$4:I$31)=0,"",(COUNTA(TIME)-COUNTIF(I$33:I$60,TRUE))/COUNTA(TIME)) -> 1 | ... BK32: =IF(COUNTA(BK$4:BK$31)=0,"",(COUNTA(TIME)-COUNTIF(BK$33:BK$60,TRUE))/COUNTA(TIME))
B33: {=Notmerged(B4)} -> #NAME? | C33: {=Notmerged(C4)} -> #NAME? | D33: {=Notmerged(D4)} -> #NAME? | E33: {=Notmerged(E4)} -> #NAME? | F33: {=Notmerged(F4)} -> #NAME? | G33: {=Notmerged(G4)} -> #NAME? | H33: {=Notmerged(H4)} -> #NAME? | I33: {=Notmerged(I4)} -> #NAME? | ... BK33: {=Notmerged(BK4)} -> #NAME?
B34: {=Notmerged(B5)} -> #NAME? | C34: {=Notmerged(C5)} -> #NAME? | D34: {=Notmerged(D5)} -> #NAME? | E34: {=Notmerged(E5)} -> #NAME? | F34: {=Notmerged(F5)} -> #NAME? | G34: {=Notmerged(G5)} -> #NAME? | H34: {=Notmerged(H5)} -> #NAME? | I34: {=Notmerged(I5)} -> #NAME? | ... BK34: {=Notmerged(BK5)} -> #NAME?
B35: {=Notmerged(B6)} -> #NAME? | C35: {=Notmerged(C6)} -> #NAME? | D35: {=Notmerged(D6)} -> #NAME? | E35: {=Notmerged(E6)} -> #NAME? | F35: {=Notmerged(F6)} -> #NAME? | G35: {=Notmerged(G6)} -> #NAME? | H35: {=Notmerged(H6)} -> #NAME? | I35: {=Notmerged(I6)} -> #NAME? | ... BK35: {=Notmerged(BK6)} -> #NAME?
B36: {=Notmerged(B7)} -> #NAME? | C36: {=Notmerged(C7)} -> #NAME? | D36: {=Notmerged(D7)} -> #NAME? | E36: {=Notmerged(E7)} -> #NAME? | F36: {=Notmerged(F7)} -> #NAME? | G36: {=Notmerged(G7)} -> #NAME? | H36: {=Notmerged(H7)} -> #NAME? | I36: {=Notmerged(I7)} -> #NAME? | ... BK36: {=Notmerged(BK7)} -> #NAME?
B37: {=Notmerged(B8)} -> #NAME? | C37: {=Notmerged(C8)} -> #NAME? | D37: {=Notmerged(D8)} -> #NAME? | E37: {=Notmerged(E8)} -> #NAME? | F37: {=Notmerged(F8)} -> #NAME? | G37: {=Notmerged(G8)} -> #NAME? | H37: {=Notmerged(H8)} -> #NAME? | I37: {=Notmerged(I8)} -> #NAME? | ... BK37: {=Notmerged(BK8)} -> #NAME?
B38: {=Notmerged(B9)} -> #NAME? | C38: {=Notmerged(C9)} -> #NAME? | D38: {=Notmerged(D9)} -> #NAME? | E38: {=Notmerged(E9)} -> #NAME? | F38: {=Notmerged(F9)} -> #NAME? | G38: {=Notmerged(G9)} -> #NAME? | H38: {=Notmerged(H9)} -> #NAME? | I38: {=Notmerged(I9)} -> #NAME? | ... BK38: {=Notmerged(BK9)} -> #NAME?
B39: {=Notmerged(B10)} -> #NAME? | C39: {=Notmerged(C10)} -> #NAME? | D39: {=Notmerged(#REF!)} -> #NAME? | E39: {=Notmerged(E10)} -> #NAME? | F39: {=Notmerged(F10)} -> #NAME? | G39: {=Notmerged(G10)} -> #NAME? | H39: {=Notmerged(H10)} -> #NAME? | I39: {=Notmerged(I10)} -> #NAME? | J39: {=Notmerged(J10)} -> #NAME? | K39: {=Notmerged(K10)} -> #NAME? | L39: {=Notmerged(L10)} -> #NAME? | ... BK39: {=Notmerged(BK10)} -> #NAME?
B40: {=Notmerged(B11)} -> #NAME? | C40: {=Notmerged(C11)} -> #NAME? | D40: {=Notmerged(D10)} -> #NAME? | E40: {=Notmerged(E11)} -> #NAME? | F40: {=Notmerged(F11)} -> #NAME? | G40: {=Notmerged(G11)} -> #NAME? | H40: {=Notmerged(H11)} -> #NAME? | I40: {=Notmerged(I11)} -> #NAME? | J40: {=Notmerged(J11)} -> #NAME? | K40: {=Notmerged(K11)} -> #NAME? | L40: {=Notmerged(L11)} -> #NAME? | ... BK40: {=Notmerged(BK11)} -> #NAME?
B41: {=Notmerged(B12)} -> #NAME? | C41: {=Notmerged(C12)} -> #NAME? | D41: {=Notmerged(D12)} -> #NAME? | E41: {=Notmerged(E12)} -> #NAME? | F41: {=Notmerged(F12)} -> #NAME? | G41: {=Notmerged(G12)} -> #NAME? | H41: {=Notmerged(H12)} -> #NAME? | I41: {=Notmerged(I12)} -> #NAME? | ... BK41: {=Notmerged(BK12)} -> #NAME?
B42: {=Notmerged(B13)} -> #NAME? | C42: {=Notmerged(C13)} -> #NAME? | D42: {=Notmerged(D13)} -> #NAME? | E42: {=Notmerged(E13)} -> #NAME? | F42: {=Notmerged(F13)} -> #NAME? | G42: {=Notmerged(G13)} -> #NAME? | H42: {=Notmerged(H13)} -> #NAME? | I42: {=Notmerged(I13)} -> #NAME? | ... BK42: {=Notmerged(BK13)} -> #NAME?
B43: {=Notmerged(B14)} -> #NAME? | C43: {=Notmerged(C15)} -> #NAME? | D43: {=Notmerged(D14)} -> #NAME? | E43: {=Notmerged(E14)} -> #NAME? | F43: {=Notmerged(F14)} -> #NAME? | G43: {=Notmerged(G14)} -> #NAME? | H43: {=Notmerged(H14)} -> #NAME? | I43: {=Notmerged(I14)} -> #NAME? | J43: {=Notmerged(J14)} -> #NAME? | K43: {=Notmerged(K14)} -> #NAME? | ... BK43: {=Notmerged(BK14)} -> #NAME?
B44: {=Notmerged(B15)} -> #NAME? | C44: {=Notmerged(#REF!)} -> #NAME? | D44: {=Notmerged(D15)} -> #NAME? | E44: {=Notmerged(E15)} -> #NAME? | F44: {=Notmerged(F15)} -> #NAME? | G44: {=Notmerged(G15)} -> #NAME? | H44: {=Notmerged(H15)} -> #NAME? | I44: {=Notmerged(I15)} -> #NAME? | J44: {=Notmerged(J15)} -> #NAME? | K44: {=Notmerged(K15)} -> #NAME? | ... BK44: {=Notmerged(BK15)} -> #NAME?
B45: {=Notmerged(B16)} -> #NAME? | C45: {=Notmerged(C16)} -> #NAME? | D45: {=Notmerged(D16)} -> #NAME? | E45: {=Notmerged(E16)} -> #NAME? | F45: {=Notmerged(F16)} -> #NAME? | G45: {=Notmerged(G16)} -> #NAME? | H45: {=Notmerged(H16)} -> #NAME? | I45: {=Notmerged(I16)} -> #NAME? | ... BK45: {=Notmerged(BK16)} -> #NAME?
B46: {=Notmerged(B17)} -> #NAME? | C46: {=Notmerged(C17)} -> #NAME? | D46: {=Notmerged(D17)} -> #NAME? | E46: {=Notmerged(E17)} -> #NAME? | F46: {=Notmerged(F17)} -> #NAME? | G46: {=Notmerged(G17)} -> #NAME? | H46: {=Notmerged(H17)} -> #NAME? | I46: {=Notmerged(I17)} -> #NAME? | ... BK46: {=Notmerged(BK17)} -> #NAME?
B47: {=Notmerged(B18)} -> #NAME? | C47: {=Notmerged(C18)} -> #NAME? | D47: {=Notmerged(D18)} -> #NAME? | E47: {=Notmerged(E18)} -> #NAME? | F47: {=Notmerged(F18)} -> #NAME? | G47: {=Notmerged(G18)} -> #NAME? | H47: {=Notmerged(H18)} -> #NAME? | I47: {=Notmerged(I18)} -> #NAME? | ... BK47: {=Notmerged(BK18)} -> #NAME?
B48: {=Notmerged(B19)} -> #NAME? | C48: {=Notmerged(C19)} -> #NAME? | D48: {=Notmerged(D19)} -> #NAME? | E48: {=Notmerged(E19)} -> #NAME? | F48: {=Notmerged(F19)} -> #NAME? | G48: {=Notmerged(G19)} -> #NAME? | H48: {=Notmerged(H19)} -> #NAME? | I48: {=Notmerged(I19)} -> #NAME? | ... BK48: {=Notmerged(BK19)} -> #NAME?
B49: {=Notmerged(B20)} -> #NAME? | C49: {=Notmerged(C20)} -> #NAME? | D49: {=Notmerged(D20)} -> #NAME? | E49: {=Notmerged(E20)} -> #NAME? | F49: {=Notmerged(F20)} -> #NAME? | G49: {=Notmerged(G20)} -> #NAME? | H49: {=Notmerged(H20)} -> #NAME? | I49: {=Notmerged(I20)} -> #NAME? | ... BK49: {=Notmerged(BK20)} -> #NAME?
B50: {=Notmerged(B21)} -> #NAME? | C50: {=Notmerged(C21)} -> #NAME? | D50: {=Notmerged(D21)} -> #NAME? | E50: {=Notmerged(E21)} -> #NAME? | F50: {=Notmerged(F21)} -> #NAME? | G50: {=Notmerged(G21)} -> #NAME? | H50: {=Notmerged(H21)} -> #NAME? | I50: {=Notmerged(I21)} -> #NAME? | ... BK50: {=Notmerged(BK21)} -> #NAME?
B51: {=Notmerged(#REF!)} -> #NAME? | C51: {=Notmerged(C22)} -> #NAME? | D51: {=Notmerged(D22)} -> #NAME? | E51: {=Notmerged(E22)} -> #NAME? | F51: {=Notmerged(F22)} -> #NAME? | G51: {=Notmerged(G22)} -> #NAME? | H51: {=Notmerged(H22)} -> #NAME? | I51: {=Notmerged(I22)} -> #NAME? | J51: {=Notmerged(J22)} -> #NAME? | ... BK51: {=Notmerged(BK22)} -> #NAME?
B52: {=Notmerged(B23)} -> #NAME? | C52: {=Notmerged(#REF!)} -> #NAME? | D52: {=Notmerged(D23)} -> #NAME? | E52: {=Notmerged(E23)} -> #NAME? | F52: {=Notmerged(F23)} -> #NAME? | G52: {=Notmerged(G23)} -> #NAME? | H52: {=Notmerged(H23)} -> #NAME? | I52: {=Notmerged(I23)} -> #NAME? | J52: {=Notmerged(J23)} -> #NAME? | K52: {=Notmerged(K23)} -> #NAME? | ... BK52: {=Notmerged(BK23)} -> #NAME?
B53: {=Notmerged(B22)} -> #NAME? | C53: {=Notmerged(C23)} -> #NAME? | D53: {=Notmerged(D24)} -> #NAME? | E53: {=Notmerged(E24)} -> #NAME? | F53: {=Notmerged(F24)} -> #NAME? | G53: {=Notmerged(G24)} -> #NAME? | H53: {=Notmerged(H24)} -> #NAME? | I53: {=Notmerged(I24)} -> #NAME? | J53: {=Notmerged(J24)} -> #NAME? | K53: {=Notmerged(K24)} -> #NAME? | ... BK53: {=Notmerged(BK24)} -> #NAME?
B54: {=Notmerged(#REF!)} -> #NAME? | C54: {=Notmerged(C25)} -> #NAME? | D54: {=Notmerged(D25)} -> #NAME? | E54: {=Notmerged(E25)} -> #NAME? | F54: {=Notmerged(F25)} -> #NAME? | G54: {=Notmerged(G25)} -> #NAME? | H54: {=Notmerged(H25)} -> #NAME? | I54: {=Notmerged(I25)} -> #NAME? | J54: {=Notmerged(J25)} -> #NAME? | ... BK54: {=Notmerged(BK25)} -> #NAME?
B55: {=Notmerged(B26)} -> #NAME? | C55: {=Notmerged(C26)} -> #NAME? | D55: {=Notmerged(D26)} -> #NAME? | E55: {=Notmerged(E26)} -> #NAME? | F55: {=Notmerged(F26)} -> #NAME? | G55: {=Notmerged(G26)} -> #NAME? | H55: {=Notmerged(H26)} -> #NAME? | I55: {=Notmerged(I26)} -> #NAME? | ... BK55: {=Notmerged(BK26)} -> #NAME?
B56: {=Notmerged(B25)} -> #NAME? | C56: {=Notmerged(C27)} -> #NAME? | D56: {=Notmerged(D27)} -> #NAME? | E56: {=Notmerged(E27)} -> #NAME? | F56: {=Notmerged(F27)} -> #NAME? | G56: {=Notmerged(G27)} -> #NAME? | H56: {=Notmerged(H27)} -> #NAME? | I56: {=Notmerged(I27)} -> #NAME? | J56: {=Notmerged(J27)} -> #NAME? | ... BK56: {=Notmerged(BK27)} -> #NAME?
B57: {=Notmerged(B28)} -> #NAME? | C57: {=Notmerged(C28)} -> #NAME? | D57: {=Notmerged(D28)} -> #NAME? | E57: {=Notmerged(E28)} -> #NAME? | F57: {=Notmerged(F28)} -> #NAME? | G57: {=Notmerged(G28)} -> #NAME? | H57: {=Notmerged(H28)} -> #NAME? | I57: {=Notmerged(I28)} -> #NAME? | ... BK57: {=Notmerged(BK28)} -> #NAME?
B58: {=Notmerged(B29)} -> #NAME? | C58: {=Notmerged(C29)} -> #NAME? | D58: {=Notmerged(D29)} -> #NAME? | E58: {=Notmerged(E29)} -> #NAME? | F58: {=Notmerged(F29)} -> #NAME? | G58: {=Notmerged(G29)} -> #NAME? | H58: {=Notmerged(H29)} -> #NAME? | I58: {=Notmerged(I29)} -> #NAME? | ... BK58: {=Notmerged(BK29)} -> #NAME?
B59: {=Notmerged(B30)} -> #NAME? | C59: {=Notmerged(C30)} -> #NAME? | D59: {=Notmerged(D30)} -> #NAME? | E59: {=Notmerged(E30)} -> #NAME? | F59: {=Notmerged(F30)} -> #NAME? | G59: {=Notmerged(G30)} -> #NAME? | H59: {=Notmerged(H30)} -> #NAME? | I59: {=Notmerged(I30)} -> #NAME? | ... BK59: {=Notmerged(BK30)} -> #NAME?
B60: {=Notmerged(B31)} -> #NAME? | C60: {=Notmerged(C31)} -> #NAME? | D60: {=Notmerged(D31)} -> #NAME? | E60: {=Notmerged(E31)} -> #NAME? | F60: {=Notmerged(F31)} -> #NAME? | G60: {=Notmerged(G31)} -> #NAME? | H60: {=Notmerged(H31)} -> #NAME? | I60: {=Notmerged(I31)} -> #NAME? | ... BK60: {=Notmerged(BK31)} -> #NAME?

Sheet WEDNESDAY
A2: WEDNESDAY
A3: TIME | B3: SAMPLE | C3: =MONDAY!C3 -> 201 | D3: =MONDAY!D3 -> 202 | E3: =MONDAY!E3 -> 203 | F3: =MONDAY!F3 -> 204 | G3: =MONDAY!G3 -> 205 | H3: =MONDAY!H3 -> 206 | I3: =MONDAY!I3 -> 207 | J3: =MONDAY!J3 -> 212 | ... BK3: =MONDAY!BK3 -> <Lab>
A4: 7:00 - 7:30 AM | B4: <SUBJECT> <SECTION> <INSTRUCTOR> | C4: VACANT | D4: VACANT | E4: The Contemporary World BMA101 SOC SCI FT3 | F4: VACANT | G4: Statistical Analysis with Software Application LECTURE BSA501 RM 205 | H4: Mathematics in the Modern World TM101 BURGOS | I4: Great Books BSA301 ENGLISH FT | J4: Basic Accounting BSA101 RM 212 | K4: Multicultural Diversity in Workplace for the Tourism Professional BH501 | L4: Philippine Popular Culture BT102 CAGADO | M4: VACANT | N4: Risk Management as Applied to Safety, Security, and Sanitation BH103 | O4: Macro Perspective of Tourism and Hospitality BH102 | P4: Understanding the Self BS101 REFUERZO | Q4: Risk Management as Applied to Safety, Security, and Sanitation TM104 | R4: The Contemporary World BT103 MAGABILIN | S4: Mathematics in the Modern World BH104 MATH FT | T4: The Entrepreneurial Mind TM501 SAN DIEGO | U4: Physical Science GAS201 FRANK | V4: Organization and Management ABM101 | W4: Introduction to the Philosophy of Human ABM102 | X4: General Mathematics HUMSS103 | Y4: Introduction to Culinary Operations CULART101 | Z4: Oral Communication CULART102 | AA4: Introduction to Travel & Tour Industy TOP101 | AB4: The Entrepreneurial Mind BMA302 ESPIRITU | AC4: Introduction to the Philosophy of Human HUMSS102 | AD4: VACANT | AE4: General Mathematics IT102 | AF4: 21st Century Literature IT103 | AG4: Drawing 1 LAB BMA102 BARRIENTOS | AH4: Pre-Calculus STEM101 | AI4: 21st Century Literature STEM102 | AJ4: Media and Information Literacy STEM103 | AK4: Oral Communication STEM104 | AL4: 21st Century Literature STEM105 | AM4: General Biology 1 STEM106 | AN4: Introduction to the Philosophy of Human STEM107 | AO4: 21st Century Literature STEM108 | AU4: VACANT | AV4: VACANT | AW4: Color Theory LAB BMA301 BMA FT1 | AX4: Application Development and Emerging Technologies LAB BS501 CIFRA | AY4: Advanced Systems Integration and Architecture LAB BT504 FELICEN | AZ4: Multimedia Seminars LAB BMA703 BAUTISTA | BA4: VACANT | BB4: General Biology 1 STEM109 | BC4: General Chemistry 1 STEM208 | BD4: Fundamentals of Electrical Circuits LAB COE301 BERTUBIN | BE4: VACANT | BF4: NO CLASS | BG4: NO CLASS | BH4: Tour and Travel Management TM302
A5: 7:30 - 8:00 AM | C5: VACANT | D5: VACANT | F5: VACANT | M5: VACANT | AD5: VACANT | AU5: VACANT | AV5: VACANT | BA5: VACANT | BE5: VACANT
A6: 8:00 - 8:30 AM | C6: Computer Programming 1 LEC BT105 RESULLAR | D6: Data Structures and Algorithms LEC BT302 DOMINGUEZ | F6: VACANT | M6: VACANT | AD6: VACANT | AU6: VACANT | AV6: VACANT | BA6: VACANT | BE6: VACANT
A7: 8:30 - 9:00 AM | B7: <SUBJECT> <SECTION> <INSTRUCTOR> | F7: Practical Research 2 STEM207 | M7: Physical Science TOP202 RM505 | AD7: Pagbasa at Pagsusuri IT202 | AU7: Computer Engineering as a Discipline COE101 COE FT1 | AV7: VACANT | BA7: VACANT | BE7: VACANT
A8: 9:00 - 9:30 AM | G8: Drawing 1 LEC BMA104 MANALO | AV8: VACANT | BA8: VACANT | BE8: VACANT
A9: 9:30 - 10:00 AM | AU9: VACANT | AV9: VACANT | BA9: VACANT | BE9: VACANT
A10: 10:00 - 10:30 AM | B10: <SUBJECT> <SECTION> <INSTRUCTOR> | C10: Computer Programming 1 LEC BT104 IT FT1 | D10: Human-Computer Interaction LEC BT304 MORAL | E10: Color Theory LEC BMA301 BMA FT1 | G10: Application Development and Emerging Technologies LEC BT504 AGUILA | I10: Fil sa Piling Larang (Akad) DIGI201 | L10: Euthenics 1 TM101 SOC SCI FT3 | N10: Euthenics 1 BH102 MATH FT | P10: VACANT | Q10: Rizal's Life and Works BH701 BUSTALINIO | R10: VACANT | S10: Fundamentals of Electrical Circuits LEC COE301 BERTUBIN | T10: Introduction to Commercial Cookery CULART202 | U10: VACANT | V10: VACANT | W10: Business Finance ABM203 | X10: VACANT | Y10: VACANT | Z10: VACANT | AA10: Creative Nonfiction HUMSS201 | AB10: Introduction to Commercial Cookery CULART202 | AC10: VACANT | AE10: VACANT | AF10: VACANT | AG10: Drawing 1 LAB BMA104 MANALO | AH10: VACANT | AI10: VACANT | AJ10: VACANT | AK10: VACANT | AL10: VACANT | AM10: VACANT | AN10: VACANT | AO10: VACANT | AU10: Application Development and Emerging Technologies BS501 CIFRA | AV10: Embedded Systems LEC RM MO2 LLENO | AW10: Digital Photography LAB BMA503 BARRIENTOS | AX10: Introduction to Computing LAB BS101 IT FT1 | AY10: Data Structures and Algorithms LAB BT303 FELICEN | AZ10: Computer Programming 1 LAB BT105 RESULLAR | BA10: Data Structures and Algorithms LAB BT302 DOMINGUEZ | BB10: VACANT | BC10: General Physics 1 STEM206 | BD10: VACANT | BE10: VACANT | BH10: Tour and Travel Management TM303
A11: 10:30 - 11:00 AM | J11: Tourism and Hospitality Marketing BH502 | K11: Euthenics 1 BT103 MAGABILIN | O11: Macro Perspective of Tourism and Hospitality BH103 | P11: Operations Management (TQM) TM501 MANALANG | R11: Understanding the Self BT102 BAGOL | U11: The Entrepreneurial Mind BH501 MATEO | V11: VACANT | X11: Euthenics 2 BT702 CAGADO | Y11: VACANT | Z11: VACANT | AC11: VACANT | AE11: VACANT | AF11: VACANT | AH11: VACANT | AI11: VACANT | AJ11: VACANT | AK11: VACANT | AL11: VACANT | AM11: VACANT | AN11: VACANT | AO11: VACANT | BB11: Physical Science ABM202 | BD11: VACANT | BE11: VACANT
A12: 11:00 - 11:30 AM | L12: Great Books TM502 ENGLISH FT | V12: VACANT | Y12: VACANT | Z12: VACANT | AC12: VACANT | AE12: VACANT | AF12: VACANT | AH12: VACANT | AI12: VACANT | AJ12: VACANT | AK12: VACANT | AL12: VACANT | AM12: VACANT | AN12: VACANT | AO12: VACANT | BD12: VACANT | BE12: VACANT
A13: 11:30 - 12:00 PM | B13: <SUBJECT> <SECTION> <INSTRUCTOR> | F13: English for Academic & Prof STEM208 | H13: The Entrepreneurial Mind BS301 ESPIRITU | K13: Mathematics in the Modern World BSA301 MATH FT | M13: Organization & Management ABM103 | N13: Euthenics 2 BS701 CAGADO | V13: Media and Information Literacy ABM101 | X13: Organization & Management ABM103 | Y13: Intro to World Rel & BS HUMSS103 | Z13: Introduction to Culinary Operations CULART102 | AC13: Media and Information Literacy HUMSS102 | AD13: Introduction to the Philosophy of Human IT101 | AE13: Introduction to the Philosophy of Human TOP101 | AF13: General Mathematics IT103 | AH13: 21st Century Literature STEM101 | AI13: Pre-Calculus STEM102 | AJ13: Oral Communication STEM103 | AK13: 21st Century Literature STEM104 | AL13: Oral Communication STEM105 | AM13: Introduction to the Philosophy of Human STEM106 | AN13: Media and Information Literacy STEM107 | AO13: Introduction to the Philosophy of Human STEM108 | AX13: VACANT | BD13: General Biology 1 STEM108 | BE13: Introduction to Culinary Operations CULART102
A14: 12:00 - 12:30 PM | C14: VACANT | D14: Network Technology 2 LEC BT702 IT FT3 | E14: Multimedia Seminars LEC COE703 BAUTISTA | G14: IT Elective 4: Game Development LEC BT701 RESULLAR | S14: Rizal's Life and Works BMA304 REFUERZO | AU14: VACANT | AX14: VACANT
A15: 12:30 - 1:00 PM | C15: VACANT | N15: Risk Management as Applied to Safety, Security, and Sanitation BH102 | AU15: VACANT | AX15: VACANT
A16: 1:00 - 1:30 PM | B16: VACANT | C16: Philippine Popular Culture BT103 CAGADO | I16: Business Ventures in Multimedia BMA501 BARRIENTOS | Q16: VACANT | T16: Great Books BA502 BONCAN | W16: VACANT | AA16: VACANT | AB16: Introduction to the Philosophy of Human STEM109 | AG16: Engineering Economics COE501 BERTUBIN | AU16: Professional Issues in Information Systems and Technology BS701 MORAL | AV16: VACANT | AW16: Color Theory LAB BMA303 BMA FT1 | AX16: IT Elective 1: Object-Oriented Programming LAB BT304 GAID | AY16: Event-Driven Programming LAB BT501 DOMONDON | AZ16: Application Development and Emerging Technologies LAB BT501 CIFRA | BA16: Network Technology 2 LAB BT703 IT FT3 | BC16: VACANT | BH16: Hotel Front Office Operations Management BH302
A17: 1:30 - 2:00 PM | J17: VACANT | O17: Good Governance & Social Responsibility BAOM501 RM 302 ATTY. PT | P17: NO CLASS | Q17: VACANT | R17: VACANT | U17: VACANT | W17: VACANT | AA17: VACANT | AV17: VACANT | BB17: VACANT | BC17: VACANT
A18: 2:00 - 2:30 PM | D18: MMA Elective 2: Brand Communication and Design LEC BMA502 MANALO | E18: VACANT | G18: MMA Free Elective 1: Web Programming LEC BMA503 DOMINGUEZ | J18: IT Elective 2: Introduction to Computer Animation LEC BT503 IT FT2 | Q18: Rizal's Life and Works TM701 BUSTALINIO | R18: VACANT | U18: VACANT | W18: VACANT | AA18: VACANT | AV18: CpE Elective 3: Robot Assembly and Programming COE 701 COE FT1 | BB18: VACANT | BC18: VACANT
A19: 2:30 - 3:00 PM | B19: <SUBJECT> <SECTION> <INSTRUCTOR> | E19: The Entrepreneurial Mind TM502 MATEO | F19: Practical Research 2 STEM203 | H19: Readings in Philippine History BMA104 SOC SCI FT3 | K19: Understanding the Self BT105 MAGABILIN | L19: Readings in Philippine History BT303 CONDINO | M19: Economic Development BSA501 RM 303 SAN DIEGO | R19: VACANT | U19: Understanding the Self BT104 BAGOL | V19: Physical Science ABM201 | W19: Business Finance ABM202 | X19: NO CLASS | Y19: English for Academic and Professional Purposes STEM207 | Z19: Rizal's Life and Works BH702 SOC SCI FT2 | AA19: Personal Development TOP202 | AC19: VACANT | AD19: Great Books TM501 ENGLISH FT | AE19: Practical Research 2 IT203 | AF19: Creative Nonfiction HUMSS202 | AH19: Pagbasa at Pagsusuri STEM205 | AI19: Practical Research 2 STEM202 | AJ19: Practical Research 2 IT201 | AK19: Practical Research 2 STEM201 | AL19: Personal Development GAS201 | AM19: Practical Research 2 TOP201 | AN19: Quality Service Management in Tourism and Hospitality BH303 CELESTINO | AO19: Filipino sa Piling Larang STEM204 | BB19: Physical Science ABM203 | BC19: Chemistry for Engineers LAB COE101 | BD19: Physical Science CULART202 | BE19: NO CLASS
A20: 3:00 - 3:30 PM | R20: Quantitative Methods (Data Analysis) BS501 MATH FT | S20: Multicultural Diversity in Workplace for the Tourism Professional BH502 | AC20: VACANT
A21: 3:30 - 4:00 PM | N21: The Entrepreneurial Mind BMA304 MANALANG | AC21: Readings in Philippine History BS301 REFUERZO
